Workbook

Sheet 00_Read_Me
A1: MWG FP&A Showcase — Monthly Reporting, Variance & Rolling Forecast | B1: MWG FP&A Showcase — Monthly Reporting, Variance & Rolling Forecast | C1: MWG FP&A Showcase — Monthly Reporting, Variance & Rolling Forecast | D1: MWG FP&A Showcase — Monthly Reporting, Variance & Rolling Forecast | E1: MWG FP&A Showcase — Monthly Reporting, Variance & Rolling Forecast | F1: MWG FP&A Showcase — Monthly Reporting, Variance & Rolling Forecast | G1: MWG FP&A Showcase — Monthly Reporting, Variance & Rolling Forecast | H1: MWG FP&A Showcase — Monthly Reporting, Variance & Rolling Forecast | I1: MWG FP&A Showcase — Monthly Reporting, Variance & Rolling Forecast | J1: MWG FP&A Showcase — Monthly Reporting, Variance & Rolling Forecast
A2: CV work sample | FY2024/FY2025 actuals tie to audited filings; Budget and Forecast are analyst-prepared and clearly labelled. | B2: CV work sample | FY2024/FY2025 actuals tie to audited filings; Budget and Forecast are analyst-prepared and clearly labelled. | C2: CV work sample | FY2024/FY2025 actuals tie to audited filings; Budget and Forecast are analyst-prepared and clearly labelled. | D2: CV work sample | FY2024/FY2025 actuals tie to audited filings; Budget and Forecast are analyst-prepared and clearly labelled. | E2: CV work sample | FY2024/FY2025 actuals tie to audited filings; Budget and Forecast are analyst-prepared and clearly labelled. | F2: CV work sample | FY2024/FY2025 actuals tie to audited filings; Budget and Forecast are analyst-prepared and clearly labelled. | G2: CV work sample | FY2024/FY2025 actuals tie to audited filings; Budget and Forecast are analyst-prepared and clearly labelled. | H2: CV work sample | FY2024/FY2025 actuals tie to audited filings; Budget and Forecast are analyst-prepared and clearly labelled. | I2: CV work sample | FY2024/FY2025 actuals tie to audited filings; Budget and Forecast are analyst-prepared and clearly labelled. | J2: CV work sample | FY2024/FY2025 actuals tie to audited filings; Budget and Forecast are analyst-prepared and clearly labelled.
A4: Workbook purpose and scope | B4: Workbook purpose and scope | C4: Workbook purpose and scope | D4: Workbook purpose and scope | E4: Workbook purpose and scope | F4: Workbook purpose and scope | G4: Workbook purpose and scope | H4: Workbook purpose and scope | I4: Workbook purpose and scope | J4: Workbook purpose and scope
A5: Purpose | B5: Demonstrate Excel / FP&A skills using public MWG disclosures: monthly reporting, budget variance, forecast, working capital, dashboard and controls.
A6: Core management question | B6: Did FY2025 beat plan, which business units drove the variance, and what H2 growth is required for FY2026 guidance?
A7: Actual period | B7: FY2024 and FY2025 actual P&L; 6M2026 reported revenue.
A8: Budget period | B8: FY2025 and FY2026 analyst-prepared monthly budgets calibrated to MWG official revenue and PAT targets.
A9: Forecast period | B9: FY2026 rolling forecast as of Jun-2026 with Base / Bull / Bear scenario selector.
A10: Units | B10: VND bn unless stated otherwise.
A11: Data limitation | B11: MWG does not publish a monthly cost-center ledger or segment P&L. Quarterly expenses are allocated to months and BUs by revenue; do not present allocated BU margins as company-reported.
A12: Refresh layer | B12: Queries reference workbook input tables; outputs remain formula-driven even if Power Query is not refreshed.
A13: Owner / version | B13: Le Hoang Nghia | v1.2 | 28 Jul 2026
A15: How to use | B15: How to use | C15: How to use | D15: How to use | E15: How to use | F15: How to use | G15: How to use | H15: How to use | I15: How to use | J15: How to use
A16: 1) Refresh or replace the two raw input tables. 2) Review account and BU mappings. 3) Read Monthly P&L, YoY Analysis and Variance Analysis. 4) Change the scenario in Rolling Forecast cell B3. 5) Review Forecast vs Budget and working-capital assumptions. 6) Confirm MODEL STATUS = PASS before sharing. 7) Use the PivotTable on Variance Analysis to filter Revenue / Opex by BU and version.
A22: Financial-model color legend | B22: Financial-model color legend | C22: Financial-model color legend | D22: Financial-model color legend | E22: Financial-model color legend | F22: Financial-model color legend | G22: Financial-model color legend | H22: Financial-model color legend | I22: Financial-model color legend | J22: Financial-model color legend
A23: Blue font | B23: Editable assumptions / scenario inputs
A24: Green font | B24: Formula linked to another worksheet
A25: Black font | B25: Formula or calculation on the same worksheet
A26: Yellow fill | B26: Key assumption / limitation requiring attention
A27: Green or red fill | B27: Control status or favorable / unfavorable output
A29: Model status | B29: Model status | C29: Model status | D29: Model status | E29: Model status | F29: Model status | G29: Model status | H29: Model status | I29: Model status | J29: Model status
A30: MODEL STATUS | B30: ='10_Checks'!B2 -> PASS
A31: Checks passed | B31: =COUNTIF('10_Checks'!F6:F21,"PASS") -> 16
A32: Checks failed | B32: =COUNTIF('10_Checks'!F6:F21,"FAIL") -> 0
A34: Learning mode (optional; does not affect the core model) | B34: Learning mode (optional; does not affect the core model) | C34: Learning mode (optional; does not affect the core model) | D34: Learning mode (optional; does not affect the core model) | E34: Learning mode (optional; does not affect the core model) | F34: Learning mode (optional; does not affect the core model) | G34: Learning mode (optional; does not affect the core model) | H34: Learning mode (optional; does not affect the core model) | I34: Learning mode (optional; does not affect the core model) | J34: Learning mode (optional; does not affect the core model)
A35: Use 14_Formula_Guide to understand the logic and formula patterns used across the workbook. Then complete the blue/yellow formula cells in 15_Practice_Lab and use the automatic status column to check your work. Open 16_Answer_Key only after attempting the exercises. Practice formulas are isolated and do not feed the management reports or model checks.

Sheet 01_Raw_Actual
A1: Actual input table — FY2024/FY2025 audited P&L and 6M2026 reported revenue | B1: Actual input table — FY2024/FY2025 audited P&L and 6M2026 reported revenue | C1: Actual input table — FY2024/FY2025 audited P&L and 6M2026 reported revenue | D1: Actual input table — FY2024/FY2025 audited P&L and 6M2026 reported revenue | E1: Actual input table — FY2024/FY2025 audited P&L and 6M2026 reported revenue | F1: Actual input table — FY2024/FY2025 audited P&L and 6M2026 reported revenue | G1: Actual input table — FY2024/FY2025 audited P&L and 6M2026 reported revenue | H1: Actual input table — FY2024/FY2025 audited P&L and 6M2026 reported revenue | I1: Actual input table — FY2024/FY2025 audited P&L and 6M2026 reported revenue | J1: Actual input table — FY2024/FY2025 audited P&L and 6M2026 reported revenue | K1: Actual input table — FY2024/FY2025 audited P&L and 6M2026 reported revenue
A2: Green formula columns use XLOOKUP against 04_Account_Mapping. Input values are intentionally separate from report outputs. | B2: Green formula columns use XLOOKUP against 04_Account_Mapping. Input values are intentionally separate from report outputs. | C2: Green formula columns use XLOOKUP against 04_Account_Mapping. Input values are intentionally separate from report outputs. | D2: Green formula columns use XLOOKUP against 04_Account_Mapping. Input values are intentionally separate from report outputs. | E2: Green formula columns use XLOOKUP against 04_Account_Mapping. Input values are intentionally separate from report outputs. | F2: Green formula columns use XLOOKUP against 04_Account_Mapping. Input values are intentionally separate from report outputs. | G2: Green formula columns use XLOOKUP against 04_Account_Mapping. Input values are intentionally separate from report outputs. | H2: Green formula columns use XLOOKUP against 04_Account_Mapping. Input values are intentionally separate from report outputs. | I2: Green formula columns use XLOOKUP against 04_Account_Mapping. Input values are intentionally separate from report outputs. | J2: Green formula columns use XLOOKUP against 04_Account_Mapping. Input values are intentionally separate from report outputs. | K2: Green formula columns use XLOOKUP against 04_Account_Mapping. Input values are intentionally separate from report outputs.
A5: Period | B5: Year | C5: Month | D5: BusinessUnit | E5: CostCenter | F5: AccountCode | G5: Amount_VNDm | H5: EvidenceClass | I5: SourceID | J5: MappedCategory | K5: CostNature
A6: 45292 | B6: 2024 | C6: 1 | D6: Group | E6: CC_GROUP | F6: REV | G6: 10806.512 | H6: Reported monthly revenue; scaled to audited FY2024 revenue | I6: SRC-005 | J6: =_xlfn.XLOOKUP(F6,'04_Account_Mapping'!$A$6:$A$14,'04_Account_Mapping'!$C$6:$C$14,"Unmapped",0) -> Revenue | K6: =_xlfn.XLOOKUP(F6,'04_Account_Mapping'!$A$6:$A$14,'04_Account_Mapping'!$D$6:$D$14,"Unmapped",0) -> Income
A7: 45292 | B7: 2024 | C7: 1 | D7: Group | E7: CC_GROUP | F7: COGS | G7: -8594.4533 | H7: Audited FY2024 account allocated monthly by reported revenue | I7: SRC-005 | J7: =_xlfn.XLOOKUP(F7,'04_Account_Mapping'!$A$6:$A$14,'04_Account_Mapping'!$C$6:$C$14,"Unmapped",0) -> COGS | K7: =_xlfn.XLOOKUP(F7,'04_Account_Mapping'!$A$6:$A$14,'04_Account_Mapping'!$D$6:$D$14,"Unmapped",0) -> Expense
A8: 45292 | B8: 2024 | C8: 1 | D8: Group | E8: CC_GROUP | F8: SELL | G8: -1596.7372 | H8: Audited FY2024 account allocated monthly by reported revenue | I8: SRC-005 | J8: =_xlfn.XLOOKUP(F8,'04_Account_Mapping'!$A$6:$A$14,'04_Account_Mapping'!$C$6:$C$14,"Unmapped",0) -> Selling Expense | K8: =_xlfn.XLOOKUP(F8,'04_Account_Mapping'!$A$6:$A$14,'04_Account_Mapping'!$D$6:$D$14,"Unmapped",0) -> Expense
A9: 45292 | B9: 2024 | C9: 1 | D9: Group | E9: CC_GROUP | F9: GA | G9: -286.83326 | H9: Audited FY2024 account allocated monthly by reported revenue | I9: SRC-005 | J9: =_xlfn.XLOOKUP(F9,'04_Account_Mapping'!$A$6:$A$14,'04_Account_Mapping'!$C$6:$C$14,"Unmapped",0) -> G&A | K9: =_xlfn.XLOOKUP(F9,'04_Account_Mapping'!$A$6:$A$14,'04_Account_Mapping'!$D$6:$D$14,"Unmapped",0) -> Expense
A10: 45292 | B10: 2024 | C10: 1 | D10: Group | E10: CC_GROUP | F10: FIN_INC | G10: 191.16781 | H10: Audited FY2024 account allocated monthly by reported revenue | I10: SRC-005 | J10: =_xlfn.XLOOKUP(F10,'04_Account_Mapping'!$A$6:$A$14,'04_Account_Mapping'!$C$6:$C$14,"Unmapped",0) -> Finance Income | K10: =_xlfn.XLOOKUP(F10,'04_Account_Mapping'!$A$6:$A$14,'04_Account_Mapping'!$D$6:$D$14,"Unmapped",0) -> Income
A11: 45292 | B11: 2024 | C11: 1 | D11: Group | E11: CC_GROUP | F11: FIN_EXP | G11: -95.601146 | H11: Audited FY2024 account allocated monthly by reported revenue | I11: SRC-005 | J11: =_xlfn.XLOOKUP(F11,'04_Account_Mapping'!$A$6:$A$14,'04_Account_Mapping'!$C$6:$C$14,"Unmapped",0) -> Finance Expense | K11: =_xlfn.XLOOKUP(F11,'04_Account_Mapping'!$A$6:$A$14,'04_Account_Mapping'!$D$6:$D$14,"Unmapped",0) -> Expense
A12: 45292 | B12: 2024 | C12: 1 | D12: Group | E12: CC_GROUP | F12: JV | G12: -3.5873753 | H12: Audited FY2024 account allocated monthly by reported revenue | I12: SRC-005 | J12: =_xlfn.XLOOKUP(F12,'04_Account_Mapping'!$A$6:$A$14,'04_Account_Mapping'!$C$6:$C$14,"Unmapped",0) -> JV Profit/(Loss) | K12: =_xlfn.XLOOKUP(F12,'04_Account_Mapping'!$A$6:$A$14,'04_Account_Mapping'!$D$6:$D$14,"Unmapped",0) -> Income
A13: 45292 | B13: 2024 | C13: 1 | D13: Group | E13: CC_GROUP | F13: OTHER | G13: -32.279486 | H13: Audited FY2024 account allocated monthly by reported revenue | I13: SRC-005 | J13: =_xlfn.XLOOKUP(F13,'04_Account_Mapping'!$A$6:$A$14,'04_Account_Mapping'!$C$6:$C$14,"Unmapped",0) -> Other Net | K13: =_xlfn.XLOOKUP(F13,'04_Account_Mapping'!$A$6:$A$14,'04_Account_Mapping'!$D$6:$D$14,"Unmapped",0) -> Income
A14: 45292 | B14: 2024 | C14: 1 | D14: Group | E14: CC_GROUP | F14: TAX | G14: -87.879566 | H14: Audited FY2024 account allocated monthly by reported revenue | I14: SRC-005 | J14: =_xlfn.XLOOKUP(F14,'04_Account_Mapping'!$A$6:$A$14,'04_Account_Mapping'!$C$6:$C$14,"Unmapped",0) -> Tax Expense | K14: =_xlfn.XLOOKUP(F14,'04_Account_Mapping'!$A$6:$A$14,'04_Account_Mapping'!$D$6:$D$14,"Unmapped",0) -> Expense
A15: 45323 | B15: 2024 | C15: 2 | D15: Group | E15: CC_GROUP | F15: REV | G15: 10806.512 | H15: Reported monthly revenue; scaled to audited FY2024 revenue | I15: SRC-005 | J15: =_xlfn.XLOOKUP(F15,'04_Account_Mapping'!$A$6:$A$14,'04_Account_Mapping'!$C$6:$C$14,"Unmapped",0) -> Revenue | K15: =_xlfn.XLOOKUP(F15,'04_Account_Mapping'!$A$6:$A$14,'04_Account_Mapping'!$D$6:$D$14,"Unmapped",0) -> Income
A16: 45323 | B16: 2024 | C16: 2 | D16: Group | E16: CC_GROUP | F16: COGS | G16: -8594.4533 | H16: Audited FY2024 account allocated monthly by reported revenue | I16: SRC-005 | J16: =_xlfn.XLOOKUP(F16,'04_Account_Mapping'!$A$6:$A$14,'04_Account_Mapping'!$C$6:$C$14,"Unmapped",0) -> COGS | K16: =_xlfn.XLOOKUP(F16,'04_Account_Mapping'!$A$6:$A$14,'04_Account_Mapping'!$D$6:$D$14,"Unmapped",0) -> Expense
A17: 45323 | B17: 2024 | C17: 2 | D17: Group | E17: CC_GROUP | F17: SELL | G17: -1596.7372 | H17: Audited FY2024 account allocated monthly by reported revenue | I17: SRC-005 | J17: =_xlfn.XLOOKUP(F17,'04_Account_Mapping'!$A$6:$A$14,'04_Account_Mapping'!$C$6:$C$14,"Unmapped",0) -> Selling Expense | K17: =_xlfn.XLOOKUP(F17,'04_Account_Mapping'!$A$6:$A$14,'04_Account_Mapping'!$D$6:$D$14,"Unmapped",0) -> Expense
... A569: 46174 | B569: 2026 | C569: 6 | D569: Other | E569: CC_NEWVENTURES | F569: REV | G569: 322.92 | H569: Reported cumulative revenue; monthly delta | I569: SRC-007 | J569: =_xlfn.XLOOKUP(F569,'04_Account_Mapping'!$A$6:$A$14,'04_Account_Mapping'!$C$6:$C$14,"Unmapped",0) -> Revenue | K569: =_xlfn.XLOOKUP(F569,'04_Account_Mapping'!$A$6:$A$14,'04_Account_Mapping'!$D$6:$D$14,"Unmapped",0) -> Income

Sheet 02_Raw_Budget
A1: Budget input table — analyst prepared and calibrated to FY2025/FY2026 official targets | B1: Budget input table — analyst prepared and calibrated to FY2025/FY2026 official targets | C1: Budget input table — analyst prepared and calibrated to FY2025/FY2026 official targets | D1: Budget input table — analyst prepared and calibrated to FY2025/FY2026 official targets | E1: Budget input table — analyst prepared and calibrated to FY2025/FY2026 official targets | F1: Budget input table — analyst prepared and calibrated to FY2025/FY2026 official targets | G1: Budget input table — analyst prepared and calibrated to FY2025/FY2026 official targets | H1: Budget input table — analyst prepared and calibrated to FY2025/FY2026 official targets | I1: Budget input table — analyst prepared and calibrated to FY2025/FY2026 official targets | J1: Budget input table — analyst prepared and calibrated to FY2025/FY2026 official targets | K1: Budget input table — analyst prepared and calibrated to FY2025/FY2026 official targets
A2: Green formula columns use XLOOKUP against 04_Account_Mapping. Input values are intentionally separate from report outputs. | B2: Green formula columns use XLOOKUP against 04_Account_Mapping. Input values are intentionally separate from report outputs. | C2: Green formula columns use XLOOKUP against 04_Account_Mapping. Input values are intentionally separate from report outputs. | D2: Green formula columns use XLOOKUP against 04_Account_Mapping. Input values are intentionally separate from report outputs. | E2: Green formula columns use XLOOKUP against 04_Account_Mapping. Input values are intentionally separate from report outputs. | F2: Green formula columns use XLOOKUP against 04_Account_Mapping. Input values are intentionally separate from report outputs. | G2: Green formula columns use XLOOKUP against 04_Account_Mapping. Input values are intentionally separate from report outputs. | H2: Green formula columns use XLOOKUP against 04_Account_Mapping. Input values are intentionally separate from report outputs. | I2: Green formula columns use XLOOKUP against 04_Account_Mapping. Input values are intentionally separate from report outputs. | J2: Green formula columns use XLOOKUP against 04_Account_Mapping. Input values are intentionally separate from report outputs. | K2: Green formula columns use XLOOKUP against 04_Account_Mapping. Input values are intentionally separate from report outputs.
A5: Period | B5: Year | C5: Month | D5: BusinessUnit | E5: CostCenter | F5: AccountCode | G5: Amount_VNDm | H5: EvidenceClass | I5: SourceID | J5: MappedCategory | K5: CostNature
A6: 45658 | B6: 2025 | C6: 1 | D6: TGDĐ | E6: CC_TECH | F6: REV | G6: 2654.547 | H6: Analyst-prepared monthly budget calibrated to official FY2025 revenue/PAT plan | I6: SRC-008 | J6: =_xlfn.XLOOKUP(F6,'04_Account_Mapping'!$A$6:$A$14,'04_Account_Mapping'!$C$6:$C$14,"Unmapped",0) -> Revenue | K6: =_xlfn.XLOOKUP(F6,'04_Account_Mapping'!$A$6:$A$14,'04_Account_Mapping'!$D$6:$D$14,"Unmapped",0) -> Income
A7: 45658 | B7: 2025 | C7: 1 | D7: TGDĐ | E7: CC_TECH | F7: COGS | G7: -2112.9752 | H7: Analyst-prepared monthly budget calibrated to official FY2025 revenue/PAT plan | I7: SRC-008 | J7: =_xlfn.XLOOKUP(F7,'04_Account_Mapping'!$A$6:$A$14,'04_Account_Mapping'!$C$6:$C$14,"Unmapped",0) -> COGS | K7: =_xlfn.XLOOKUP(F7,'04_Account_Mapping'!$A$6:$A$14,'04_Account_Mapping'!$D$6:$D$14,"Unmapped",0) -> Expense
A8: 45658 | B8: 2025 | C8: 1 | D8: TGDĐ | E8: CC_TECH | F8: SELL | G8: -376.94568 | H8: Analyst-prepared monthly budget calibrated to official FY2025 revenue/PAT plan | I8: SRC-008 | J8: =_xlfn.XLOOKUP(F8,'04_Account_Mapping'!$A$6:$A$14,'04_Account_Mapping'!$C$6:$C$14,"Unmapped",0) -> Selling Expense | K8: =_xlfn.XLOOKUP(F8,'04_Account_Mapping'!$A$6:$A$14,'04_Account_Mapping'!$D$6:$D$14,"Unmapped",0) -> Expense
A9: 45658 | B9: 2025 | C9: 1 | D9: TGDĐ | E9: CC_TECH | F9: GA | G9: -71.672769 | H9: Analyst-prepared monthly budget calibrated to official FY2025 revenue/PAT plan | I9: SRC-008 | J9: =_xlfn.XLOOKUP(F9,'04_Account_Mapping'!$A$6:$A$14,'04_Account_Mapping'!$C$6:$C$14,"Unmapped",0) -> G&A | K9: =_xlfn.XLOOKUP(F9,'04_Account_Mapping'!$A$6:$A$14,'04_Account_Mapping'!$D$6:$D$14,"Unmapped",0) -> Expense
A10: 45658 | B10: 2025 | C10: 1 | D10: TGDĐ | E10: CC_TECH | F10: FIN_INC | G10: 39.818205 | H10: Analyst-prepared monthly budget calibrated to official FY2025 revenue/PAT plan | I10: SRC-008 | J10: =_xlfn.XLOOKUP(F10,'04_Account_Mapping'!$A$6:$A$14,'04_Account_Mapping'!$C$6:$C$14,"Unmapped",0) -> Finance Income | K10: =_xlfn.XLOOKUP(F10,'04_Account_Mapping'!$A$6:$A$14,'04_Account_Mapping'!$D$6:$D$14,"Unmapped",0) -> Income
A11: 45658 | B11: 2025 | C11: 1 | D11: TGDĐ | E11: CC_TECH | F11: FIN_EXP | G11: -21.236376 | H11: Analyst-prepared monthly budget calibrated to official FY2025 revenue/PAT plan | I11: SRC-008 | J11: =_xlfn.XLOOKUP(F11,'04_Account_Mapping'!$A$6:$A$14,'04_Account_Mapping'!$C$6:$C$14,"Unmapped",0) -> Finance Expense | K11: =_xlfn.XLOOKUP(F11,'04_Account_Mapping'!$A$6:$A$14,'04_Account_Mapping'!$D$6:$D$14,"Unmapped",0) -> Expense
A12: 45658 | B12: 2025 | C12: 1 | D12: TGDĐ | E12: CC_TECH | F12: JV | G12: 0 | H12: Analyst-prepared monthly budget calibrated to official FY2025 revenue/PAT plan | I12: SRC-008 | J12: =_xlfn.XLOOKUP(F12,'04_Account_Mapping'!$A$6:$A$14,'04_Account_Mapping'!$C$6:$C$14,"Unmapped",0) -> JV Profit/(Loss) | K12: =_xlfn.XLOOKUP(F12,'04_Account_Mapping'!$A$6:$A$14,'04_Account_Mapping'!$D$6:$D$14,"Unmapped",0) -> Income
A13: 45658 | B13: 2025 | C13: 1 | D13: TGDĐ | E13: CC_TECH | F13: OTHER | G13: -4.2472752 | H13: Analyst-prepared monthly budget calibrated to official FY2025 revenue/PAT plan | I13: SRC-008 | J13: =_xlfn.XLOOKUP(F13,'04_Account_Mapping'!$A$6:$A$14,'04_Account_Mapping'!$C$6:$C$14,"Unmapped",0) -> Other Net | K13: =_xlfn.XLOOKUP(F13,'04_Account_Mapping'!$A$6:$A$14,'04_Account_Mapping'!$D$6:$D$14,"Unmapped",0) -> Income
A14: 45658 | B14: 2025 | C14: 1 | D14: TGDĐ | E14: CC_TECH | F14: TAX | G14: -21.457588 | H14: Analyst-prepared monthly budget calibrated to official FY2025 revenue/PAT plan | I14: SRC-008 | J14: =_xlfn.XLOOKUP(F14,'04_Account_Mapping'!$A$6:$A$14,'04_Account_Mapping'!$C$6:$C$14,"Unmapped",0) -> Tax Expense | K14: =_xlfn.XLOOKUP(F14,'04_Account_Mapping'!$A$6:$A$14,'04_Account_Mapping'!$D$6:$D$14,"Unmapped",0) -> Expense
A15: 45658 | B15: 2025 | C15: 1 | D15: ĐMX | E15: CC_TECH | F15: REV | G15: 5067.7716 | H15: Analyst-prepared monthly budget calibrated to official FY2025 revenue/PAT plan | I15: SRC-008 | J15: =_xlfn.XLOOKUP(F15,'04_Account_Mapping'!$A$6:$A$14,'04_Account_Mapping'!$C$6:$C$14,"Unmapped",0) -> Revenue | K15: =_xlfn.XLOOKUP(F15,'04_Account_Mapping'!$A$6:$A$14,'04_Account_Mapping'!$D$6:$D$14,"Unmapped",0) -> Income
A16: 45658 | B16: 2025 | C16: 1 | D16: ĐMX | E16: CC_TECH | F16: COGS | G16: -4033.8617 | H16: Analyst-prepared monthly budget calibrated to official FY2025 revenue/PAT plan | I16: SRC-008 | J16: =_xlfn.XLOOKUP(F16,'04_Account_Mapping'!$A$6:$A$14,'04_Account_Mapping'!$C$6:$C$14,"Unmapped",0) -> COGS | K16: =_xlfn.XLOOKUP(F16,'04_Account_Mapping'!$A$6:$A$14,'04_Account_Mapping'!$D$6:$D$14,"Unmapped",0) -> Expense
A17: 45658 | B17: 2025 | C17: 1 | D17: ĐMX | E17: CC_TECH | F17: SELL | G17: -719.62356 | H17: Analyst-prepared monthly budget calibrated to official FY2025 revenue/PAT plan | I17: SRC-008 | J17: =_xlfn.XLOOKUP(F17,'04_Account_Mapping'!$A$6:$A$14,'04_Account_Mapping'!$C$6:$C$14,"Unmapped",0) -> Selling Expense | K17: =_xlfn.XLOOKUP(F17,'04_Account_Mapping'!$A$6:$A$14,'04_Account_Mapping'!$D$6:$D$14,"Unmapped",0) -> Expense
... A869: 46357 | B869: 2026 | C869: 12 | D869: Other | E869: CC_NEWVENTURES | F869: TAX | G869: -4.6963206 | H869: Analyst monthly phasing calibrated to official FY2026 revenue/PAT plan | I869: SRC-009 | J869: =_xlfn.XLOOKUP(F869,'04_Account_Mapping'!$A$6:$A$14,'04_Account_Mapping'!$C$6:$C$14,"Unmapped",0) -> Tax Expense | K869: =_xlfn.XLOOKUP(F869,'04_Account_Mapping'!$A$6:$A$14,'04_Account_Mapping'!$D$6:$D$14,"Unmapped",0) -> Expense

Sheet 03_Master_Data
A1: Master Data, Scenario Drivers & Refresh Control | B1: Master Data, Scenario Drivers & Refresh Control | C1: Master Data, Scenario Drivers & Refresh Control | D1: Master Data, Scenario Drivers & Refresh Control | E1: Master Data, Scenario Drivers & Refresh Control | F1: Master Data, Scenario Drivers & Refresh Control | G1: Master Data, Scenario Drivers & Refresh Control | H1: Master Data, Scenario Drivers & Refresh Control
A2: Blue cells are user-editable assumptions. Company targets remain separate from analyst assumptions. | B2: Blue cells are user-editable assumptions. Company targets remain separate from analyst assumptions. | C2: Blue cells are user-editable assumptions. Company targets remain separate from analyst assumptions. | D2: Blue cells are user-editable assumptions. Company targets remain separate from analyst assumptions. | E2: Blue cells are user-editable assumptions. Company targets remain separate from analyst assumptions. | F2: Blue cells are user-editable assumptions. Company targets remain separate from analyst assumptions. | G2: Blue cells are user-editable assumptions. Company targets remain separate from analyst assumptions. | H2: Blue cells are user-editable assumptions. Company targets remain separate from analyst assumptions.
A4: Business unit and cost-center master | B4: Business unit and cost-center master | C4: Business unit and cost-center master | D4: Business unit and cost-center master | E4: Business unit and cost-center master | F4: Business unit and cost-center master | G4: Business unit and cost-center master | H4: Business unit and cost-center master
A6: BusinessUnit | B6: CostCenter | C6: Description | D6: FY2025 actual mix
A7: TGDĐ | B7: CC_TECH | C7: thegioididong.com + TopZone | D7: 0.239
A8: ĐMX | B8: CC_TECH | C8: Điện Máy Xanh | D8: 0.438
A9: BHX | B9: CC_GROCERY | C9: Bách Hóa Xanh | D9: 0.3
A10: Other | B10: CC_NEWVENTURES | C10: An Khang, AVAKids and other | D10: 0.023
A11: Group | B11: CC_GROUP | C11: FY2024 consolidated allocation only
A12: FY2025 budget assumptions | B12: FY2025 budget assumptions | C12: FY2025 budget assumptions | D12: FY2025 budget assumptions | E12: FY2026 plan / rolling forecast assumptions | F12: FY2026 plan / rolling forecast assumptions | G12: FY2026 plan / rolling forecast assumptions | H12: FY2026 plan / rolling forecast assumptions
A14: Driver | B14: Value | C14: Source / rationale | E14: Driver | F14: Value | G14: Source / rationale
A15: Revenue target | B15: 150000 | C15: Official MWG FY2025 guidance | E15: Revenue target | F15: 185000 | G15: Official MWG FY2026 guidance
A16: PAT target | B16: 4850 | C16: Official MWG FY2025 guidance | E16: PAT target | F16: 9200 | G16: Official MWG FY2026 guidance
A17: Selling expense / revenue | B17: 0.142 | C17: Analyst assumption | E17: Selling expense / revenue | F17: 0.122 | G17: Analyst assumption
A18: G&A / revenue | B18: 0.027 | C18: Analyst assumption | E18: G&A / revenue | F18: 0.029 | G18: Analyst assumption
A19: Finance income / revenue | B19: 0.015 | C19: Analyst assumption | E19: Finance income / revenue | F19: 0.02 | G19: Analyst assumption
A20: Finance expense / revenue | B20: 0.008 | C20: Analyst assumption | E20: Finance expense / revenue | F20: 0.01 | G20: Analyst assumption
A21: JV profit / revenue | B21: 0 | C21: Analyst assumption | E21: JV profit / revenue | F21: 0.0002 | G21: Analyst assumption
A22: Other net / revenue | B22: -0.0016 | C22: Analyst assumption | E22: Other net / revenue | F22: 0 | G22: Analyst assumption
A23: Tax rate | B23: 0.2 | C23: Analyst assumption | E23: Tax rate | F23: 0.2 | G23: Analyst assumption
A24: Implied gross margin | B24: =B16/(B15*(1-B23))+B17+B18-B19+B20-B21-B22 -> 0.20401667 | C24: Solved to make budget PAT equal official target | E24: Bull / Bear spread | F24: 0.05 | G24: ±5ppt H2 growth
E25: As-of month | F25: 6 | G25: Actual revenue through Jun-2026
E26: Implied gross margin | F26: =F16/(F15*(1-F23))+F17+F18-F19+F20-F21-F22 -> 0.20296216 | G26: Solved to make plan PAT equal official target
A28: Power Query objects expected in Queries & Connections | B28: Power Query objects expected in Queries & Connections | C28: Power Query objects expected in Queries & Connections | D28: Power Query objects expected in Queries & Connections | E28: Power Query objects expected in Queries & Connections | F28: Power Query objects expected in Queries & Connections | G28: Power Query objects expected in Queries & Connections | H28: Power Query objects expected in Queries & Connections
A30: Query | B30: Purpose | C30: Load type | D30: Status
A31: qActual_Clean | B31: Type and clean Actual input | C31: Connection only | D31: READY
A32: qBudget_Clean | B32: Type and clean Budget input | C32: Connection only | D32: READY
A33: qAccount_Map | B33: Type account mapping | C33: Connection only | D33: READY
A34: qActual_Mapped | B34: Merge Actual with mapping | C34: Connection only | D34: READY
A35: qCombined_Actual_Budget | B35: Append Actual and Budget | C35: Connection only | D35: READY

Sheet 04_Account_Mapping
A1: Account Mapping | B1: Account Mapping | C1: Account Mapping | D1: Account Mapping | E1: Account Mapping | F1: Account Mapping
A2: This mapping is used by XLOOKUP on raw inputs and by Power Query merge logic. | B2: This mapping is used by XLOOKUP on raw inputs and by Power Query merge logic. | C2: This mapping is used by XLOOKUP on raw inputs and by Power Query merge logic. | D2: This mapping is used by XLOOKUP on raw inputs and by Power Query merge logic. | E2: This mapping is used by XLOOKUP on raw inputs and by Power Query merge logic. | F2: This mapping is used by XLOOKUP on raw inputs and by Power Query merge logic.
A5: AccountCode | B5: AccountName | C5: P&L Category | D5: CostNature | E5: FavorableSign | F5: Variance rule
A6: REV | B6: Doanh thu thuần | C6: Revenue | D6: Income | E6: 1 | F6: Higher is favorable
A7: COGS | B7: Giá vốn hàng bán | C7: COGS | D7: Expense | E7: -1 | F7: Lower is favorable
A8: SELL | B8: Chi phí bán hàng | C8: Selling Expense | D8: Expense | E8: -1 | F8: Lower is favorable
A9: GA | B9: Chi phí quản lý doanh nghiệp | C9: G&A | D9: Expense | E9: -1 | F9: Lower is favorable
A10: FIN_INC | B10: Doanh thu tài chính | C10: Finance Income | D10: Income | E10: 1 | F10: Higher is favorable
A11: FIN_EXP | B11: Chi phí tài chính | C11: Finance Expense | D11: Expense | E11: -1 | F11: Lower is favorable
A12: JV | B12: Lãi/(lỗ) công ty liên doanh | C12: JV Profit/(Loss) | D12: Income | E12: 1 | F12: Higher is favorable
A13: OTHER | B13: Thu nhập/(chi phí) khác thuần | C13: Other Net | D13: Income | E13: 1 | F13: Higher is favorable
A14: TAX | B14: Thuế TNDN | C14: Tax Expense | D14: Expense | E14: -1 | F14: Lower is favorable

Sheet 05_Monthly_P&L
A1: Monthly P&L — FY2025 Actual vs Budget | B1: Monthly P&L — FY2025 Actual vs Budget | C1: Monthly P&L — FY2025 Actual vs Budget | D1: Monthly P&L — FY2025 Actual vs Budget | E1: Monthly P&L — FY2025 Actual vs Budget | F1: Monthly P&L — FY2025 Actual vs Budget | G1: Monthly P&L — FY2025 Actual vs Budget | H1: Monthly P&L — FY2025 Actual vs Budget | I1: Monthly P&L — FY2025 Actual vs Budget | J1: Monthly P&L — FY2025 Actual vs Budget | K1: Monthly P&L — FY2025 Actual vs Budget | L1: Monthly P&L — FY2025 Actual vs Budget | M1: Monthly P&L — FY2025 Actual vs Budget | N1: Monthly P&L — FY2025 Actual vs Budget | O1: Monthly P&L — FY2025 Actual vs Budget
A2: Actual quarterly totals tie to consolidated filings. Monthly and BU expense allocations use revenue weights because MWG does not disclose a monthly cost-center ledger. | B2: Actual quarterly totals tie to consolidated filings. Monthly and BU expense allocations use revenue weights because MWG does not disclose a monthly cost-center ledger. | C2: Actual quarterly totals tie to consolidated filings. Monthly and BU expense allocations use revenue weights because MWG does not disclose a monthly cost-center ledger. | D2: Actual quarterly totals tie to consolidated filings. Monthly and BU expense allocations use revenue weights because MWG does not disclose a monthly cost-center ledger. | E2: Actual quarterly totals tie to consolidated filings. Monthly and BU expense allocations use revenue weights because MWG does not disclose a monthly cost-center ledger. | F2: Actual quarterly totals tie to consolidated filings. Monthly and BU expense allocations use revenue weights because MWG does not disclose a monthly cost-center ledger. | G2: Actual quarterly totals tie to consolidated filings. Monthly and BU expense allocations use revenue weights because MWG does not disclose a monthly cost-center ledger. | H2: Actual quarterly totals tie to consolidated filings. Monthly and BU expense allocations use revenue weights because MWG does not disclose a monthly cost-center ledger. | I2: Actual quarterly totals tie to consolidated filings. Monthly and BU expense allocations use revenue weights because MWG does not disclose a monthly cost-center ledger. | J2: Actual quarterly totals tie to consolidated filings. Monthly and BU expense allocations use revenue weights because MWG does not disclose a monthly cost-center ledger. | K2: Actual quarterly totals tie to consolidated filings. Monthly and BU expense allocations use revenue weights because MWG does not disclose a monthly cost-center ledger. | L2: Actual quarterly totals tie to consolidated filings. Monthly and BU expense allocations use revenue weights because MWG does not disclose a monthly cost-center ledger. | M2: Actual quarterly totals tie to consolidated filings. Monthly and BU expense allocations use revenue weights because MWG does not disclose a monthly cost-center ledger. | N2: Actual quarterly totals tie to consolidated filings. Monthly and BU expense allocations use revenue weights because MWG does not disclose a monthly cost-center ledger. | O2: Actual quarterly totals tie to consolidated filings. Monthly and BU expense allocations use revenue weights because MWG does not disclose a monthly cost-center ledger.
A4: Code | B4: P&L line | C4: 45658 | D4: 45689 | E4: 45717 | F4: 45748 | G4: 45778 | H4: 45809 | I4: 45839 | J4: 45870 | K4: 45901 | L4: 45931 | M4: 45962 | N4: 45992 | O4: FY2025
A6: ACTUAL | B6: ACTUAL | C6: ACTUAL | D6: ACTUAL | E6: ACTUAL | F6: ACTUAL | G6: ACTUAL | H6: ACTUAL | I6: ACTUAL | J6: ACTUAL | K6: ACTUAL | L6: ACTUAL | M6: ACTUAL | N6: ACTUAL | O6: ACTUAL
A7: REV | B7: Revenue | C7: =SUMIFS('01_Raw_Actual'!$G$6:$G$569,'01_Raw_Actual'!$A$6:$A$569,C$4,'01_Raw_Actual'!$F$6:$F$569,$A7) -> 12276.935 | D7: =SUMIFS('01_Raw_Actual'!$G$6:$G$569,'01_Raw_Actual'!$A$6:$A$569,D$4,'01_Raw_Actual'!$F$6:$F$569,$A7) -> 12276.935 | E7: =SUMIFS('01_Raw_Actual'!$G$6:$G$569,'01_Raw_Actual'!$A$6:$A$569,E$4,'01_Raw_Actual'!$F$6:$F$569,$A7) -> 11581.088 | F7: =SUMIFS('01_Raw_Actual'!$G$6:$G$569,'01_Raw_Actual'!$A$6:$A$569,F$4,'01_Raw_Actual'!$F$6:$F$569,$A7) -> 12562.69 | G7: =SUMIFS('01_Raw_Actual'!$G$6:$G$569,'01_Raw_Actual'!$A$6:$A$569,G$4,'01_Raw_Actual'!$F$6:$F$569,$A7) -> 12612.764 | H7: =SUMIFS('01_Raw_Actual'!$G$6:$G$569,'01_Raw_Actual'!$A$6:$A$569,H$4,'01_Raw_Actual'!$F$6:$F$569,$A7) -> 12444.514 | I7: =SUMIFS('01_Raw_Actual'!$G$6:$G$569,'01_Raw_Actual'!$A$6:$A$569,I$4,'01_Raw_Actual'!$F$6:$F$569,$A7) -> 12875.102 | J7: =SUMIFS('01_Raw_Actual'!$G$6:$G$569,'01_Raw_Actual'!$A$6:$A$569,J$4,'01_Raw_Actual'!$F$6:$F$569,$A7) -> 13317.896 | ... N7: =SUMIFS('01_Raw_Actual'!$G$6:$G$569,'01_Raw_Actual'!$A$6:$A$569,N$4,'01_Raw_Actual'!$F$6:$F$569,$A7) -> 13731.204 | O7: =SUM(C7:N7) -> 155928.15
A8: COGS | B8: COGS | C8: =SUMIFS('01_Raw_Actual'!$G$6:$G$569,'01_Raw_Actual'!$A$6:$A$569,C$4,'01_Raw_Actual'!$F$6:$F$569,$A8) -> -9830.579 | D8: =SUMIFS('01_Raw_Actual'!$G$6:$G$569,'01_Raw_Actual'!$A$6:$A$569,D$4,'01_Raw_Actual'!$F$6:$F$569,$A8) -> -9830.579 | E8: =SUMIFS('01_Raw_Actual'!$G$6:$G$569,'01_Raw_Actual'!$A$6:$A$569,E$4,'01_Raw_Actual'!$F$6:$F$569,$A8) -> -9273.3899 | F8: =SUMIFS('01_Raw_Actual'!$G$6:$G$569,'01_Raw_Actual'!$A$6:$A$569,F$4,'01_Raw_Actual'!$F$6:$F$569,$A8) -> -10035.223 | G8: =SUMIFS('01_Raw_Actual'!$G$6:$G$569,'01_Raw_Actual'!$A$6:$A$569,G$4,'01_Raw_Actual'!$F$6:$F$569,$A8) -> -10075.223 | H8: =SUMIFS('01_Raw_Actual'!$G$6:$G$569,'01_Raw_Actual'!$A$6:$A$569,H$4,'01_Raw_Actual'!$F$6:$F$569,$A8) -> -9940.8225 | I8: =SUMIFS('01_Raw_Actual'!$G$6:$G$569,'01_Raw_Actual'!$A$6:$A$569,I$4,'01_Raw_Actual'!$F$6:$F$569,$A8) -> -10459.133 | J8: =SUMIFS('01_Raw_Actual'!$G$6:$G$569,'01_Raw_Actual'!$A$6:$A$569,J$4,'01_Raw_Actual'!$F$6:$F$569,$A8) -> -10818.838 | ... N8: =SUMIFS('01_Raw_Actual'!$G$6:$G$569,'01_Raw_Actual'!$A$6:$A$569,N$4,'01_Raw_Actual'!$F$6:$F$569,$A8) -> -10890.729 | O8: =SUM(C8:N8) -> -124926.27
B9: Gross Profit | C9: =C7+C8 -> 2446.356 | D9: =D7+D8 -> 2446.356 | E9: =E7+E8 -> 2307.6986 | F9: =F7+F8 -> 2527.4673 | G9: =G7+G8 -> 2537.5417 | H9: =H7+H8 -> 2503.6917 | I9: =I7+I8 -> 2415.9689 | J9: =J7+J8 -> 2499.0578 | ... N9: =N7+N8 -> 2840.4748 | O9: =SUM(C9:N9) -> 31001.877
B10: Gross Margin | C10: =IFERROR(C9/C7,0) -> 0.19926439 | D10: =IFERROR(D9/D7,0) -> 0.19926439 | E10: =IFERROR(E9/E7,0) -> 0.19926439 | F10: =IFERROR(F9/F7,0) -> 0.20118838 | G10: =IFERROR(G9/G7,0) -> 0.20118838 | H10: =IFERROR(H9/H7,0) -> 0.20118838 | I10: =IFERROR(I9/I7,0) -> 0.18764659 | J10: =IFERROR(J9/J7,0) -> 0.18764659 | ... O10: =IFERROR(O9/O7,0) -> 0.19882156
A11: SELL | B11: Selling Expense | C11: =SUMIFS('01_Raw_Actual'!$G$6:$G$569,'01_Raw_Actual'!$A$6:$A$569,C$4,'01_Raw_Actual'!$F$6:$F$569,$A11) -> -1495.9315 | D11: =SUMIFS('01_Raw_Actual'!$G$6:$G$569,'01_Raw_Actual'!$A$6:$A$569,D$4,'01_Raw_Actual'!$F$6:$F$569,$A11) -> -1495.9315 | E11: =SUMIFS('01_Raw_Actual'!$G$6:$G$569,'01_Raw_Actual'!$A$6:$A$569,E$4,'01_Raw_Actual'!$F$6:$F$569,$A11) -> -1411.1433 | F11: =SUMIFS('01_Raw_Actual'!$G$6:$G$569,'01_Raw_Actual'!$A$6:$A$569,F$4,'01_Raw_Actual'!$F$6:$F$569,$A11) -> -1570.5991 | G11: =SUMIFS('01_Raw_Actual'!$G$6:$G$569,'01_Raw_Actual'!$A$6:$A$569,G$4,'01_Raw_Actual'!$F$6:$F$569,$A11) -> -1576.8595 | H11: =SUMIFS('01_Raw_Actual'!$G$6:$G$569,'01_Raw_Actual'!$A$6:$A$569,H$4,'01_Raw_Actual'!$F$6:$F$569,$A11) -> -1555.8246 | I11: =SUMIFS('01_Raw_Actual'!$G$6:$G$569,'01_Raw_Actual'!$A$6:$A$569,I$4,'01_Raw_Actual'!$F$6:$F$569,$A11) -> -1476.6937 | J11: =SUMIFS('01_Raw_Actual'!$G$6:$G$569,'01_Raw_Actual'!$A$6:$A$569,J$4,'01_Raw_Actual'!$F$6:$F$569,$A11) -> -1527.4795 | ... N11: =SUMIFS('01_Raw_Actual'!$G$6:$G$569,'01_Raw_Actual'!$A$6:$A$569,N$4,'01_Raw_Actual'!$F$6:$F$569,$A11) -> -1834.4024 | O11: =SUM(C11:N11) -> -19330.904
A12: GA | B12: G&A | C12: =SUMIFS('01_Raw_Actual'!$G$6:$G$569,'01_Raw_Actual'!$A$6:$A$569,C$4,'01_Raw_Actual'!$F$6:$F$569,$A12) -> -412.66306 | D12: =SUMIFS('01_Raw_Actual'!$G$6:$G$569,'01_Raw_Actual'!$A$6:$A$569,D$4,'01_Raw_Actual'!$F$6:$F$569,$A12) -> -412.66306 | E12: =SUMIFS('01_Raw_Actual'!$G$6:$G$569,'01_Raw_Actual'!$A$6:$A$569,E$4,'01_Raw_Actual'!$F$6:$F$569,$A12) -> -389.27366 | F12: =SUMIFS('01_Raw_Actual'!$G$6:$G$569,'01_Raw_Actual'!$A$6:$A$569,F$4,'01_Raw_Actual'!$F$6:$F$569,$A12) -> -401.28047 | G12: =SUMIFS('01_Raw_Actual'!$G$6:$G$569,'01_Raw_Actual'!$A$6:$A$569,G$4,'01_Raw_Actual'!$F$6:$F$569,$A12) -> -402.87996 | H12: =SUMIFS('01_Raw_Actual'!$G$6:$G$569,'01_Raw_Actual'!$A$6:$A$569,H$4,'01_Raw_Actual'!$F$6:$F$569,$A12) -> -397.50567 | I12: =SUMIFS('01_Raw_Actual'!$G$6:$G$569,'01_Raw_Actual'!$A$6:$A$569,I$4,'01_Raw_Actual'!$F$6:$F$569,$A12) -> -361.64782 | J12: =SUMIFS('01_Raw_Actual'!$G$6:$G$569,'01_Raw_Actual'!$A$6:$A$569,J$4,'01_Raw_Actual'!$F$6:$F$569,$A12) -> -374.08545 | ... N12: =SUMIFS('01_Raw_Actual'!$G$6:$G$569,'01_Raw_Actual'!$A$6:$A$569,N$4,'01_Raw_Actual'!$F$6:$F$569,$A12) -> -344.05119 | O12: =SUM(C12:N12) -> -4596.0745
B13: Operating Profit | C13: =SUM(C9,C11:C12) -> 537.76145 | D13: =SUM(D9,D11:D12) -> 537.76145 | E13: =SUM(E9,E11:E12) -> 507.28158 | F13: =SUM(F9,F11:F12) -> 555.58772 | G13: =SUM(G9,G11:G12) -> 557.80227 | H13: =SUM(H9,H11:H12) -> 550.36137 | I13: =SUM(I9,I11:I12) -> 577.62735 | J13: =SUM(J9,J11:J12) -> 597.49284 | ... N13: =SUM(N9,N11:N12) -> 662.02121 | O13: =SUM(C13:N13) -> 7074.8993
A14: FIN_INC | B14: Finance Income | C14: =SUMIFS('01_Raw_Actual'!$G$6:$G$569,'01_Raw_Actual'!$A$6:$A$569,C$4,'01_Raw_Actual'!$F$6:$F$569,$A14) -> 235.54811 | D14: =SUMIFS('01_Raw_Actual'!$G$6:$G$569,'01_Raw_Actual'!$A$6:$A$569,D$4,'01_Raw_Actual'!$F$6:$F$569,$A14) -> 235.54811 | E14: =SUMIFS('01_Raw_Actual'!$G$6:$G$569,'01_Raw_Actual'!$A$6:$A$569,E$4,'01_Raw_Actual'!$F$6:$F$569,$A14) -> 222.19744 | F14: =SUMIFS('01_Raw_Actual'!$G$6:$G$569,'01_Raw_Actual'!$A$6:$A$569,F$4,'01_Raw_Actual'!$F$6:$F$569,$A14) -> 256.74134 | G14: =SUMIFS('01_Raw_Actual'!$G$6:$G$569,'01_Raw_Actual'!$A$6:$A$569,G$4,'01_Raw_Actual'!$F$6:$F$569,$A14) -> 257.7647 | H14: =SUMIFS('01_Raw_Actual'!$G$6:$G$569,'01_Raw_Actual'!$A$6:$A$569,H$4,'01_Raw_Actual'!$F$6:$F$569,$A14) -> 254.3262 | I14: =SUMIFS('01_Raw_Actual'!$G$6:$G$569,'01_Raw_Actual'!$A$6:$A$569,I$4,'01_Raw_Actual'!$F$6:$F$569,$A14) -> 261.38492 | J14: =SUMIFS('01_Raw_Actual'!$G$6:$G$569,'01_Raw_Actual'!$A$6:$A$569,J$4,'01_Raw_Actual'!$F$6:$F$569,$A14) -> 270.37435 | ... N14: =SUMIFS('01_Raw_Actual'!$G$6:$G$569,'01_Raw_Actual'!$A$6:$A$569,N$4,'01_Raw_Actual'!$F$6:$F$569,$A14) -> 271.29506 | O14: =SUM(C14:N14) -> 3107.3487
A15: FIN_EXP | B15: Finance Expense | C15: =SUMIFS('01_Raw_Actual'!$G$6:$G$569,'01_Raw_Actual'!$A$6:$A$569,C$4,'01_Raw_Actual'!$F$6:$F$569,$A15) -> -115.1839 | D15: =SUMIFS('01_Raw_Actual'!$G$6:$G$569,'01_Raw_Actual'!$A$6:$A$569,D$4,'01_Raw_Actual'!$F$6:$F$569,$A15) -> -115.1839 | E15: =SUMIFS('01_Raw_Actual'!$G$6:$G$569,'01_Raw_Actual'!$A$6:$A$569,E$4,'01_Raw_Actual'!$F$6:$F$569,$A15) -> -108.65537 | F15: =SUMIFS('01_Raw_Actual'!$G$6:$G$569,'01_Raw_Actual'!$A$6:$A$569,F$4,'01_Raw_Actual'!$F$6:$F$569,$A15) -> -134.39434 | G15: =SUMIFS('01_Raw_Actual'!$G$6:$G$569,'01_Raw_Actual'!$A$6:$A$569,G$4,'01_Raw_Actual'!$F$6:$F$569,$A15) -> -134.93003 | H15: =SUMIFS('01_Raw_Actual'!$G$6:$G$569,'01_Raw_Actual'!$A$6:$A$569,H$4,'01_Raw_Actual'!$F$6:$F$569,$A15) -> -133.1301 | I15: =SUMIFS('01_Raw_Actual'!$G$6:$G$569,'01_Raw_Actual'!$A$6:$A$569,I$4,'01_Raw_Actual'!$F$6:$F$569,$A15) -> -132.69834 | J15: =SUMIFS('01_Raw_Actual'!$G$6:$G$569,'01_Raw_Actual'!$A$6:$A$569,J$4,'01_Raw_Actual'!$F$6:$F$569,$A15) -> -137.26204 | ... N15: =SUMIFS('01_Raw_Actual'!$G$6:$G$569,'01_Raw_Actual'!$A$6:$A$569,N$4,'01_Raw_Actual'!$F$6:$F$569,$A15) -> -126.63441 | O15: =SUM(C15:N15) -> -1542.5187
A16: JV | B16: JV Profit/(Loss) | C16: =SUMIFS('01_Raw_Actual'!$G$6:$G$569,'01_Raw_Actual'!$A$6:$A$569,C$4,'01_Raw_Actual'!$F$6:$F$569,$A16) -> 1.063348 | D16: =SUMIFS('01_Raw_Actual'!$G$6:$G$569,'01_Raw_Actual'!$A$6:$A$569,D$4,'01_Raw_Actual'!$F$6:$F$569,$A16) -> 1.063348 | E16: =SUMIFS('01_Raw_Actual'!$G$6:$G$569,'01_Raw_Actual'!$A$6:$A$569,E$4,'01_Raw_Actual'!$F$6:$F$569,$A16) -> 1.0030783 | F16: =SUMIFS('01_Raw_Actual'!$G$6:$G$569,'01_Raw_Actual'!$A$6:$A$569,F$4,'01_Raw_Actual'!$F$6:$F$569,$A16) -> 3.7139212 | G16: =SUMIFS('01_Raw_Actual'!$G$6:$G$569,'01_Raw_Actual'!$A$6:$A$569,G$4,'01_Raw_Actual'!$F$6:$F$569,$A16) -> 3.7287248 | H16: =SUMIFS('01_Raw_Actual'!$G$6:$G$569,'01_Raw_Actual'!$A$6:$A$569,H$4,'01_Raw_Actual'!$F$6:$F$569,$A16) -> 3.6789848 | I16: =SUMIFS('01_Raw_Actual'!$G$6:$G$569,'01_Raw_Actual'!$A$6:$A$569,I$4,'01_Raw_Actual'!$F$6:$F$569,$A16) -> 1.3493619 | J16: =SUMIFS('01_Raw_Actual'!$G$6:$G$569,'01_Raw_Actual'!$A$6:$A$569,J$4,'01_Raw_Actual'!$F$6:$F$569,$A16) -> 1.3957685 | ... N16: =SUMIFS('01_Raw_Actual'!$G$6:$G$569,'01_Raw_Actual'!$A$6:$A$569,N$4,'01_Raw_Actual'!$F$6:$F$569,$A16) -> 1.9217434 | O16: =SUM(C16:N16) -> 24.351079
A17: OTHER | B17: Other Net | C17: =SUMIFS('01_Raw_Actual'!$G$6:$G$569,'01_Raw_Actual'!$A$6:$A$569,C$4,'01_Raw_Actual'!$F$6:$F$569,$A17) -> -1.8833751 | D17: =SUMIFS('01_Raw_Actual'!$G$6:$G$569,'01_Raw_Actual'!$A$6:$A$569,D$4,'01_Raw_Actual'!$F$6:$F$569,$A17) -> -1.8833751 | E17: =SUMIFS('01_Raw_Actual'!$G$6:$G$569,'01_Raw_Actual'!$A$6:$A$569,E$4,'01_Raw_Actual'!$F$6:$F$569,$A17) -> -1.776627 | F17: =SUMIFS('01_Raw_Actual'!$G$6:$G$569,'01_Raw_Actual'!$A$6:$A$569,F$4,'01_Raw_Actual'!$F$6:$F$569,$A17) -> -4.3565437 | G17: =SUMIFS('01_Raw_Actual'!$G$6:$G$569,'01_Raw_Actual'!$A$6:$A$569,G$4,'01_Raw_Actual'!$F$6:$F$569,$A17) -> -4.3739087 | H17: =SUMIFS('01_Raw_Actual'!$G$6:$G$569,'01_Raw_Actual'!$A$6:$A$569,H$4,'01_Raw_Actual'!$F$6:$F$569,$A17) -> -4.3155622 | I17: =SUMIFS('01_Raw_Actual'!$G$6:$G$569,'01_Raw_Actual'!$A$6:$A$569,I$4,'01_Raw_Actual'!$F$6:$F$569,$A17) -> -5.8444054 | J17: =SUMIFS('01_Raw_Actual'!$G$6:$G$569,'01_Raw_Actual'!$A$6:$A$569,J$4,'01_Raw_Actual'!$F$6:$F$569,$A17) -> -6.0454035 | ... N17: =SUMIFS('01_Raw_Actual'!$G$6:$G$569,'01_Raw_Actual'!$A$6:$A$569,N$4,'01_Raw_Actual'!$F$6:$F$569,$A17) -> 1.8386158 | O17: =SUM(C17:N17) -> -31.012906
B18: Profit Before Tax | C18: =SUM(C13:C17) -> 657.30564 | D18: =SUM(D13:D17) -> 657.30564 | E18: =SUM(E13:E17) -> 620.0501 | F18: =SUM(F13:F17) -> 677.2921 | G18: =SUM(G13:G17) -> 679.99177 | H18: =SUM(H13:H17) -> 670.92089 | I18: =SUM(I13:I17) -> 701.81889 | J18: =SUM(J13:J17) -> 725.95552 | ... N18: =SUM(N13:N17) -> 810.44222 | O18: =SUM(C18:N18) -> 8633.0676
A19: TAX | B19: Tax Expense | C19: =SUMIFS('01_Raw_Actual'!$G$6:$G$569,'01_Raw_Actual'!$A$6:$A$569,C$4,'01_Raw_Actual'!$F$6:$F$569,$A19) -> -131.42557 | D19: =SUMIFS('01_Raw_Actual'!$G$6:$G$569,'01_Raw_Actual'!$A$6:$A$569,D$4,'01_Raw_Actual'!$F$6:$F$569,$A19) -> -131.42557 | E19: =SUMIFS('01_Raw_Actual'!$G$6:$G$569,'01_Raw_Actual'!$A$6:$A$569,E$4,'01_Raw_Actual'!$F$6:$F$569,$A19) -> -123.97648 | F19: =SUMIFS('01_Raw_Actual'!$G$6:$G$569,'01_Raw_Actual'!$A$6:$A$569,F$4,'01_Raw_Actual'!$F$6:$F$569,$A19) -> -123.78222 | G19: =SUMIFS('01_Raw_Actual'!$G$6:$G$569,'01_Raw_Actual'!$A$6:$A$569,G$4,'01_Raw_Actual'!$F$6:$F$569,$A19) -> -124.27561 | H19: =SUMIFS('01_Raw_Actual'!$G$6:$G$569,'01_Raw_Actual'!$A$6:$A$569,H$4,'01_Raw_Actual'!$F$6:$F$569,$A19) -> -122.61781 | I19: =SUMIFS('01_Raw_Actual'!$G$6:$G$569,'01_Raw_Actual'!$A$6:$A$569,I$4,'01_Raw_Actual'!$F$6:$F$569,$A19) -> -125.57217 | J19: =SUMIFS('01_Raw_Actual'!$G$6:$G$569,'01_Raw_Actual'!$A$6:$A$569,J$4,'01_Raw_Actual'!$F$6:$F$569,$A19) -> -129.89079 | ... N19: =SUMIFS('01_Raw_Actual'!$G$6:$G$569,'01_Raw_Actual'!$A$6:$A$569,N$4,'01_Raw_Actual'!$F$6:$F$569,$A19) -> -134.40777 | O19: =SUM(C19:N19) -> -1560.4447
B20: PAT | C20: =C18+C19 -> 525.88007 | D20: =D18+D19 -> 525.88007 | E20: =E18+E19 -> 496.07363 | F20: =F18+F19 -> 553.50988 | G20: =G18+G19 -> 555.71616 | H20: =H18+H19 -> 548.30308 | I20: =I18+I19 -> 576.24672 | J20: =J18+J19 -> 596.06473 | ... N20: =N18+N19 -> 676.03445 | O20: =SUM(C20:N20) -> 7072.6229
A23: BUDGET | B23: BUDGET | C23: BUDGET | D23: BUDGET | E23: BUDGET | F23: BUDGET | G23: BUDGET | H23: BUDGET | I23: BUDGET | J23: BUDGET | K23: BUDGET | L23: BUDGET | M23: BUDGET | N23: BUDGET | O23: BUDGET
A24: REV | B24: Revenue | C24: =SUMIFS('02_Raw_Budget'!$G$6:$G$869,'02_Raw_Budget'!$A$6:$A$869,C$4,'02_Raw_Budget'!$F$6:$F$869,$A24) -> 12066.123 | D24: =SUMIFS('02_Raw_Budget'!$G$6:$G$869,'02_Raw_Budget'!$A$6:$A$869,D$4,'02_Raw_Budget'!$F$6:$F$869,$A24) -> 12066.123 | E24: =SUMIFS('02_Raw_Budget'!$G$6:$G$869,'02_Raw_Budget'!$A$6:$A$869,E$4,'02_Raw_Budget'!$F$6:$F$869,$A24) -> 10973.567 | F24: =SUMIFS('02_Raw_Budget'!$G$6:$G$869,'02_Raw_Budget'!$A$6:$A$869,F$4,'02_Raw_Budget'!$F$6:$F$869,$A24) -> 12949.881 | G24: =SUMIFS('02_Raw_Budget'!$G$6:$G$869,'02_Raw_Budget'!$A$6:$A$869,G$4,'02_Raw_Budget'!$F$6:$F$869,$A24) -> 12506.606 | H24: =SUMIFS('02_Raw_Budget'!$G$6:$G$869,'02_Raw_Budget'!$A$6:$A$869,H$4,'02_Raw_Budget'!$F$6:$F$869,$A24) -> 12707.587 | I24: =SUMIFS('02_Raw_Budget'!$G$6:$G$869,'02_Raw_Budget'!$A$6:$A$869,I$4,'02_Raw_Budget'!$F$6:$F$869,$A24) -> 12192.853 | J24: =SUMIFS('02_Raw_Budget'!$G$6:$G$869,'02_Raw_Budget'!$A$6:$A$869,J$4,'02_Raw_Budget'!$F$6:$F$869,$A24) -> 12757.833 | ... N24: =SUMIFS('02_Raw_Budget'!$G$6:$G$869,'02_Raw_Budget'!$A$6:$A$869,N$4,'02_Raw_Budget'!$F$6:$F$869,$A24) -> 13446.751 | O24: =SUM(C24:N24) -> 150000
A25: COGS | B25: COGS | C25: =SUMIFS('02_Raw_Budget'!$G$6:$G$869,'02_Raw_Budget'!$A$6:$A$869,C$4,'02_Raw_Budget'!$F$6:$F$869,$A25) -> -9604.4326 | D25: =SUMIFS('02_Raw_Budget'!$G$6:$G$869,'02_Raw_Budget'!$A$6:$A$869,D$4,'02_Raw_Budget'!$F$6:$F$869,$A25) -> -9604.4326 | E25: =SUMIFS('02_Raw_Budget'!$G$6:$G$869,'02_Raw_Budget'!$A$6:$A$869,E$4,'02_Raw_Budget'!$F$6:$F$869,$A25) -> -8734.7767 | F25: =SUMIFS('02_Raw_Budget'!$G$6:$G$869,'02_Raw_Budget'!$A$6:$A$869,F$4,'02_Raw_Budget'!$F$6:$F$869,$A25) -> -10307.89 | G25: =SUMIFS('02_Raw_Budget'!$G$6:$G$869,'02_Raw_Budget'!$A$6:$A$869,G$4,'02_Raw_Budget'!$F$6:$F$869,$A25) -> -9955.0502 | H25: =SUMIFS('02_Raw_Budget'!$G$6:$G$869,'02_Raw_Budget'!$A$6:$A$869,H$4,'02_Raw_Budget'!$F$6:$F$869,$A25) -> -10115.028 | I25: =SUMIFS('02_Raw_Budget'!$G$6:$G$869,'02_Raw_Budget'!$A$6:$A$869,I$4,'02_Raw_Budget'!$F$6:$F$869,$A25) -> -9705.3074 | J25: =SUMIFS('02_Raw_Budget'!$G$6:$G$869,'02_Raw_Budget'!$A$6:$A$869,J$4,'02_Raw_Budget'!$F$6:$F$869,$A25) -> -10155.022 | ... N25: =SUMIFS('02_Raw_Budget'!$G$6:$G$869,'02_Raw_Budget'!$A$6:$A$869,N$4,'02_Raw_Budget'!$F$6:$F$869,$A25) -> -10703.39 | O25: =SUM(C25:N25) -> -119397.5
B26: Gross Profit | C26: =C24+C25 -> 2461.6901 | D26: =D24+D25 -> 2461.6901 | E26: =E24+E25 -> 2238.7906 | F26: =F24+F25 -> 2641.9916 | G26: =G24+G25 -> 2551.5561 | H26: =H24+H25 -> 2592.5596 | I26: =I24+I25 -> 2487.5451 | J26: =J24+J25 -> 2602.8105 | ... N26: =N24+N25 -> 2743.3614 | O26: =SUM(C26:N26) -> 30602.5
B27: Gross Margin | C27: =IFERROR(C26/C24,0) -> 0.20401667 | D27: =IFERROR(D26/D24,0) -> 0.20401667 | E27: =IFERROR(E26/E24,0) -> 0.20401667 | F27: =IFERROR(F26/F24,0) -> 0.20401667 | G27: =IFERROR(G26/G24,0) -> 0.20401667 | H27: =IFERROR(H26/H24,0) -> 0.20401667 | I27: =IFERROR(I26/I24,0) -> 0.20401667 | J27: =IFERROR(J26/J24,0) -> 0.20401667 | ... O27: =IFERROR(O26/O24,0) -> 0.20401667
A28: SELL | B28: Selling Expense | C28: =SUMIFS('02_Raw_Budget'!$G$6:$G$869,'02_Raw_Budget'!$A$6:$A$869,C$4,'02_Raw_Budget'!$F$6:$F$869,$A28) -> -1713.3894 | D28: =SUMIFS('02_Raw_Budget'!$G$6:$G$869,'02_Raw_Budget'!$A$6:$A$869,D$4,'02_Raw_Budget'!$F$6:$F$869,$A28) -> -1713.3894 | E28: =SUMIFS('02_Raw_Budget'!$G$6:$G$869,'02_Raw_Budget'!$A$6:$A$869,E$4,'02_Raw_Budget'!$F$6:$F$869,$A28) -> -1558.2466 | F28: =SUMIFS('02_Raw_Budget'!$G$6:$G$869,'02_Raw_Budget'!$A$6:$A$869,F$4,'02_Raw_Budget'!$F$6:$F$869,$A28) -> -1838.8831 | G28: =SUMIFS('02_Raw_Budget'!$G$6:$G$869,'02_Raw_Budget'!$A$6:$A$869,G$4,'02_Raw_Budget'!$F$6:$F$869,$A28) -> -1775.9381 | H28: =SUMIFS('02_Raw_Budget'!$G$6:$G$869,'02_Raw_Budget'!$A$6:$A$869,H$4,'02_Raw_Budget'!$F$6:$F$869,$A28) -> -1804.4774 | I28: =SUMIFS('02_Raw_Budget'!$G$6:$G$869,'02_Raw_Budget'!$A$6:$A$869,I$4,'02_Raw_Budget'!$F$6:$F$869,$A28) -> -1731.3851 | J28: =SUMIFS('02_Raw_Budget'!$G$6:$G$869,'02_Raw_Budget'!$A$6:$A$869,J$4,'02_Raw_Budget'!$F$6:$F$869,$A28) -> -1811.6122 | ... N28: =SUMIFS('02_Raw_Budget'!$G$6:$G$869,'02_Raw_Budget'!$A$6:$A$869,N$4,'02_Raw_Budget'!$F$6:$F$869,$A28) -> -1909.4387 | O28: =SUM(C28:N28) -> -21300
A29: GA | B29: G&A | C29: =SUMIFS('02_Raw_Budget'!$G$6:$G$869,'02_Raw_Budget'!$A$6:$A$869,C$4,'02_Raw_Budget'!$F$6:$F$869,$A29) -> -325.78531 | D29: =SUMIFS('02_Raw_Budget'!$G$6:$G$869,'02_Raw_Budget'!$A$6:$A$869,D$4,'02_Raw_Budget'!$F$6:$F$869,$A29) -> -325.78531 | E29: =SUMIFS('02_Raw_Budget'!$G$6:$G$869,'02_Raw_Budget'!$A$6:$A$869,E$4,'02_Raw_Budget'!$F$6:$F$869,$A29) -> -296.28632 | F29: =SUMIFS('02_Raw_Budget'!$G$6:$G$869,'02_Raw_Budget'!$A$6:$A$869,F$4,'02_Raw_Budget'!$F$6:$F$869,$A29) -> -349.64679 | G29: =SUMIFS('02_Raw_Budget'!$G$6:$G$869,'02_Raw_Budget'!$A$6:$A$869,G$4,'02_Raw_Budget'!$F$6:$F$869,$A29) -> -337.67837 | H29: =SUMIFS('02_Raw_Budget'!$G$6:$G$869,'02_Raw_Budget'!$A$6:$A$869,H$4,'02_Raw_Budget'!$F$6:$F$869,$A29) -> -343.10486 | I29: =SUMIFS('02_Raw_Budget'!$G$6:$G$869,'02_Raw_Budget'!$A$6:$A$869,I$4,'02_Raw_Budget'!$F$6:$F$869,$A29) -> -329.20702 | J29: =SUMIFS('02_Raw_Budget'!$G$6:$G$869,'02_Raw_Budget'!$A$6:$A$869,J$4,'02_Raw_Budget'!$F$6:$F$869,$A29) -> -344.46148 | ... N29: =SUMIFS('02_Raw_Budget'!$G$6:$G$869,'02_Raw_Budget'!$A$6:$A$869,N$4,'02_Raw_Budget'!$F$6:$F$869,$A29) -> -363.06228 | O29: =SUM(C29:N29) -> -4050
B30: Operating Profit | C30: =SUM(C26,C28:C29) -> 422.5154 | D30: =SUM(D26,D28:D29) -> 422.5154 | E30: =SUM(E26,E28:E29) -> 384.25775 | F30: =SUM(F26,F28:F29) -> 453.46168 | G30: =SUM(G26,G28:G29) -> 437.93966 | H30: =SUM(H26,H28:H29) -> 444.97735 | I30: =SUM(I26,I28:I29) -> 426.95305 | J30: =SUM(J26,J28:J29) -> 446.73677 | ... N30: =SUM(N26,N28:N29) -> 470.8604 | O30: =SUM(C30:N30) -> 5252.5
A31: FIN_INC | B31: Finance Income | C31: =SUMIFS('02_Raw_Budget'!$G$6:$G$869,'02_Raw_Budget'!$A$6:$A$869,C$4,'02_Raw_Budget'!$F$6:$F$869,$A31) -> 180.99184 | D31: =SUMIFS('02_Raw_Budget'!$G$6:$G$869,'02_Raw_Budget'!$A$6:$A$869,D$4,'02_Raw_Budget'!$F$6:$F$869,$A31) -> 180.99184 | E31: =SUMIFS('02_Raw_Budget'!$G$6:$G$869,'02_Raw_Budget'!$A$6:$A$869,E$4,'02_Raw_Budget'!$F$6:$F$869,$A31) -> 164.60351 | F31: =SUMIFS('02_Raw_Budget'!$G$6:$G$869,'02_Raw_Budget'!$A$6:$A$869,F$4,'02_Raw_Budget'!$F$6:$F$869,$A31) -> 194.24822 | G31: =SUMIFS('02_Raw_Budget'!$G$6:$G$869,'02_Raw_Budget'!$A$6:$A$869,G$4,'02_Raw_Budget'!$F$6:$F$869,$A31) -> 187.59909 | H31: =SUMIFS('02_Raw_Budget'!$G$6:$G$869,'02_Raw_Budget'!$A$6:$A$869,H$4,'02_Raw_Budget'!$F$6:$F$869,$A31) -> 190.61381 | I31: =SUMIFS('02_Raw_Budget'!$G$6:$G$869,'02_Raw_Budget'!$A$6:$A$869,I$4,'02_Raw_Budget'!$F$6:$F$869,$A31) -> 182.89279 | J31: =SUMIFS('02_Raw_Budget'!$G$6:$G$869,'02_Raw_Budget'!$A$6:$A$869,J$4,'02_Raw_Budget'!$F$6:$F$869,$A31) -> 191.36749 | ... N31: =SUMIFS('02_Raw_Budget'!$G$6:$G$869,'02_Raw_Budget'!$A$6:$A$869,N$4,'02_Raw_Budget'!$F$6:$F$869,$A31) -> 201.70127 | O31: =SUM(C31:N31) -> 2250
A32: FIN_EXP | B32: Finance Expense | C32: =SUMIFS('02_Raw_Budget'!$G$6:$G$869,'02_Raw_Budget'!$A$6:$A$869,C$4,'02_Raw_Budget'!$F$6:$F$869,$A32) -> -96.528982 | D32: =SUMIFS('02_Raw_Budget'!$G$6:$G$869,'02_Raw_Budget'!$A$6:$A$869,D$4,'02_Raw_Budget'!$F$6:$F$869,$A32) -> -96.528982 | E32: =SUMIFS('02_Raw_Budget'!$G$6:$G$869,'02_Raw_Budget'!$A$6:$A$869,E$4,'02_Raw_Budget'!$F$6:$F$869,$A32) -> -87.788538 | F32: =SUMIFS('02_Raw_Budget'!$G$6:$G$869,'02_Raw_Budget'!$A$6:$A$869,F$4,'02_Raw_Budget'!$F$6:$F$869,$A32) -> -103.59905 | G32: =SUMIFS('02_Raw_Budget'!$G$6:$G$869,'02_Raw_Budget'!$A$6:$A$869,G$4,'02_Raw_Budget'!$F$6:$F$869,$A32) -> -100.05285 | H32: =SUMIFS('02_Raw_Budget'!$G$6:$G$869,'02_Raw_Budget'!$A$6:$A$869,H$4,'02_Raw_Budget'!$F$6:$F$869,$A32) -> -101.6607 | I32: =SUMIFS('02_Raw_Budget'!$G$6:$G$869,'02_Raw_Budget'!$A$6:$A$869,I$4,'02_Raw_Budget'!$F$6:$F$869,$A32) -> -97.54282 | J32: =SUMIFS('02_Raw_Budget'!$G$6:$G$869,'02_Raw_Budget'!$A$6:$A$869,J$4,'02_Raw_Budget'!$F$6:$F$869,$A32) -> -102.06266 | ... N32: =SUMIFS('02_Raw_Budget'!$G$6:$G$869,'02_Raw_Budget'!$A$6:$A$869,N$4,'02_Raw_Budget'!$F$6:$F$869,$A32) -> -107.57401 | O32: =SUM(C32:N32) -> -1200
A33: JV | B33: JV Profit/(Loss) | C33: =SUMIFS('02_Raw_Budget'!$G$6:$G$869,'02_Raw_Budget'!$A$6:$A$869,C$4,'02_Raw_Budget'!$F$6:$F$869,$A33) -> 0 | D33: =SUMIFS('02_Raw_Budget'!$G$6:$G$869,'02_Raw_Budget'!$A$6:$A$869,D$4,'02_Raw_Budget'!$F$6:$F$869,$A33) -> 0 | E33: =SUMIFS('02_Raw_Budget'!$G$6:$G$869,'02_Raw_Budget'!$A$6:$A$869,E$4,'02_Raw_Budget'!$F$6:$F$869,$A33) -> 0 | F33: =SUMIFS('02_Raw_Budget'!$G$6:$G$869,'02_Raw_Budget'!$A$6:$A$869,F$4,'02_Raw_Budget'!$F$6:$F$869,$A33) -> 0 | G33: =SUMIFS('02_Raw_Budget'!$G$6:$G$869,'02_Raw_Budget'!$A$6:$A$869,G$4,'02_Raw_Budget'!$F$6:$F$869,$A33) -> 0 | H33: =SUMIFS('02_Raw_Budget'!$G$6:$G$869,'02_Raw_Budget'!$A$6:$A$869,H$4,'02_Raw_Budget'!$F$6:$F$869,$A33) -> 0 | I33: =SUMIFS('02_Raw_Budget'!$G$6:$G$869,'02_Raw_Budget'!$A$6:$A$869,I$4,'02_Raw_Budget'!$F$6:$F$869,$A33) -> 0 | J33: =SUMIFS('02_Raw_Budget'!$G$6:$G$869,'02_Raw_Budget'!$A$6:$A$869,J$4,'02_Raw_Budget'!$F$6:$F$869,$A33) -> 0 | ... N33: =SUMIFS('02_Raw_Budget'!$G$6:$G$869,'02_Raw_Budget'!$A$6:$A$869,N$4,'02_Raw_Budget'!$F$6:$F$869,$A33) -> 0 | O33: =SUM(C33:N33) -> 0
A34: OTHER | B34: Other Net | C34: =SUMIFS('02_Raw_Budget'!$G$6:$G$869,'02_Raw_Budget'!$A$6:$A$869,C$4,'02_Raw_Budget'!$F$6:$F$869,$A34) -> -19.305796 | D34: =SUMIFS('02_Raw_Budget'!$G$6:$G$869,'02_Raw_Budget'!$A$6:$A$869,D$4,'02_Raw_Budget'!$F$6:$F$869,$A34) -> -19.305796 | E34: =SUMIFS('02_Raw_Budget'!$G$6:$G$869,'02_Raw_Budget'!$A$6:$A$869,E$4,'02_Raw_Budget'!$F$6:$F$869,$A34) -> -17.557708 | F34: =SUMIFS('02_Raw_Budget'!$G$6:$G$869,'02_Raw_Budget'!$A$6:$A$869,F$4,'02_Raw_Budget'!$F$6:$F$869,$A34) -> -20.71981 | G34: =SUMIFS('02_Raw_Budget'!$G$6:$G$869,'02_Raw_Budget'!$A$6:$A$869,G$4,'02_Raw_Budget'!$F$6:$F$869,$A34) -> -20.01057 | H34: =SUMIFS('02_Raw_Budget'!$G$6:$G$869,'02_Raw_Budget'!$A$6:$A$869,H$4,'02_Raw_Budget'!$F$6:$F$869,$A34) -> -20.33214 | I34: =SUMIFS('02_Raw_Budget'!$G$6:$G$869,'02_Raw_Budget'!$A$6:$A$869,I$4,'02_Raw_Budget'!$F$6:$F$869,$A34) -> -19.508564 | J34: =SUMIFS('02_Raw_Budget'!$G$6:$G$869,'02_Raw_Budget'!$A$6:$A$869,J$4,'02_Raw_Budget'!$F$6:$F$869,$A34) -> -20.412532 | ... N34: =SUMIFS('02_Raw_Budget'!$G$6:$G$869,'02_Raw_Budget'!$A$6:$A$869,N$4,'02_Raw_Budget'!$F$6:$F$869,$A34) -> -21.514802 | O34: =SUM(C34:N34) -> -240
B35: Profit Before Tax | C35: =SUM(C30:C34) -> 487.67246 | D35: =SUM(D30:D34) -> 487.67246 | E35: =SUM(E30:E34) -> 443.51501 | F35: =SUM(F30:F34) -> 523.39103 | G35: =SUM(G30:G34) -> 505.47534 | H35: =SUM(H30:H34) -> 513.59832 | I35: =SUM(I30:I34) -> 492.79446 | J35: =SUM(J30:J34) -> 515.62907 | ... N35: =SUM(N30:N34) -> 543.47286 | O35: =SUM(C35:N35) -> 6062.5
A36: TAX | B36: Tax Expense | C36: =SUMIFS('02_Raw_Budget'!$G$6:$G$869,'02_Raw_Budget'!$A$6:$A$869,C$4,'02_Raw_Budget'!$F$6:$F$869,$A36) -> -97.534492 | D36: =SUMIFS('02_Raw_Budget'!$G$6:$G$869,'02_Raw_Budget'!$A$6:$A$869,D$4,'02_Raw_Budget'!$F$6:$F$869,$A36) -> -97.534492 | E36: =SUMIFS('02_Raw_Budget'!$G$6:$G$869,'02_Raw_Budget'!$A$6:$A$869,E$4,'02_Raw_Budget'!$F$6:$F$869,$A36) -> -88.703002 | F36: =SUMIFS('02_Raw_Budget'!$G$6:$G$869,'02_Raw_Budget'!$A$6:$A$869,F$4,'02_Raw_Budget'!$F$6:$F$869,$A36) -> -104.67821 | G36: =SUMIFS('02_Raw_Budget'!$G$6:$G$869,'02_Raw_Budget'!$A$6:$A$869,G$4,'02_Raw_Budget'!$F$6:$F$869,$A36) -> -101.09507 | H36: =SUMIFS('02_Raw_Budget'!$G$6:$G$869,'02_Raw_Budget'!$A$6:$A$869,H$4,'02_Raw_Budget'!$F$6:$F$869,$A36) -> -102.71966 | I36: =SUMIFS('02_Raw_Budget'!$G$6:$G$869,'02_Raw_Budget'!$A$6:$A$869,I$4,'02_Raw_Budget'!$F$6:$F$869,$A36) -> -98.558891 | J36: =SUMIFS('02_Raw_Budget'!$G$6:$G$869,'02_Raw_Budget'!$A$6:$A$869,J$4,'02_Raw_Budget'!$F$6:$F$869,$A36) -> -103.12581 | ... N36: =SUMIFS('02_Raw_Budget'!$G$6:$G$869,'02_Raw_Budget'!$A$6:$A$869,N$4,'02_Raw_Budget'!$F$6:$F$869,$A36) -> -108.69457 | O36: =SUM(C36:N36) -> -1212.5
B37: PAT | C37: =C35+C36 -> 390.13797 | D37: =D35+D36 -> 390.13797 | E37: =E35+E36 -> 354.81201 | F37: =F35+F36 -> 418.71283 | G37: =G35+G36 -> 404.38027 | H37: =H35+H36 -> 410.87866 | I37: =I35+I36 -> 394.23556 | J37: =J35+J36 -> 412.50326 | ... N37: =N35+N36 -> 434.77829 | O37: =SUM(C37:N37) -> 4850
A40: VARIANCE — ACTUAL MINUS BUDGET | B40: VARIANCE — ACTUAL MINUS BUDGET | C40: VARIANCE — ACTUAL MINUS BUDGET | D40: VARIANCE — ACTUAL MINUS BUDGET | E40: VARIANCE — ACTUAL MINUS BUDGET | F40: VARIANCE — ACTUAL MINUS BUDGET | G40: VARIANCE — ACTUAL MINUS BUDGET | H40: VARIANCE — ACTUAL MINUS BUDGET | I40: VARIANCE — ACTUAL MINUS BUDGET | J40: VARIANCE — ACTUAL MINUS BUDGET | K40: VARIANCE — ACTUAL MINUS BUDGET | L40: VARIANCE — ACTUAL MINUS BUDGET | M40: VARIANCE — ACTUAL MINUS BUDGET | N40: VARIANCE — ACTUAL MINUS BUDGET | O40: VARIANCE — ACTUAL MINUS BUDGET
A41: REV | B41: Revenue | C41: =C7-C24 -> 210.8122 | D41: =D7-D24 -> 210.8122 | E41: =E7-E24 -> 607.52121 | F41: =F7-F24 -> -387.19128 | G41: =G7-G24 -> 106.15817 | H41: =H7-H24 -> -263.07323 | I41: =I7-I24 -> 682.24921 | J41: =J7-J24 -> 560.06355 | ... O41: =O7-O24 -> 5928.1456
A42: COGS | B42: COGS | C42: =C8-C25 -> -226.14633 | D42: =D8-D25 -> -226.14633 | E42: =E8-E25 -> -538.61324 | F42: =F8-F25 -> 272.66695 | G42: =G8-G25 -> -120.17261 | H42: =H8-H25 -> 174.20529 | I42: =I8-I25 -> -753.82547 | J42: =J8-J25 -> -663.8163 | ... O42: =O8-O25 -> -5528.7682
B43: Gross Profit | C43: =C9-C26 -> -15.334133 | D43: =D9-D26 -> -15.334133 | E43: =E9-E26 -> 68.907969 | F43: =F9-F26 -> -114.52433 | G43: =G9-G26 -> -14.014441 | H43: =H9-H26 -> -88.867941 | I43: =I9-I26 -> -71.576254 | J43: =J9-J26 -> -103.75275 | ... O43: =O9-O26 -> 399.3774
B44: Gross Margin | C44: =C10-C27 -> -0.004752272 | D44: =D10-D27 -> -0.004752272 | E44: =E10-E27 -> -0.004752272 | F44: =F10-F27 -> -0.0028282837 | G44: =G10-G27 -> -0.0028282837 | H44: =H10-H27 -> -0.0028282837 | I44: =I10-I27 -> -0.016370081 | J44: =J10-J27 -> -0.016370081 | ... O44: =O10-O27 -> -0.0051951051
A45: SELL | B45: Selling Expense | C45: =C11-C28 -> 217.45793 | D45: =D11-D28 -> 217.45793 | E45: =E11-E28 -> 147.10321 | F45: =F11-F28 -> 268.28404 | G45: =G11-G28 -> 199.07864 | H45: =H11-H28 -> 248.65276 | I45: =I11-I28 -> 254.69136 | J45: =J11-J28 -> 284.13278 | ... O45: =O11-O28 -> 1969.0965
A46: GA | B46: G&A | C46: =C12-C29 -> -86.877747 | D46: =D12-D29 -> -86.877747 | E46: =E12-E29 -> -92.987346 | F46: =F12-F29 -> -51.633673 | G46: =G12-G29 -> -65.201589 | H46: =H12-H29 -> -54.400807 | I46: =I12-I29 -> -32.440806 | J46: =J12-J29 -> -29.623966 | ... O46: =O12-O29 -> -546.07451
B47: Operating Profit | C47: =C13-C30 -> 115.24605 | D47: =D13-D30 -> 115.24605 | E47: =E13-E30 -> 123.02383 | F47: =F13-F30 -> 102.12604 | G47: =G13-G30 -> 119.86261 | H47: =H13-H30 -> 105.38402 | I47: =I13-I30 -> 150.6743 | J47: =J13-J30 -> 150.75607 | ... O47: =O13-O30 -> 1822.3993
A48: FIN_INC | B48: Finance Income | C48: =C14-C31 -> 54.556272 | D48: =D14-D31 -> 54.556272 | E48: =E14-E31 -> 57.593932 | F48: =F14-F31 -> 62.493121 | G48: =G14-G31 -> 70.165609 | H48: =H14-H31 -> 63.712392 | I48: =I14-I31 -> 78.492131 | J48: =J14-J31 -> 79.006857 | ... O48: =O14-O31 -> 857.34873
A49: FIN_EXP | B49: Finance Expense | C49: =C15-C32 -> -18.654915 | D49: =D15-D32 -> -18.654915 | E49: =E15-E32 -> -20.866831 | F49: =F15-F32 -> -30.795286 | G49: =G15-G32 -> -34.877178 | H49: =H15-H32 -> -31.469405 | I49: =I15-I32 -> -35.155518 | J49: =J15-J32 -> -35.199376 | ... O49: =O15-O32 -> -342.51867
A50: JV | B50: JV Profit/(Loss) | C50: =C16-C33 -> 1.063348 | D50: =D16-D33 -> 1.063348 | E50: =E16-E33 -> 1.0030783 | F50: =F16-F33 -> 3.7139212 | G50: =G16-G33 -> 3.7287248 | H50: =H16-H33 -> 3.6789848 | I50: =I16-I33 -> 1.3493619 | J50: =J16-J33 -> 1.3957685 | ... O50: =O16-O33 -> 24.351079
A51: OTHER | B51: Other Net | C51: =C17-C34 -> 17.422421 | D51: =D17-D34 -> 17.422421 | E51: =E17-E34 -> 15.781081 | F51: =F17-F34 -> 16.363266 | G51: =G17-G34 -> 15.636661 | H51: =H17-H34 -> 16.016578 | I51: =I17-I34 -> 13.664159 | J51: =J17-J34 -> 14.367129 | ... O51: =O17-O34 -> 208.98709
B52: Profit Before Tax | C52: =C18-C35 -> 169.63318 | D52: =D18-D35 -> 169.63318 | E52: =E18-E35 -> 176.53509 | F52: =F18-F35 -> 153.90107 | G52: =G18-G35 -> 174.51643 | H52: =H18-H35 -> 157.32257 | I52: =I18-I35 -> 209.02443 | J52: =J18-J35 -> 210.32645 | ... O52: =O18-O35 -> 2570.5676
A53: TAX | B53: Tax Expense | C53: =C19-C36 -> -33.891078 | D53: =D19-D36 -> -33.891078 | E53: =E19-E36 -> -35.273476 | F53: =F19-F36 -> -19.104009 | G53: =G19-G36 -> -23.18054 | H53: =H19-H36 -> -19.898146 | I53: =I19-I36 -> -27.013278 | J53: =J19-J36 -> -26.764974 | ... O53: =O19-O36 -> -347.9447
B54: PAT | C54: =C20-C37 -> 135.7421 | D54: =D20-D37 -> 135.7421 | E54: =E20-E37 -> 141.26162 | F54: =F20-F37 -> 134.79706 | G54: =G20-G37 -> 151.33589 | H54: =H20-H37 -> 137.42442 | I54: =I20-I37 -> 182.01115 | J54: =J20-J37 -> 183.56147 | ... O54: =O20-O37 -> 2222.6229

Sheet 05A_YoY_Analysis
A1: Prior-Year Analysis — FY2025 Actual vs FY2024 Actual | B1: Prior-Year Analysis — FY2025 Actual vs FY2024 Actual | C1: Prior-Year Analysis — FY2025 Actual vs FY2024 Actual | D1: Prior-Year Analysis — FY2025 Actual vs FY2024 Actual | E1: Prior-Year Analysis — FY2025 Actual vs FY2024 Actual | F1: Prior-Year Analysis — FY2025 Actual vs FY2024 Actual | G1: Prior-Year Analysis — FY2025 Actual vs FY2024 Actual | H1: Prior-Year Analysis — FY2025 Actual vs FY2024 Actual | I1: Prior-Year Analysis — FY2025 Actual vs FY2024 Actual | J1: Prior-Year Analysis — FY2025 Actual vs FY2024 Actual | K1: Prior-Year Analysis — FY2025 Actual vs FY2024 Actual | L1: Prior-Year Analysis — FY2025 Actual vs FY2024 Actual | M1: Prior-Year Analysis — FY2025 Actual vs FY2024 Actual | N1: Prior-Year Analysis — FY2025 Actual vs FY2024 Actual
A2: FY2024 annual P&L ties to the audited filing. Monthly FY2024 costs are allocated by reported revenue solely to support trend analysis. | B2: FY2024 annual P&L ties to the audited filing. Monthly FY2024 costs are allocated by reported revenue solely to support trend analysis. | C2: FY2024 annual P&L ties to the audited filing. Monthly FY2024 costs are allocated by reported revenue solely to support trend analysis. | D2: FY2024 annual P&L ties to the audited filing. Monthly FY2024 costs are allocated by reported revenue solely to support trend analysis. | E2: FY2024 annual P&L ties to the audited filing. Monthly FY2024 costs are allocated by reported revenue solely to support trend analysis. | F2: FY2024 annual P&L ties to the audited filing. Monthly FY2024 costs are allocated by reported revenue solely to support trend analysis. | G2: FY2024 annual P&L ties to the audited filing. Monthly FY2024 costs are allocated by reported revenue solely to support trend analysis. | H2: FY2024 annual P&L ties to the audited filing. Monthly FY2024 costs are allocated by reported revenue solely to support trend analysis. | I2: FY2024 annual P&L ties to the audited filing. Monthly FY2024 costs are allocated by reported revenue solely to support trend analysis. | J2: FY2024 annual P&L ties to the audited filing. Monthly FY2024 costs are allocated by reported revenue solely to support trend analysis. | K2: FY2024 annual P&L ties to the audited filing. Monthly FY2024 costs are allocated by reported revenue solely to support trend analysis. | L2: FY2024 annual P&L ties to the audited filing. Monthly FY2024 costs are allocated by reported revenue solely to support trend analysis. | M2: FY2024 annual P&L ties to the audited filing. Monthly FY2024 costs are allocated by reported revenue solely to support trend analysis. | N2: FY2024 annual P&L ties to the audited filing. Monthly FY2024 costs are allocated by reported revenue solely to support trend analysis.
A4: Annual P&L comparison | B4: Annual P&L comparison | C4: Annual P&L comparison | D4: Annual P&L comparison | E4: Annual P&L comparison | F4: Annual P&L comparison
A6: P&L line | B6: FY2024A | C6: FY2025A | D6: Var VND bn / ppt | E6: YoY % | F6: Management interpretation
A7: Revenue | B7: =SUMIFS('01_Raw_Actual'!$G$6:$G$569,'01_Raw_Actual'!$B$6:$B$569,2024,'01_Raw_Actual'!$F$6:$F$569,"REV") -> 134341.15 | C7: ='05_Monthly_P&L'!O7 -> 155928.15 | D7: =C7-B7 -> 21586.993 | E7: =IFERROR(D7/ABS(B7),0) -> 0.16068786 | F7: Scale expanded; use store productivity and category demand to explain the increase.
A8: Gross Profit | B8: =B7+SUMIFS('01_Raw_Actual'!$G$6:$G$569,'01_Raw_Actual'!$B$6:$B$569,2024,'01_Raw_Actual'!$F$6:$F$569,"COGS") -> 27499.21 | C8: ='05_Monthly_P&L'!O9 -> 31001.877 | D8: =C8-B8 -> 3502.6673 | E8: =IFERROR(D8/ABS(B8),0) -> 0.12737338 | F8: Gross profit rose despite a modest decline in gross margin.
A9: Gross Margin | B9: =IFERROR(B8/B7,0) -> 0.20469684 | C9: ='05_Monthly_P&L'!O10 -> 0.19882156 | D9: =C9-B9 -> -0.005875283 | E9: =C9-B9 -> -0.005875283 | F9: Mix and promotional intensity reduced margin versus FY2024.
A10: Selling Expense | B10: =SUMIFS('01_Raw_Actual'!$G$6:$G$569,'01_Raw_Actual'!$B$6:$B$569,2024,'01_Raw_Actual'!$F$6:$F$569,"SELL") -> -19849.838 | C10: ='05_Monthly_P&L'!O11 -> -19330.904 | D10: =C10-B10 -> 518.93407 | E10: =IFERROR(D10/ABS(B10),0) -> 0.026142988 | F10: Selling-expense productivity was the largest source of operating leverage.
A11: G&A | B11: =SUMIFS('01_Raw_Actual'!$G$6:$G$569,'01_Raw_Actual'!$B$6:$B$569,2024,'01_Raw_Actual'!$F$6:$F$569,"GA") -> -3565.7676 | C11: ='05_Monthly_P&L'!O12 -> -4596.0745 | D11: =C11-B11 -> -1030.3069 | E11: =IFERROR(D11/ABS(B11),0) -> -0.28894394 | F11: G&A grew faster than revenue; overhead discipline remains important.
A12: Operating Profit | B12: =SUM(B8,B10:B11) -> 4083.6049 | C12: ='05_Monthly_P&L'!O13 -> 7074.8993 | D12: =C12-B12 -> 2991.2945 | E12: =IFERROR(D12/ABS(B12),0) -> 0.7325132 | F12: Operating leverage converted revenue growth into faster operating-profit growth.
A13: Profit Before Tax | B13: =SUMIFS('01_Raw_Actual'!$G$6:$G$569,'01_Raw_Actual'!$B$6:$B$569,2024)-SUMIFS('01_Raw_Actual'!$G$6:$G$569,'01_Raw_Actual'!$B$6:$B$569,2024,'01_Raw_Actual'!$F$6:$F$569,"TAX") -> 4825.763 | C13: ='05_Monthly_P&L'!O18 -> 8633.0676 | D13: =C13-B13 -> 3807.3046 | E13: =IFERROR(D13/ABS(B13),0) -> 0.7889539 | F13: Operating improvement and finance income supported the PBT step-up.
A14: PAT | B14: =SUMIFS('01_Raw_Actual'!$G$6:$G$569,'01_Raw_Actual'!$B$6:$B$569,2024) -> 3733.2882 | C14: ='05_Monthly_P&L'!O20 -> 7072.6229 | D14: =C14-B14 -> 3339.3347 | E14: =IFERROR(D14/ABS(B14),0) -> 0.89447545 | F14: PAT growth materially exceeded revenue growth.
A17: Revenue growth | C17: PAT growth | E17: Gross-margin change | G17: Selling-expense ratio improvement
A18: =E7 -> 0.16068786 | C18: =E14 -> 0.89447545 | E18: =D9 -> -0.005875283 | G18: =ABS(B10/B7)-ABS(C10/C7) -> 0.023783789
I23: Month | J23: FY2024A | K23: FY2025A
I24: Jan | J24: =SUMIFS('01_Raw_Actual'!$G$6:$G$569,'01_Raw_Actual'!$B$6:$B$569,2024,'01_Raw_Actual'!$C$6:$C$569,1,'01_Raw_Actual'!$F$6:$F$569,"REV") -> 10806.512 | K24: =SUMIFS('01_Raw_Actual'!$G$6:$G$569,'01_Raw_Actual'!$B$6:$B$569,2025,'01_Raw_Actual'!$C$6:$C$569,1,'01_Raw_Actual'!$F$6:$F$569,"REV") -> 12276.935
I25: Feb | J25: =SUMIFS('01_Raw_Actual'!$G$6:$G$569,'01_Raw_Actual'!$B$6:$B$569,2024,'01_Raw_Actual'!$C$6:$C$569,2,'01_Raw_Actual'!$F$6:$F$569,"REV") -> 10806.512 | K25: =SUMIFS('01_Raw_Actual'!$G$6:$G$569,'01_Raw_Actual'!$B$6:$B$569,2025,'01_Raw_Actual'!$C$6:$C$569,2,'01_Raw_Actual'!$F$6:$F$569,"REV") -> 12276.935
I26: Mar | J26: =SUMIFS('01_Raw_Actual'!$G$6:$G$569,'01_Raw_Actual'!$B$6:$B$569,2024,'01_Raw_Actual'!$C$6:$C$569,3,'01_Raw_Actual'!$F$6:$F$569,"REV") -> 9828.0112 | K26: =SUMIFS('01_Raw_Actual'!$G$6:$G$569,'01_Raw_Actual'!$B$6:$B$569,2025,'01_Raw_Actual'!$C$6:$C$569,3,'01_Raw_Actual'!$F$6:$F$569,"REV") -> 11581.088
I27: Apr | J27: =SUMIFS('01_Raw_Actual'!$G$6:$G$569,'01_Raw_Actual'!$B$6:$B$569,2024,'01_Raw_Actual'!$C$6:$C$569,4,'01_Raw_Actual'!$F$6:$F$569,"REV") -> 11598.013 | K27: =SUMIFS('01_Raw_Actual'!$G$6:$G$569,'01_Raw_Actual'!$B$6:$B$569,2025,'01_Raw_Actual'!$C$6:$C$569,4,'01_Raw_Actual'!$F$6:$F$569,"REV") -> 12562.69
I28: May | J28: =SUMIFS('01_Raw_Actual'!$G$6:$G$569,'01_Raw_Actual'!$B$6:$B$569,2024,'01_Raw_Actual'!$C$6:$C$569,5,'01_Raw_Actual'!$F$6:$F$569,"REV") -> 11201.013 | K28: =SUMIFS('01_Raw_Actual'!$G$6:$G$569,'01_Raw_Actual'!$B$6:$B$569,2025,'01_Raw_Actual'!$C$6:$C$569,5,'01_Raw_Actual'!$F$6:$F$569,"REV") -> 12612.764
I29: Jun | J29: =SUMIFS('01_Raw_Actual'!$G$6:$G$569,'01_Raw_Actual'!$B$6:$B$569,2024,'01_Raw_Actual'!$C$6:$C$569,6,'01_Raw_Actual'!$F$6:$F$569,"REV") -> 11381.013 | K29: =SUMIFS('01_Raw_Actual'!$G$6:$G$569,'01_Raw_Actual'!$B$6:$B$569,2025,'01_Raw_Actual'!$C$6:$C$569,6,'01_Raw_Actual'!$F$6:$F$569,"REV") -> 12444.514
I30: Jul | J30: =SUMIFS('01_Raw_Actual'!$G$6:$G$569,'01_Raw_Actual'!$B$6:$B$569,2024,'01_Raw_Actual'!$C$6:$C$569,7,'01_Raw_Actual'!$F$6:$F$569,"REV") -> 10920.012 | K30: =SUMIFS('01_Raw_Actual'!$G$6:$G$569,'01_Raw_Actual'!$B$6:$B$569,2025,'01_Raw_Actual'!$C$6:$C$569,7,'01_Raw_Actual'!$F$6:$F$569,"REV") -> 12875.102
I31: Aug | J31: =SUMIFS('01_Raw_Actual'!$G$6:$G$569,'01_Raw_Actual'!$B$6:$B$569,2024,'01_Raw_Actual'!$C$6:$C$569,8,'01_Raw_Actual'!$F$6:$F$569,"REV") -> 11426.013 | K31: =SUMIFS('01_Raw_Actual'!$G$6:$G$569,'01_Raw_Actual'!$B$6:$B$569,2025,'01_Raw_Actual'!$C$6:$C$569,8,'01_Raw_Actual'!$F$6:$F$569,"REV") -> 13317.896
I32: Sep | J32: =SUMIFS('01_Raw_Actual'!$G$6:$G$569,'01_Raw_Actual'!$B$6:$B$569,2024,'01_Raw_Actual'!$C$6:$C$569,9,'01_Raw_Actual'!$F$6:$F$569,"REV") -> 11800.013 | K32: =SUMIFS('01_Raw_Actual'!$G$6:$G$569,'01_Raw_Actual'!$B$6:$B$569,2025,'01_Raw_Actual'!$C$6:$C$569,9,'01_Raw_Actual'!$F$6:$F$569,"REV") -> 13659.509
I33: Oct | J33: =SUMIFS('01_Raw_Actual'!$G$6:$G$569,'01_Raw_Actual'!$B$6:$B$569,2024,'01_Raw_Actual'!$C$6:$C$569,10,'01_Raw_Actual'!$F$6:$F$569,"REV") -> 11586.013 | K33: =SUMIFS('01_Raw_Actual'!$G$6:$G$569,'01_Raw_Actual'!$B$6:$B$569,2025,'01_Raw_Actual'!$C$6:$C$569,10,'01_Raw_Actual'!$F$6:$F$569,"REV") -> 14710.731
I34: Nov | J34: =SUMIFS('01_Raw_Actual'!$G$6:$G$569,'01_Raw_Actual'!$B$6:$B$569,2024,'01_Raw_Actual'!$C$6:$C$569,11,'01_Raw_Actual'!$F$6:$F$569,"REV") -> 10945.012 | K34: =SUMIFS('01_Raw_Actual'!$G$6:$G$569,'01_Raw_Actual'!$B$6:$B$569,2025,'01_Raw_Actual'!$C$6:$C$569,11,'01_Raw_Actual'!$F$6:$F$569,"REV") -> 13878.777
I35: Dec | J35: =SUMIFS('01_Raw_Actual'!$G$6:$G$569,'01_Raw_Actual'!$B$6:$B$569,2024,'01_Raw_Actual'!$C$6:$C$569,12,'01_Raw_Actual'!$F$6:$F$569,"REV") -> 12043.014 | K35: =SUMIFS('01_Raw_Actual'!$G$6:$G$569,'01_Raw_Actual'!$B$6:$B$569,2025,'01_Raw_Actual'!$C$6:$C$569,12,'01_Raw_Actual'!$F$6:$F$569,"REV") -> 13731.204
A40: Management takeaway: FY2025 revenue grew faster than the prior year while selling-expense intensity improved materially. Gross-margin compression and faster G&A growth are the main items to monitor. | B40: Management takeaway: FY2025 revenue grew faster than the prior year while selling-expense intensity improved materially. Gross-margin compression and faster G&A growth are the main items to monitor. | C40: Management takeaway: FY2025 revenue grew faster than the prior year while selling-expense intensity improved materially. Gross-margin compression and faster G&A growth are the main items to monitor. | D40: Management takeaway: FY2025 revenue grew faster than the prior year while selling-expense intensity improved materially. Gross-margin compression and faster G&A growth are the main items to monitor. | E40: Management takeaway: FY2025 revenue grew faster than the prior year while selling-expense intensity improved materially. Gross-margin compression and faster G&A growth are the main items to monitor. | F40: Management takeaway: FY2025 revenue grew faster than the prior year while selling-expense intensity improved materially. Gross-margin compression and faster G&A growth are the main items to monitor. | G40: Management takeaway: FY2025 revenue grew faster than the prior year while selling-expense intensity improved materially. Gross-margin compression and faster G&A growth are the main items to monitor. | H40: Management takeaway: FY2025 revenue grew faster than the prior year while selling-expense intensity improved materially. Gross-margin compression and faster G&A growth are the main items to monitor.
A41: Management takeaway: FY2025 revenue grew faster than the prior year while selling-expense intensity improved materially. Gross-margin compression and faster G&A growth are the main items to monitor. | B41: Management takeaway: FY2025 revenue grew faster than the prior year while selling-expense intensity improved materially. Gross-margin compression and faster G&A growth are the main items to monitor. | C41: Management takeaway: FY2025 revenue grew faster than the prior year while selling-expense intensity improved materially. Gross-margin compression and faster G&A growth are the main items to monitor. | D41: Management takeaway: FY2025 revenue grew faster than the prior year while selling-expense intensity improved materially. Gross-margin compression and faster G&A growth are the main items to monitor. | E41: Management takeaway: FY2025 revenue grew faster than the prior year while selling-expense intensity improved materially. Gross-margin compression and faster G&A growth are the main items to monitor. | F41: Management takeaway: FY2025 revenue grew faster than the prior year while selling-expense intensity improved materially. Gross-margin compression and faster G&A growth are the main items to monitor. | G41: Management takeaway: FY2025 revenue grew faster than the prior year while selling-expense intensity improved materially. Gross-margin compression and faster G&A growth are the main items to monitor. | H41: Management takeaway: FY2025 revenue grew faster than the prior year while selling-expense intensity improved materially. Gross-margin compression and faster G&A growth are the main items to monitor.
A42: Management takeaway: FY2025 revenue grew faster than the prior year while selling-expense intensity improved materially. Gross-margin compression and faster G&A growth are the main items to monitor. | B42: Management takeaway: FY2025 revenue grew faster than the prior year while selling-expense intensity improved materially. Gross-margin compression and faster G&A growth are the main items to monitor. | C42: Management takeaway: FY2025 revenue grew faster than the prior year while selling-expense intensity improved materially. Gross-margin compression and faster G&A growth are the main items to monitor. | D42: Management takeaway: FY2025 revenue grew faster than the prior year while selling-expense intensity improved materially. Gross-margin compression and faster G&A growth are the main items to monitor. | E42: Management takeaway: FY2025 revenue grew faster than the prior year while selling-expense intensity improved materially. Gross-margin compression and faster G&A growth are the main items to monitor. | F42: Management takeaway: FY2025 revenue grew faster than the prior year while selling-expense intensity improved materially. Gross-margin compression and faster G&A growth are the main items to monitor. | G42: Management takeaway: FY2025 revenue grew faster than the prior year while selling-expense intensity improved materially. Gross-margin compression and faster G&A growth are the main items to monitor. | H42: Management takeaway: FY2025 revenue grew faster than the prior year while selling-expense intensity improved materially. Gross-margin compression and faster G&A growth are the main items to monitor.
A43: Management takeaway: FY2025 revenue grew faster than the prior year while selling-expense intensity improved materially. Gross-margin compression and faster G&A growth are the main items to monitor. | B43: Management takeaway: FY2025 revenue grew faster than the prior year while selling-expense intensity improved materially. Gross-margin compression and faster G&A growth are the main items to monitor. | C43: Management takeaway: FY2025 revenue grew faster than the prior year while selling-expense intensity improved materially. Gross-margin compression and faster G&A growth are the main items to monitor. | D43: Management takeaway: FY2025 revenue grew faster than the prior year while selling-expense intensity improved materially. Gross-margin compression and faster G&A growth are the main items to monitor. | E43: Management takeaway: FY2025 revenue grew faster than the prior year while selling-expense intensity improved materially. Gross-margin compression and faster G&A growth are the main items to monitor. | F43: Management takeaway: FY2025 revenue grew faster than the prior year while selling-expense intensity improved materially. Gross-margin compression and faster G&A growth are the main items to monitor. | G43: Management takeaway: FY2025 revenue grew faster than the prior year while selling-expense intensity improved materially. Gross-margin compression and faster G&A growth are the main items to monitor. | H43: Management takeaway: FY2025 revenue grew faster than the prior year while selling-expense intensity improved materially. Gross-margin compression and faster G&A growth are the main items to monitor.

Sheet 06_Variance_Analysis
A1: Variance Analysis — FY2025 Actual vs Budget | B1: Variance Analysis — FY2025 Actual vs Budget | C1: Variance Analysis — FY2025 Actual vs Budget | D1: Variance Analysis — FY2025 Actual vs Budget | E1: Variance Analysis — FY2025 Actual vs Budget | F1: Variance Analysis — FY2025 Actual vs Budget | G1: Variance Analysis — FY2025 Actual vs Budget | H1: Variance Analysis — FY2025 Actual vs Budget | I1: Variance Analysis — FY2025 Actual vs Budget | J1: Variance Analysis — FY2025 Actual vs Budget | K1: Variance Analysis — FY2025 Actual vs Budget | L1: Variance Analysis — FY2025 Actual vs Budget
A2: Favorable / unfavorable is based on account nature. A live PivotTable is placed at N4 after the workbook build. | B2: Favorable / unfavorable is based on account nature. A live PivotTable is placed at N4 after the workbook build. | C2: Favorable / unfavorable is based on account nature. A live PivotTable is placed at N4 after the workbook build. | D2: Favorable / unfavorable is based on account nature. A live PivotTable is placed at N4 after the workbook build. | E2: Favorable / unfavorable is based on account nature. A live PivotTable is placed at N4 after the workbook build. | F2: Favorable / unfavorable is based on account nature. A live PivotTable is placed at N4 after the workbook build. | G2: Favorable / unfavorable is based on account nature. A live PivotTable is placed at N4 after the workbook build. | H2: Favorable / unfavorable is based on account nature. A live PivotTable is placed at N4 after the workbook build. | I2: Favorable / unfavorable is based on account nature. A live PivotTable is placed at N4 after the workbook build. | J2: Favorable / unfavorable is based on account nature. A live PivotTable is placed at N4 after the workbook build. | K2: Favorable / unfavorable is based on account nature. A live PivotTable is placed at N4 after the workbook build. | L2: Favorable / unfavorable is based on account nature. A live PivotTable is placed at N4 after the workbook build. | N2: AccountCategory | O2: Revenue
A4: P&L variance summary and management commentary | B4: P&L variance summary and management commentary | C4: P&L variance summary and management commentary | D4: P&L variance summary and management commentary | E4: P&L variance summary and management commentary | F4: P&L variance summary and management commentary | G4: P&L variance summary and management commentary | H4: P&L variance summary and management commentary | I4: P&L variance summary and management commentary | N4: Sum of Amount (VND bn) | O4: Version
N5: BusinessUnit | O5: Actual | P5: Budget | Q5: Grand Total
A6: P&L line | B6: Actual | C6: Budget | D6: Var VND bn | E6: Var % | F6: F/U | G6: Primary driver | H6: Business impact | I6: Recommended action | N6: BHX | O6: 46782.107 | P6: 46500 | Q6: 93282.107
A7: Revenue | B7: ='05_Monthly_P&L'!O7 -> 155928.15 | C7: ='05_Monthly_P&L'!O24 -> 150000 | D7: =B7-C7 -> 5928.1456 | E7: =IFERROR(D7/ABS(C7),0) -> 0.039520971 | F7: =IF(D7*1>=0,"F","U") -> F | G7: Revenue exceeded plan, led by the core electronics chains and BHX. | H7: Higher gross profit and stronger fixed-cost absorption. | I7: Protect conversion and store productivity; validate BHX expansion returns. | N7: ĐMX | O7: 68304.05 | P7: 63000 | Q7: 131304.05
A8: Gross Profit | B8: ='05_Monthly_P&L'!O9 -> 31001.877 | C8: ='05_Monthly_P&L'!O26 -> 30602.5 | D8: =B8-C8 -> 399.3774 | E8: =IFERROR(D8/ABS(C8),0) -> 0.013050483 | F8: =IF(D8*1>=0,"F","U") -> F | G8: Volume growth offset part of the gross-margin shortfall. | H8: Gross profit remained above budget despite lower margin. | I8: Tighten category mix, markdown and supplier-funding reviews. | N8: Other | O8: 3586.37 | P8: 7500 | Q8: 11086.37
A9: Gross Margin | B9: ='05_Monthly_P&L'!O10 -> 0.19882156 | C9: ='05_Monthly_P&L'!O27 -> 0.20401667 | D9: =B9-C9 -> -0.0051951051 | E9: =IFERROR(D9/ABS(C9),0) -> -0.025464121 | F9: =IF(D9*1>=0,"F","U") -> U | G9: Mix and promotional intensity kept margin below budget. | H9: Each 10bp of margin is material at MWG's revenue scale. | I9: Track weekly margin by category and promotion cohort. | N9: TGDĐ | O9: 37255.618 | P9: 33000 | Q9: 70255.618
A10: Selling Expense | B10: ='05_Monthly_P&L'!O11 -> -19330.904 | C10: ='05_Monthly_P&L'!O28 -> -21300 | D10: =B10-C10 -> 1969.0965 | E10: =IFERROR(D10/ABS(C10),0) -> 0.092445843 | F10: =IF(D10*-1>=0,"F","U") -> U | G10: Selling-expense ratio was materially below the budget assumption. | H10: Largest operating-leverage contribution versus plan. | I10: Retain productivity gains without weakening service levels. | N10: Grand Total | O10: 155928.15 | P10: 150000 | Q10: 305928.15
A11: G&A | B11: ='05_Monthly_P&L'!O12 -> -4596.0745 | C11: ='05_Monthly_P&L'!O29 -> -4050 | D11: =B11-C11 -> -546.07451 | E11: =IFERROR(D11/ABS(C11),0) -> -0.13483321 | F11: =IF(D11*-1>=0,"F","U") -> F | G11: G&A ran above budget. | H11: Partly offset the selling-expense benefit. | I11: Set owner-level cost actions and monthly run-rate limits.
A12: Operating Profit | B12: ='05_Monthly_P&L'!O13 -> 7074.8993 | C12: ='05_Monthly_P&L'!O30 -> 5252.5 | D12: =B12-C12 -> 1822.3993 | E12: =IFERROR(D12/ABS(C12),0) -> 0.34695847 | F12: =IF(D12*1>=0,"F","U") -> F | G12: Revenue growth and selling-cost leverage outweighed G&A pressure. | H12: Operating profit finished above plan. | I12: Preserve margin and prevent overhead growth from re-accelerating.
A13: Profit Before Tax | B13: ='05_Monthly_P&L'!O18 -> 8633.0676 | C13: ='05_Monthly_P&L'!O35 -> 6062.5 | D13: =B13-C13 -> 2570.5676 | E13: =IFERROR(D13/ABS(C13),0) -> 0.42401115 | F13: =IF(D13*1>=0,"F","U") -> F | G13: Operating performance and finance income supported the beat. | H13: Improved earnings capacity and liquidity headroom. | I13: Separate recurring operating improvement from financial-income effects.
A14: PAT | B14: ='05_Monthly_P&L'!O20 -> 7072.6229 | C14: ='05_Monthly_P&L'!O37 -> 4850 | D14: =B14-C14 -> 2222.6229 | E14: =IFERROR(D14/ABS(C14),0) -> 0.45827276 | F14: =IF(D14*1>=0,"F","U") -> F | G14: PAT materially exceeded the official plan. | H14: Provides room for reinvestment while preserving the annual target. | I14: Use the beat to fund high-return growth, not permanent cost expansion.
A17: Revenue variance by business unit | B17: Revenue variance by business unit | C17: Revenue variance by business unit | D17: Revenue variance by business unit | E17: Revenue variance by business unit | F17: Revenue variance by business unit | G17: Revenue variance by business unit | H17: Revenue variance by business unit
A19: Business Unit | B19: Actual | C19: Budget | D19: Var VND bn | E19: Var % | F19: F/U
A20: TGDĐ | B20: =SUMIFS('01_Raw_Actual'!$G$6:$G$569,'01_Raw_Actual'!$B$6:$B$569,2025,'01_Raw_Actual'!$D$6:$D$569,A20,'01_Raw_Actual'!$F$6:$F$569,"REV") -> 37255.618 | C20: =SUMIFS('02_Raw_Budget'!$G$6:$G$869,'02_Raw_Budget'!$B$6:$B$869,2025,'02_Raw_Budget'!$D$6:$D$869,A20,'02_Raw_Budget'!$F$6:$F$869,"REV") -> 33000 | D20: =B20-C20 -> 4255.6183 | E20: =IFERROR(D20/C20,0) -> 0.12895813 | F20: =IF(D20>=0,"F","U") -> F
A21: ĐMX | B21: =SUMIFS('01_Raw_Actual'!$G$6:$G$569,'01_Raw_Actual'!$B$6:$B$569,2025,'01_Raw_Actual'!$D$6:$D$569,A21,'01_Raw_Actual'!$F$6:$F$569,"REV") -> 68304.05 | C21: =SUMIFS('02_Raw_Budget'!$G$6:$G$869,'02_Raw_Budget'!$B$6:$B$869,2025,'02_Raw_Budget'!$D$6:$D$869,A21,'02_Raw_Budget'!$F$6:$F$869,"REV") -> 63000 | D21: =B21-C21 -> 5304.05 | E21: =IFERROR(D21/C21,0) -> 0.08419127 | F21: =IF(D21>=0,"F","U") -> F
A22: BHX | B22: =SUMIFS('01_Raw_Actual'!$G$6:$G$569,'01_Raw_Actual'!$B$6:$B$569,2025,'01_Raw_Actual'!$D$6:$D$569,A22,'01_Raw_Actual'!$F$6:$F$569,"REV") -> 46782.107 | C22: =SUMIFS('02_Raw_Budget'!$G$6:$G$869,'02_Raw_Budget'!$B$6:$B$869,2025,'02_Raw_Budget'!$D$6:$D$869,A22,'02_Raw_Budget'!$F$6:$F$869,"REV") -> 46500 | D22: =B22-C22 -> 282.10738 | E22: =IFERROR(D22/C22,0) -> 0.0060668253 | F22: =IF(D22>=0,"F","U") -> F
A23: Other | B23: =SUMIFS('01_Raw_Actual'!$G$6:$G$569,'01_Raw_Actual'!$B$6:$B$569,2025,'01_Raw_Actual'!$D$6:$D$569,A23,'01_Raw_Actual'!$F$6:$F$569,"REV") -> 3586.37 | C23: =SUMIFS('02_Raw_Budget'!$G$6:$G$869,'02_Raw_Budget'!$B$6:$B$869,2025,'02_Raw_Budget'!$D$6:$D$869,A23,'02_Raw_Budget'!$F$6:$F$869,"REV") -> 7500 | D23: =B23-C23 -> -3913.63 | E23: =IFERROR(D23/C23,0) -> -0.52181733 | F23: =IF(D23>=0,"F","U") -> U
A26: Interpretation: FY2025 beat both revenue and PAT plans. Revenue outperformance was concentrated in TGDĐ/ĐMX and BHX. Commentary is analyst-prepared from public disclosures and model variances, not management commentary. | B26: Interpretation: FY2025 beat both revenue and PAT plans. Revenue outperformance was concentrated in TGDĐ/ĐMX and BHX. Commentary is analyst-prepared from public disclosures and model variances, not management commentary. | C26: Interpretation: FY2025 beat both revenue and PAT plans. Revenue outperformance was concentrated in TGDĐ/ĐMX and BHX. Commentary is analyst-prepared from public disclosures and model variances, not management commentary. | D26: Interpretation: FY2025 beat both revenue and PAT plans. Revenue outperformance was concentrated in TGDĐ/ĐMX and BHX. Commentary is analyst-prepared from public disclosures and model variances, not management commentary. | E26: Interpretation: FY2025 beat both revenue and PAT plans. Revenue outperformance was concentrated in TGDĐ/ĐMX and BHX. Commentary is analyst-prepared from public disclosures and model variances, not management commentary. | F26: Interpretation: FY2025 beat both revenue and PAT plans. Revenue outperformance was concentrated in TGDĐ/ĐMX and BHX. Commentary is analyst-prepared from public disclosures and model variances, not management commentary. | G26: Interpretation: FY2025 beat both revenue and PAT plans. Revenue outperformance was concentrated in TGDĐ/ĐMX and BHX. Commentary is analyst-prepared from public disclosures and model variances, not management commentary. | H26: Interpretation: FY2025 beat both revenue and PAT plans. Revenue outperformance was concentrated in TGDĐ/ĐMX and BHX. Commentary is analyst-prepared from public disclosures and model variances, not management commentary. | I26: Interpretation: FY2025 beat both revenue and PAT plans. Revenue outperformance was concentrated in TGDĐ/ĐMX and BHX. Commentary is analyst-prepared from public disclosures and model variances, not management commentary.
A27: Interpretation: FY2025 beat both revenue and PAT plans. Revenue outperformance was concentrated in TGDĐ/ĐMX and BHX. Commentary is analyst-prepared from public disclosures and model variances, not management commentary. | B27: Interpretation: FY2025 beat both revenue and PAT plans. Revenue outperformance was concentrated in TGDĐ/ĐMX and BHX. Commentary is analyst-prepared from public disclosures and model variances, not management commentary. | C27: Interpretation: FY2025 beat both revenue and PAT plans. Revenue outperformance was concentrated in TGDĐ/ĐMX and BHX. Commentary is analyst-prepared from public disclosures and model variances, not management commentary. | D27: Interpretation: FY2025 beat both revenue and PAT plans. Revenue outperformance was concentrated in TGDĐ/ĐMX and BHX. Commentary is analyst-prepared from public disclosures and model variances, not management commentary. | E27: Interpretation: FY2025 beat both revenue and PAT plans. Revenue outperformance was concentrated in TGDĐ/ĐMX and BHX. Commentary is analyst-prepared from public disclosures and model variances, not management commentary. | F27: Interpretation: FY2025 beat both revenue and PAT plans. Revenue outperformance was concentrated in TGDĐ/ĐMX and BHX. Commentary is analyst-prepared from public disclosures and model variances, not management commentary. | G27: Interpretation: FY2025 beat both revenue and PAT plans. Revenue outperformance was concentrated in TGDĐ/ĐMX and BHX. Commentary is analyst-prepared from public disclosures and model variances, not management commentary. | H27: Interpretation: FY2025 beat both revenue and PAT plans. Revenue outperformance was concentrated in TGDĐ/ĐMX and BHX. Commentary is analyst-prepared from public disclosures and model variances, not management commentary. | I27: Interpretation: FY2025 beat both revenue and PAT plans. Revenue outperformance was concentrated in TGDĐ/ĐMX and BHX. Commentary is analyst-prepared from public disclosures and model variances, not management commentary.
A28: Interpretation: FY2025 beat both revenue and PAT plans. Revenue outperformance was concentrated in TGDĐ/ĐMX and BHX. Commentary is analyst-prepared from public disclosures and model variances, not management commentary. | B28: Interpretation: FY2025 beat both revenue and PAT plans. Revenue outperformance was concentrated in TGDĐ/ĐMX and BHX. Commentary is analyst-prepared from public disclosures and model variances, not management commentary. | C28: Interpretation: FY2025 beat both revenue and PAT plans. Revenue outperformance was concentrated in TGDĐ/ĐMX and BHX. Commentary is analyst-prepared from public disclosures and model variances, not management commentary. | D28: Interpretation: FY2025 beat both revenue and PAT plans. Revenue outperformance was concentrated in TGDĐ/ĐMX and BHX. Commentary is analyst-prepared from public disclosures and model variances, not management commentary. | E28: Interpretation: FY2025 beat both revenue and PAT plans. Revenue outperformance was concentrated in TGDĐ/ĐMX and BHX. Commentary is analyst-prepared from public disclosures and model variances, not management commentary. | F28: Interpretation: FY2025 beat both revenue and PAT plans. Revenue outperformance was concentrated in TGDĐ/ĐMX and BHX. Commentary is analyst-prepared from public disclosures and model variances, not management commentary. | G28: Interpretation: FY2025 beat both revenue and PAT plans. Revenue outperformance was concentrated in TGDĐ/ĐMX and BHX. Commentary is analyst-prepared from public disclosures and model variances, not management commentary. | H28: Interpretation: FY2025 beat both revenue and PAT plans. Revenue outperformance was concentrated in TGDĐ/ĐMX and BHX. Commentary is analyst-prepared from public disclosures and model variances, not management commentary. | I28: Interpretation: FY2025 beat both revenue and PAT plans. Revenue outperformance was concentrated in TGDĐ/ĐMX and BHX. Commentary is analyst-prepared from public disclosures and model variances, not management commentary.
A29: Interpretation: FY2025 beat both revenue and PAT plans. Revenue outperformance was concentrated in TGDĐ/ĐMX and BHX. Commentary is analyst-prepared from public disclosures and model variances, not management commentary. | B29: Interpretation: FY2025 beat both revenue and PAT plans. Revenue outperformance was concentrated in TGDĐ/ĐMX and BHX. Commentary is analyst-prepared from public disclosures and model variances, not management commentary. | C29: Interpretation: FY2025 beat both revenue and PAT plans. Revenue outperformance was concentrated in TGDĐ/ĐMX and BHX. Commentary is analyst-prepared from public disclosures and model variances, not management commentary. | D29: Interpretation: FY2025 beat both revenue and PAT plans. Revenue outperformance was concentrated in TGDĐ/ĐMX and BHX. Commentary is analyst-prepared from public disclosures and model variances, not management commentary. | E29: Interpretation: FY2025 beat both revenue and PAT plans. Revenue outperformance was concentrated in TGDĐ/ĐMX and BHX. Commentary is analyst-prepared from public disclosures and model variances, not management commentary. | F29: Interpretation: FY2025 beat both revenue and PAT plans. Revenue outperformance was concentrated in TGDĐ/ĐMX and BHX. Commentary is analyst-prepared from public disclosures and model variances, not management commentary. | G29: Interpretation: FY2025 beat both revenue and PAT plans. Revenue outperformance was concentrated in TGDĐ/ĐMX and BHX. Commentary is analyst-prepared from public disclosures and model variances, not management commentary. | H29: Interpretation: FY2025 beat both revenue and PAT plans. Revenue outperformance was concentrated in TGDĐ/ĐMX and BHX. Commentary is analyst-prepared from public disclosures and model variances, not management commentary. | I29: Interpretation: FY2025 beat both revenue and PAT plans. Revenue outperformance was concentrated in TGDĐ/ĐMX and BHX. Commentary is analyst-prepared from public disclosures and model variances, not management commentary.

Sheet 07_Rolling_Forecast
A1: Rolling Forecast — FY2026 as of Jun-2026 | B1: Rolling Forecast — FY2026 as of Jun-2026 | C1: Rolling Forecast — FY2026 as of Jun-2026 | D1: Rolling Forecast — FY2026 as of Jun-2026 | E1: Rolling Forecast — FY2026 as of Jun-2026 | F1: Rolling Forecast — FY2026 as of Jun-2026 | G1: Rolling Forecast — FY2026 as of Jun-2026 | H1: Rolling Forecast — FY2026 as of Jun-2026 | I1: Rolling Forecast — FY2026 as of Jun-2026 | J1: Rolling Forecast — FY2026 as of Jun-2026 | K1: Rolling Forecast — FY2026 as of Jun-2026 | L1: Rolling Forecast — FY2026 as of Jun-2026 | M1: Rolling Forecast — FY2026 as of Jun-2026 | N1: Rolling Forecast — FY2026 as of Jun-2026 | O1: Rolling Forecast — FY2026 as of Jun-2026
A2: Reported revenue through Jun-2026 + scenario-based H2 forecast. Cost lines are analyst estimates, not reported 6M2026 actuals. | B2: Reported revenue through Jun-2026 + scenario-based H2 forecast. Cost lines are analyst estimates, not reported 6M2026 actuals. | C2: Reported revenue through Jun-2026 + scenario-based H2 forecast. Cost lines are analyst estimates, not reported 6M2026 actuals. | D2: Reported revenue through Jun-2026 + scenario-based H2 forecast. Cost lines are analyst estimates, not reported 6M2026 actuals. | E2: Reported revenue through Jun-2026 + scenario-based H2 forecast. Cost lines are analyst estimates, not reported 6M2026 actuals. | F2: Reported revenue through Jun-2026 + scenario-based H2 forecast. Cost lines are analyst estimates, not reported 6M2026 actuals. | G2: Reported revenue through Jun-2026 + scenario-based H2 forecast. Cost lines are analyst estimates, not reported 6M2026 actuals. | H2: Reported revenue through Jun-2026 + scenario-based H2 forecast. Cost lines are analyst estimates, not reported 6M2026 actuals. | I2: Reported revenue through Jun-2026 + scenario-based H2 forecast. Cost lines are analyst estimates, not reported 6M2026 actuals. | J2: Reported revenue through Jun-2026 + scenario-based H2 forecast. Cost lines are analyst estimates, not reported 6M2026 actuals. | K2: Reported revenue through Jun-2026 + scenario-based H2 forecast. Cost lines are analyst estimates, not reported 6M2026 actuals. | L2: Reported revenue through Jun-2026 + scenario-based H2 forecast. Cost lines are analyst estimates, not reported 6M2026 actuals. | M2: Reported revenue through Jun-2026 + scenario-based H2 forecast. Cost lines are analyst estimates, not reported 6M2026 actuals. | N2: Reported revenue through Jun-2026 + scenario-based H2 forecast. Cost lines are analyst estimates, not reported 6M2026 actuals. | O2: Reported revenue through Jun-2026 + scenario-based H2 forecast. Cost lines are analyst estimates, not reported 6M2026 actuals.
A3: Scenario | B3: Base
A5: Scenario assumptions | B5: Scenario assumptions | C5: Scenario assumptions | D5: Scenario assumptions | E5: Scenario assumptions | F5: Scenario assumptions | G5: Scenario assumptions | H5: Scenario assumptions | I5: Scenario assumptions | J5: Scenario assumptions | K5: Scenario assumptions | L5: Scenario assumptions | M5: Scenario assumptions | N5: Scenario assumptions | O5: Scenario assumptions
A6: FY2026 revenue target | B6: 185000
A7: 6M2026 reported revenue | B7: 95305
A8: H2 2025 revenue | B8: 82511
A9: Base H2 growth | B9: =(B6-B7)/B8-1 -> 0.087067179
A10: Bull / Bear spread | B10: 0.05
A11: Selected H2 growth | B11: =IF(B3="Bear",B9-B10,IF(B3="Bull",B9+B10,B9)) -> 0.087067179
A14: Code | B14: Forecast line | C14: 46023 | D14: 46054 | E14: 46082 | F14: 46113 | G14: 46143 | H14: 46174 | I14: 46204 | J14: 46235 | K14: 46266 | L14: 46296 | M14: 46327 | N14: 46357 | O14: FY2026F
A16: REV | B16: Revenue | C16: =SUMIFS('01_Raw_Actual'!$G$6:$G$569,'01_Raw_Actual'!$A$6:$A$569,C$14,'01_Raw_Actual'!$F$6:$F$569,"REV") -> 16102 | D16: =SUMIFS('01_Raw_Actual'!$G$6:$G$569,'01_Raw_Actual'!$A$6:$A$569,D$14,'01_Raw_Actual'!$F$6:$F$569,"REV") -> 16102 | E16: =SUMIFS('01_Raw_Actual'!$G$6:$G$569,'01_Raw_Actual'!$A$6:$A$569,E$14,'01_Raw_Actual'!$F$6:$F$569,"REV") -> 14304 | F16: =SUMIFS('01_Raw_Actual'!$G$6:$G$569,'01_Raw_Actual'!$A$6:$A$569,F$14,'01_Raw_Actual'!$F$6:$F$569,"REV") -> 15988 | G16: =SUMIFS('01_Raw_Actual'!$G$6:$G$569,'01_Raw_Actual'!$A$6:$A$569,G$14,'01_Raw_Actual'!$F$6:$F$569,"REV") -> 16663 | H16: =SUMIFS('01_Raw_Actual'!$G$6:$G$569,'01_Raw_Actual'!$A$6:$A$569,H$14,'01_Raw_Actual'!$F$6:$F$569,"REV") -> 16146 | I16: =12852*(1+$B$11) -> 13970.987 | J16: =13294*(1+$B$11) -> 14451.471 | K16: =13635*(1+$B$11) -> 14822.161 | L16: =14853*(1+$B$11) -> 16146.209 | M16: =14013*(1+$B$11) -> 15233.072 | N16: =13864*(1+$B$11) -> 15071.099 | O16: =SUM(C16:N16) -> 185000
A17: COGS | B17: COGS | C17: =-C16*(1-'03_Master_Data'!$F$26) -> -12833.903 | D17: =-D16*(1-'03_Master_Data'!$F$26) -> -12833.903 | E17: =-E16*(1-'03_Master_Data'!$F$26) -> -11400.829 | F17: =-F16*(1-'03_Master_Data'!$F$26) -> -12743.041 | G17: =-G16*(1-'03_Master_Data'!$F$26) -> -13281.041 | H17: =-H16*(1-'03_Master_Data'!$F$26) -> -12868.973 | I17: =-I16*(1-'03_Master_Data'!$F$26) -> -11135.406 | J17: =-J16*(1-'03_Master_Data'!$F$26) -> -11518.369 | ... N17: =-N16*(1-'03_Master_Data'!$F$26) -> -12012.236 | O17: =SUM(C17:N17) -> -147452
B18: Gross Profit | C18: =C16+C17 -> 3268.0967 | D18: =D16+D17 -> 3268.0967 | E18: =E16+E17 -> 2903.1708 | F18: =F16+F17 -> 3244.959 | G18: =G16+G17 -> 3381.9585 | H18: =H16+H17 -> 3277.0271 | I18: =I16+I17 -> 2835.5818 | J18: =J16+J17 -> 2933.1018 | ... N18: =N16+N17 -> 3058.8629 | O18: =SUM(C18:N18) -> 37548
B19: Gross Margin | C19: =IFERROR(C18/C16,0) -> 0.20296216 | D19: =IFERROR(D18/D16,0) -> 0.20296216 | E19: =IFERROR(E18/E16,0) -> 0.20296216 | F19: =IFERROR(F18/F16,0) -> 0.20296216 | G19: =IFERROR(G18/G16,0) -> 0.20296216 | H19: =IFERROR(H18/H16,0) -> 0.20296216 | I19: =IFERROR(I18/I16,0) -> 0.20296216 | J19: =IFERROR(J18/J16,0) -> 0.20296216 | ... O19: =IFERROR(O18/O16,0) -> 0.20296216
A20: SELL | B20: Selling Expense | C20: =-C16*'03_Master_Data'!$F$17 -> -1964.444 | D20: =-D16*'03_Master_Data'!$F$17 -> -1964.444 | E20: =-E16*'03_Master_Data'!$F$17 -> -1745.088 | F20: =-F16*'03_Master_Data'!$F$17 -> -1950.536 | G20: =-G16*'03_Master_Data'!$F$17 -> -2032.886 | H20: =-H16*'03_Master_Data'!$F$17 -> -1969.812 | I20: =-I16*'03_Master_Data'!$F$17 -> -1704.4605 | J20: =-J16*'03_Master_Data'!$F$17 -> -1763.0795 | ... N20: =-N16*'03_Master_Data'!$F$17 -> -1838.6741 | O20: =SUM(C20:N20) -> -22570
A21: GA | B21: G&A | C21: =-C16*'03_Master_Data'!$F$18 -> -466.958 | D21: =-D16*'03_Master_Data'!$F$18 -> -466.958 | E21: =-E16*'03_Master_Data'!$F$18 -> -414.816 | F21: =-F16*'03_Master_Data'!$F$18 -> -463.652 | G21: =-G16*'03_Master_Data'!$F$18 -> -483.227 | H21: =-H16*'03_Master_Data'!$F$18 -> -468.234 | I21: =-I16*'03_Master_Data'!$F$18 -> -405.15863 | J21: =-J16*'03_Master_Data'!$F$18 -> -419.09266 | ... N21: =-N16*'03_Master_Data'!$F$18 -> -437.06188 | O21: =SUM(C21:N21) -> -5365
B22: Operating Profit | C22: =SUM(C18,C20:C21) -> 836.69474 | D22: =SUM(D18,D20:D21) -> 836.69474 | E22: =SUM(E18,E20:E21) -> 743.26677 | F22: =SUM(F18,F20:F21) -> 830.77105 | G22: =SUM(G18,G20:G21) -> 865.84551 | H22: =SUM(H18,H20:H21) -> 838.98107 | I22: =SUM(I18,I20:I21) -> 725.96271 | J22: =SUM(J18,J20:J21) -> 750.92968 | ... N22: =SUM(N18,N20:N21) -> 783.12691 | O22: =SUM(C22:N22) -> 9613
A23: FIN_INC | B23: Finance Income | C23: =C16*'03_Master_Data'!$F$19 -> 322.04 | D23: =D16*'03_Master_Data'!$F$19 -> 322.04 | E23: =E16*'03_Master_Data'!$F$19 -> 286.08 | F23: =F16*'03_Master_Data'!$F$19 -> 319.76 | G23: =G16*'03_Master_Data'!$F$19 -> 333.26 | H23: =H16*'03_Master_Data'!$F$19 -> 322.92 | I23: =I16*'03_Master_Data'!$F$19 -> 279.41975 | J23: =J16*'03_Master_Data'!$F$19 -> 289.02942 | ... N23: =N16*'03_Master_Data'!$F$19 -> 301.42199 | O23: =SUM(C23:N23) -> 3700
A24: FIN_EXP | B24: Finance Expense | C24: =-C16*'03_Master_Data'!$F$20 -> -161.02 | D24: =-D16*'03_Master_Data'!$F$20 -> -161.02 | E24: =-E16*'03_Master_Data'!$F$20 -> -143.04 | F24: =-F16*'03_Master_Data'!$F$20 -> -159.88 | G24: =-G16*'03_Master_Data'!$F$20 -> -166.63 | H24: =-H16*'03_Master_Data'!$F$20 -> -161.46 | I24: =-I16*'03_Master_Data'!$F$20 -> -139.70987 | J24: =-J16*'03_Master_Data'!$F$20 -> -144.51471 | ... N24: =-N16*'03_Master_Data'!$F$20 -> -150.71099 | O24: =SUM(C24:N24) -> -1850
A25: JV | B25: JV Profit | C25: =C16*'03_Master_Data'!$F$21 -> 3.2204 | D25: =D16*'03_Master_Data'!$F$21 -> 3.2204 | E25: =E16*'03_Master_Data'!$F$21 -> 2.8608 | F25: =F16*'03_Master_Data'!$F$21 -> 3.1976 | G25: =G16*'03_Master_Data'!$F$21 -> 3.3326 | H25: =H16*'03_Master_Data'!$F$21 -> 3.2292 | I25: =I16*'03_Master_Data'!$F$21 -> 2.7941975 | J25: =J16*'03_Master_Data'!$F$21 -> 2.8902942 | ... N25: =N16*'03_Master_Data'!$F$21 -> 3.0142199 | O25: =SUM(C25:N25) -> 37
A26: OTHER | B26: Other Net | C26: =C16*'03_Master_Data'!$F$22 -> 0 | D26: =D16*'03_Master_Data'!$F$22 -> 0 | E26: =E16*'03_Master_Data'!$F$22 -> 0 | F26: =F16*'03_Master_Data'!$F$22 -> 0 | G26: =G16*'03_Master_Data'!$F$22 -> 0 | H26: =H16*'03_Master_Data'!$F$22 -> 0 | I26: =I16*'03_Master_Data'!$F$22 -> 0 | J26: =J16*'03_Master_Data'!$F$22 -> 0 | ... N26: =N16*'03_Master_Data'!$F$22 -> 0 | O26: =SUM(C26:N26) -> 0
B27: PBT | C27: =SUM(C22:C26) -> 1000.9351 | D27: =SUM(D22:D26) -> 1000.9351 | E27: =SUM(E22:E26) -> 889.16757 | F27: =SUM(F22:F26) -> 993.84865 | G27: =SUM(G22:G26) -> 1035.8081 | H27: =SUM(H22:H26) -> 1003.6703 | I27: =SUM(I22:I26) -> 868.46678 | J27: =SUM(J22:J26) -> 898.33469 | ... N27: =SUM(N22:N26) -> 936.85212 | O27: =SUM(C27:N27) -> 11500
A28: TAX | B28: Tax Expense | C28: =-C27*'03_Master_Data'!$F$23 -> -200.18703 | D28: =-D27*'03_Master_Data'!$F$23 -> -200.18703 | E28: =-E27*'03_Master_Data'!$F$23 -> -177.83351 | F28: =-F27*'03_Master_Data'!$F$23 -> -198.76973 | G28: =-G27*'03_Master_Data'!$F$23 -> -207.16162 | H28: =-H27*'03_Master_Data'!$F$23 -> -200.73405 | I28: =-I27*'03_Master_Data'!$F$23 -> -173.69336 | J28: =-J27*'03_Master_Data'!$F$23 -> -179.66694 | ... N28: =-N27*'03_Master_Data'!$F$23 -> -187.37042 | O28: =SUM(C28:N28) -> -2300
B29: PAT | C29: =C27+C28 -> 800.74811 | D29: =D27+D28 -> 800.74811 | E29: =E27+E28 -> 711.33405 | F29: =F27+F28 -> 795.07892 | G29: =G27+G28 -> 828.64649 | H29: =H27+H28 -> 802.93622 | I29: =I27+I28 -> 694.77343 | J29: =J27+J28 -> 718.66775 | ... N29: =N27+N28 -> 749.4817 | O29: =SUM(C29:N29) -> 9200
B30: Cumulative Revenue | C30: =C16 -> 16102 | D30: =C30+D16 -> 32204 | E30: =D30+E16 -> 46508 | F30: =E30+F16 -> 62496 | G30: =F30+G16 -> 79159 | H30: =G30+H16 -> 95305 | I30: =H30+I16 -> 109275.99 | J30: =I30+J16 -> 123727.46 | K30: =J30+K16 -> 138549.62 | ... N30: =M30+N16 -> 185000 | O30: =N30 -> 185000
A33: Forecast output | B33: Forecast output | C33: Forecast output | D33: Forecast output | E33: Forecast output | F33: Forecast output
A35: FY2026F revenue | B35: =O16 -> 185000
A36: Revenue plan | B36: 185000
A37: Achievement | B37: =B35/B36 -> 1
A38: FY2026F PAT | B38: =O29 -> 9200
A39: PAT plan | B39: 9200

Sheet 07A_Forecast_Variance
A1: FY2026 Forecast vs Budget | B1: FY2026 Forecast vs Budget | C1: FY2026 Forecast vs Budget | D1: FY2026 Forecast vs Budget | E1: FY2026 Forecast vs Budget | F1: FY2026 Forecast vs Budget | G1: FY2026 Forecast vs Budget | H1: FY2026 Forecast vs Budget | I1: FY2026 Forecast vs Budget | J1: FY2026 Forecast vs Budget | K1: FY2026 Forecast vs Budget | L1: FY2026 Forecast vs Budget | M1: FY2026 Forecast vs Budget | N1: FY2026 Forecast vs Budget | O1: FY2026 Forecast vs Budget
A2: Budget is analyst-phased to MWG's official FY2026 revenue and PAT targets. Forecast combines reported 6M2026 revenue with scenario-based H2 estimates. | B2: Budget is analyst-phased to MWG's official FY2026 revenue and PAT targets. Forecast combines reported 6M2026 revenue with scenario-based H2 estimates. | C2: Budget is analyst-phased to MWG's official FY2026 revenue and PAT targets. Forecast combines reported 6M2026 revenue with scenario-based H2 estimates. | D2: Budget is analyst-phased to MWG's official FY2026 revenue and PAT targets. Forecast combines reported 6M2026 revenue with scenario-based H2 estimates. | E2: Budget is analyst-phased to MWG's official FY2026 revenue and PAT targets. Forecast combines reported 6M2026 revenue with scenario-based H2 estimates. | F2: Budget is analyst-phased to MWG's official FY2026 revenue and PAT targets. Forecast combines reported 6M2026 revenue with scenario-based H2 estimates. | G2: Budget is analyst-phased to MWG's official FY2026 revenue and PAT targets. Forecast combines reported 6M2026 revenue with scenario-based H2 estimates. | H2: Budget is analyst-phased to MWG's official FY2026 revenue and PAT targets. Forecast combines reported 6M2026 revenue with scenario-based H2 estimates. | I2: Budget is analyst-phased to MWG's official FY2026 revenue and PAT targets. Forecast combines reported 6M2026 revenue with scenario-based H2 estimates. | J2: Budget is analyst-phased to MWG's official FY2026 revenue and PAT targets. Forecast combines reported 6M2026 revenue with scenario-based H2 estimates. | K2: Budget is analyst-phased to MWG's official FY2026 revenue and PAT targets. Forecast combines reported 6M2026 revenue with scenario-based H2 estimates. | L2: Budget is analyst-phased to MWG's official FY2026 revenue and PAT targets. Forecast combines reported 6M2026 revenue with scenario-based H2 estimates. | M2: Budget is analyst-phased to MWG's official FY2026 revenue and PAT targets. Forecast combines reported 6M2026 revenue with scenario-based H2 estimates. | N2: Budget is analyst-phased to MWG's official FY2026 revenue and PAT targets. Forecast combines reported 6M2026 revenue with scenario-based H2 estimates. | O2: Budget is analyst-phased to MWG's official FY2026 revenue and PAT targets. Forecast combines reported 6M2026 revenue with scenario-based H2 estimates.
A3: Selected scenario | B3: ='07_Rolling_Forecast'!B3 -> Base
A5: Forecast-to-budget summary | B5: Forecast-to-budget summary | C5: Forecast-to-budget summary | D5: Forecast-to-budget summary | E5: Forecast-to-budget summary | F5: Forecast-to-budget summary | G5: Forecast-to-budget summary | H5: Forecast-to-budget summary | I5: Forecast-to-budget summary
A6: 6M revenue vs Budget | C6: H2 revenue vs Budget | E6: FY revenue variance | G6: FY PAT variance
A7: =IFERROR(SUM('07_Rolling_Forecast'!C16:H16)/SUMIFS('02_Raw_Budget'!$G$6:$G$869,'02_Raw_Budget'!$B$6:$B$869,2026,'02_Raw_Budget'!$C$6:$C$869,"<=6",'02_Raw_Budget'!$F$6:$F$869,"REV")-1,0) -> 0.092265484 | C7: =IFERROR(SUM('07_Rolling_Forecast'!I16:N16)/SUMIFS('02_Raw_Budget'!$G$6:$G$869,'02_Raw_Budget'!$B$6:$B$869,2026,'02_Raw_Budget'!$C$6:$C$869,">6",'02_Raw_Budget'!$F$6:$F$869,"REV")-1,0) -> -0.082362524 | E7: =D16 -> 0 | G7: =D23 -> 1.4551915e-11
A13: Full-year P&L variance and decision commentary | B13: Full-year P&L variance and decision commentary | C13: Full-year P&L variance and decision commentary | D13: Full-year P&L variance and decision commentary | E13: Full-year P&L variance and decision commentary | F13: Full-year P&L variance and decision commentary | G13: Full-year P&L variance and decision commentary | H13: Full-year P&L variance and decision commentary | I13: Full-year P&L variance and decision commentary
K14: Month | L14: Forecast | M14: Budget
A15: P&L line | B15: Forecast | C15: Budget | D15: Var VND bn / ppt | E15: Var % | F15: F/U/N | G15: Primary driver | H15: Business impact | I15: Recommended action | K15: Jan-26 | L15: ='07_Rolling_Forecast'!C16 -> 16102 | M15: =SUMIFS('02_Raw_Budget'!$G$6:$G$869,'02_Raw_Budget'!$B$6:$B$869,2026,'02_Raw_Budget'!$C$6:$C$869,1,'02_Raw_Budget'!$F$6:$F$869,"REV") -> 14526.017
A16: Revenue | B16: ='07_Rolling_Forecast'!O16 -> 185000 | C16: =SUMIFS('02_Raw_Budget'!$G$6:$G$869,'02_Raw_Budget'!$B$6:$B$869,2026,'02_Raw_Budget'!$F$6:$F$869,"REV") -> 185000 | D16: =B16-C16 -> 0 | E16: =IFERROR(D16/ABS(C16),0) -> 0 | F16: =IF(ABS(D16)<0.1,"N",IF(D16*1>=0,"F","U")) -> N | G16: 6M actual plus selected H2 scenario versus budget phasing. | H16: Determines whether annual guidance is met. | I16: Review H2 exit rate monthly and update the scenario when actuals arrive. | K16: Feb-26 | L16: ='07_Rolling_Forecast'!D16 -> 16102 | M16: =SUMIFS('02_Raw_Budget'!$G$6:$G$869,'02_Raw_Budget'!$B$6:$B$869,2026,'02_Raw_Budget'!$C$6:$C$869,2,'02_Raw_Budget'!$F$6:$F$869,"REV") -> 14526.017
A17: Gross Profit | B17: ='07_Rolling_Forecast'!O18 -> 37548 | C17: =C16+SUMIFS('02_Raw_Budget'!$G$6:$G$869,'02_Raw_Budget'!$B$6:$B$869,2026,'02_Raw_Budget'!$F$6:$F$869,"COGS") -> 37548 | D17: =B17-C17 -> 0 | E17: =IFERROR(D17/ABS(C17),0) -> 0 | F17: =IF(ABS(D17)<0.1,"N",IF(D17*1>=0,"F","U")) -> N | G17: Revenue phasing and the gross-margin assumption drive gross profit. | H17: Gross-profit variance funds or constrains opex capacity. | I17: Refresh category mix and supplier-funding assumptions. | K17: Mar-26 | L17: ='07_Rolling_Forecast'!E16 -> 14304 | M17: =SUMIFS('02_Raw_Budget'!$G$6:$G$869,'02_Raw_Budget'!$B$6:$B$869,2026,'02_Raw_Budget'!$C$6:$C$869,3,'02_Raw_Budget'!$F$6:$F$869,"REV") -> 13702.695
A18: Gross Margin | B18: ='07_Rolling_Forecast'!O19 -> 0.20296216 | C18: =IFERROR(C17/C16,0) -> 0.20296216 | D18: =B18-C18 -> 0 | E18: =B18-C18 -> 0 | F18: =IF(ABS(D18)<0.0001,"N",IF(D18*1>=0,"F","U")) -> N | G18: Plan and forecast currently share the same margin assumption. | H18: No annual margin variance appears until the assumption changes. | I18: Replace the assumption with reported margin evidence when available. | K18: Apr-26 | L18: ='07_Rolling_Forecast'!F16 -> 15988 | M18: =SUMIFS('02_Raw_Budget'!$G$6:$G$869,'02_Raw_Budget'!$B$6:$B$869,2026,'02_Raw_Budget'!$C$6:$C$869,4,'02_Raw_Budget'!$F$6:$F$869,"REV") -> 14860.085
A19: Selling Expense | B19: ='07_Rolling_Forecast'!O20 -> -22570 | C19: =SUMIFS('02_Raw_Budget'!$G$6:$G$869,'02_Raw_Budget'!$B$6:$B$869,2026,'02_Raw_Budget'!$F$6:$F$869,"SELL") -> -22570 | D19: =B19-C19 -> 0 | E19: =IFERROR(D19/ABS(C19),0) -> 0 | F19: =IF(ABS(D19)<0.1,"N",IF(D19*-1>=0,"F","U")) -> N | G19: Selling expense scales with forecast revenue. | H19: Scenario changes flow directly into operating profit. | I19: Add owner-level opex inputs when internal data becomes available. | K19: May-26 | L19: ='07_Rolling_Forecast'!G16 -> 16663 | M19: =SUMIFS('02_Raw_Budget'!$G$6:$G$869,'02_Raw_Budget'!$B$6:$B$869,2026,'02_Raw_Budget'!$C$6:$C$869,5,'02_Raw_Budget'!$F$6:$F$869,"REV") -> 14919.317
A20: G&A | B20: ='07_Rolling_Forecast'!O21 -> -5365 | C20: =SUMIFS('02_Raw_Budget'!$G$6:$G$869,'02_Raw_Budget'!$B$6:$B$869,2026,'02_Raw_Budget'!$F$6:$F$869,"GA") -> -5365 | D20: =B20-C20 -> 0 | E20: =IFERROR(D20/ABS(C20),0) -> 0 | F20: =IF(ABS(D20)<0.1,"N",IF(D20*-1>=0,"F","U")) -> N | G20: G&A scales with forecast revenue. | H20: Higher growth can be diluted by overhead expansion. | I20: Set a fixed-versus-variable G&A split for the next refresh. | K20: Jun-26 | L20: ='07_Rolling_Forecast'!H16 -> 16146 | M20: =SUMIFS('02_Raw_Budget'!$G$6:$G$869,'02_Raw_Budget'!$B$6:$B$869,2026,'02_Raw_Budget'!$C$6:$C$869,6,'02_Raw_Budget'!$F$6:$F$869,"REV") -> 14720.298
A21: Operating Profit | B21: ='07_Rolling_Forecast'!O22 -> 9613 | C21: =SUM(C17,C19:C20) -> 9613 | D21: =B21-C21 -> 1.6370905e-11 | E21: =IFERROR(D21/ABS(C21),0) -> 1.7029964e-15 | F21: =IF(ABS(D21)<0.1,"N",IF(D21*1>=0,"F","U")) -> N | G21: Revenue scenario drives the annual operating-profit variance. | H21: Shows operating leverage under Bull and Bear cases. | I21: Use monthly run-rate thresholds for early escalation. | K21: Jul-26 | L21: ='07_Rolling_Forecast'!I16 -> 13970.987 | M21: =SUMIFS('02_Raw_Budget'!$G$6:$G$869,'02_Raw_Budget'!$B$6:$B$869,2026,'02_Raw_Budget'!$C$6:$C$869,7,'02_Raw_Budget'!$F$6:$F$869,"REV") -> 15224.953
A22: PBT | B22: ='07_Rolling_Forecast'!O27 -> 11500 | C22: =SUMIFS('02_Raw_Budget'!$G$6:$G$869,'02_Raw_Budget'!$B$6:$B$869,2026)-SUMIFS('02_Raw_Budget'!$G$6:$G$869,'02_Raw_Budget'!$B$6:$B$869,2026,'02_Raw_Budget'!$F$6:$F$869,"TAX") -> 11500 | D22: =B22-C22 -> 1.4551915e-11 | E22: =IFERROR(D22/ABS(C22),0) -> 1.2653839e-15 | F22: =IF(ABS(D22)<0.1,"N",IF(D22*1>=0,"F","U")) -> N | G22: Operating result plus finance and JV assumptions drive PBT. | H22: Separates operating delivery from non-operating support. | I22: Track recurring versus non-recurring finance income. | K22: Aug-26 | L22: ='07_Rolling_Forecast'!J16 -> 14451.471 | M22: =SUMIFS('02_Raw_Budget'!$G$6:$G$869,'02_Raw_Budget'!$B$6:$B$869,2026,'02_Raw_Budget'!$C$6:$C$869,8,'02_Raw_Budget'!$F$6:$F$869,"REV") -> 15748.562
A23: PAT | B23: ='07_Rolling_Forecast'!O29 -> 9200 | C23: =SUMIFS('02_Raw_Budget'!$G$6:$G$869,'02_Raw_Budget'!$B$6:$B$869,2026) -> 9200 | D23: =B23-C23 -> 1.4551915e-11 | E23: =IFERROR(D23/ABS(C23),0) -> 1.5817299e-15 | F23: =IF(ABS(D23)<0.1,"N",IF(D23*1>=0,"F","U")) -> N | G23: Base is calibrated to official PAT guidance; Bull/Bear create variance. | H23: Provides a clear earnings range around management's target. | I23: Communicate the scenario, gap and corrective action together. | K23: Sep-26 | L23: ='07_Rolling_Forecast'!K16 -> 14822.161 | M23: =SUMIFS('02_Raw_Budget'!$G$6:$G$869,'02_Raw_Budget'!$B$6:$B$869,2026,'02_Raw_Budget'!$C$6:$C$869,9,'02_Raw_Budget'!$F$6:$F$869,"REV") -> 16152.524
K24: Oct-26 | L24: ='07_Rolling_Forecast'!L16 -> 16146.209 | M24: =SUMIFS('02_Raw_Budget'!$G$6:$G$869,'02_Raw_Budget'!$B$6:$B$869,2026,'02_Raw_Budget'!$C$6:$C$869,10,'02_Raw_Budget'!$F$6:$F$869,"REV") -> 17595.411
K25: Nov-26 | L25: ='07_Rolling_Forecast'!M16 -> 15233.072 | M25: =SUMIFS('02_Raw_Budget'!$G$6:$G$869,'02_Raw_Budget'!$B$6:$B$869,2026,'02_Raw_Budget'!$C$6:$C$869,11,'02_Raw_Budget'!$F$6:$F$869,"REV") -> 16600.316
K26: Dec-26 | L26: ='07_Rolling_Forecast'!N16 -> 15071.099 | M26: =SUMIFS('02_Raw_Budget'!$G$6:$G$869,'02_Raw_Budget'!$B$6:$B$869,2026,'02_Raw_Budget'!$C$6:$C$869,12,'02_Raw_Budget'!$F$6:$F$869,"REV") -> 16423.805
I28: Base-case annual revenue and PAT equal Budget by construction: H2 growth and P&L assumptions are solved to MWG's official guidance. The monthly phasing still differs, and Bull/Bear scenarios create full-year variance. | J28: Base-case annual revenue and PAT equal Budget by construction: H2 growth and P&L assumptions are solved to MWG's official guidance. The monthly phasing still differs, and Bull/Bear scenarios create full-year variance. | K28: Base-case annual revenue and PAT equal Budget by construction: H2 growth and P&L assumptions are solved to MWG's official guidance. The monthly phasing still differs, and Bull/Bear scenarios create full-year variance. | L28: Base-case annual revenue and PAT equal Budget by construction: H2 growth and P&L assumptions are solved to MWG's official guidance. The monthly phasing still differs, and Bull/Bear scenarios create full-year variance. | M28: Base-case annual revenue and PAT equal Budget by construction: H2 growth and P&L assumptions are solved to MWG's official guidance. The monthly phasing still differs, and Bull/Bear scenarios create full-year variance. | N28: Base-case annual revenue and PAT equal Budget by construction: H2 growth and P&L assumptions are solved to MWG's official guidance. The monthly phasing still differs, and Bull/Bear scenarios create full-year variance. | O28: Base-case annual revenue and PAT equal Budget by construction: H2 growth and P&L assumptions are solved to MWG's official guidance. The monthly phasing still differs, and Bull/Bear scenarios create full-year variance.
I29: Base-case annual revenue and PAT equal Budget by construction: H2 growth and P&L assumptions are solved to MWG's official guidance. The monthly phasing still differs, and Bull/Bear scenarios create full-year variance. | J29: Base-case annual revenue and PAT equal Budget by construction: H2 growth and P&L assumptions are solved to MWG's official guidance. The monthly phasing still differs, and Bull/Bear scenarios create full-year variance. | K29: Base-case annual revenue and PAT equal Budget by construction: H2 growth and P&L assumptions are solved to MWG's official guidance. The monthly phasing still differs, and Bull/Bear scenarios create full-year variance. | L29: Base-case annual revenue and PAT equal Budget by construction: H2 growth and P&L assumptions are solved to MWG's official guidance. The monthly phasing still differs, and Bull/Bear scenarios create full-year variance. | M29: Base-case annual revenue and PAT equal Budget by construction: H2 growth and P&L assumptions are solved to MWG's official guidance. The monthly phasing still differs, and Bull/Bear scenarios create full-year variance. | N29: Base-case annual revenue and PAT equal Budget by construction: H2 growth and P&L assumptions are solved to MWG's official guidance. The monthly phasing still differs, and Bull/Bear scenarios create full-year variance. | O29: Base-case annual revenue and PAT equal Budget by construction: H2 growth and P&L assumptions are solved to MWG's official guidance. The monthly phasing still differs, and Bull/Bear scenarios create full-year variance.
I30: Base-case annual revenue and PAT equal Budget by construction: H2 growth and P&L assumptions are solved to MWG's official guidance. The monthly phasing still differs, and Bull/Bear scenarios create full-year variance. | J30: Base-case annual revenue and PAT equal Budget by construction: H2 growth and P&L assumptions are solved to MWG's official guidance. The monthly phasing still differs, and Bull/Bear scenarios create full-year variance. | K30: Base-case annual revenue and PAT equal Budget by construction: H2 growth and P&L assumptions are solved to MWG's official guidance. The monthly phasing still differs, and Bull/Bear scenarios create full-year variance. | L30: Base-case annual revenue and PAT equal Budget by construction: H2 growth and P&L assumptions are solved to MWG's official guidance. The monthly phasing still differs, and Bull/Bear scenarios create full-year variance. | M30: Base-case annual revenue and PAT equal Budget by construction: H2 growth and P&L assumptions are solved to MWG's official guidance. The monthly phasing still differs, and Bull/Bear scenarios create full-year variance. | N30: Base-case annual revenue and PAT equal Budget by construction: H2 growth and P&L assumptions are solved to MWG's official guidance. The monthly phasing still differs, and Bull/Bear scenarios create full-year variance. | O30: Base-case annual revenue and PAT equal Budget by construction: H2 growth and P&L assumptions are solved to MWG's official guidance. The monthly phasing still differs, and Bull/Bear scenarios create full-year variance.
I31: Base-case annual revenue and PAT equal Budget by construction: H2 growth and P&L assumptions are solved to MWG's official guidance. The monthly phasing still differs, and Bull/Bear scenarios create full-year variance. | J31: Base-case annual revenue and PAT equal Budget by construction: H2 growth and P&L assumptions are solved to MWG's official guidance. The monthly phasing still differs, and Bull/Bear scenarios create full-year variance. | K31: Base-case annual revenue and PAT equal Budget by construction: H2 growth and P&L assumptions are solved to MWG's official guidance. The monthly phasing still differs, and Bull/Bear scenarios create full-year variance. | L31: Base-case annual revenue and PAT equal Budget by construction: H2 growth and P&L assumptions are solved to MWG's official guidance. The monthly phasing still differs, and Bull/Bear scenarios create full-year variance. | M31: Base-case annual revenue and PAT equal Budget by construction: H2 growth and P&L assumptions are solved to MWG's official guidance. The monthly phasing still differs, and Bull/Bear scenarios create full-year variance. | N31: Base-case annual revenue and PAT equal Budget by construction: H2 growth and P&L assumptions are solved to MWG's official guidance. The monthly phasing still differs, and Bull/Bear scenarios create full-year variance. | O31: Base-case annual revenue and PAT equal Budget by construction: H2 growth and P&L assumptions are solved to MWG's official guidance. The monthly phasing still differs, and Bull/Bear scenarios create full-year variance.
I32: Base-case annual revenue and PAT equal Budget by construction: H2 growth and P&L assumptions are solved to MWG's official guidance. The monthly phasing still differs, and Bull/Bear scenarios create full-year variance. | J32: Base-case annual revenue and PAT equal Budget by construction: H2 growth and P&L assumptions are solved to MWG's official guidance. The monthly phasing still differs, and Bull/Bear scenarios create full-year variance. | K32: Base-case annual revenue and PAT equal Budget by construction: H2 growth and P&L assumptions are solved to MWG's official guidance. The monthly phasing still differs, and Bull/Bear scenarios create full-year variance. | L32: Base-case annual revenue and PAT equal Budget by construction: H2 growth and P&L assumptions are solved to MWG's official guidance. The monthly phasing still differs, and Bull/Bear scenarios create full-year variance. | M32: Base-case annual revenue and PAT equal Budget by construction: H2 growth and P&L assumptions are solved to MWG's official guidance. The monthly phasing still differs, and Bull/Bear scenarios create full-year variance. | N32: Base-case annual revenue and PAT equal Budget by construction: H2 growth and P&L assumptions are solved to MWG's official guidance. The monthly phasing still differs, and Bull/Bear scenarios create full-year variance. | O32: Base-case annual revenue and PAT equal Budget by construction: H2 growth and P&L assumptions are solved to MWG's official guidance. The monthly phasing still differs, and Bull/Bear scenarios create full-year variance.
I33: Base-case annual revenue and PAT equal Budget by construction: H2 growth and P&L assumptions are solved to MWG's official guidance. The monthly phasing still differs, and Bull/Bear scenarios create full-year variance. | J33: Base-case annual revenue and PAT equal Budget by construction: H2 growth and P&L assumptions are solved to MWG's official guidance. The monthly phasing still differs, and Bull/Bear scenarios create full-year variance. | K33: Base-case annual revenue and PAT equal Budget by construction: H2 growth and P&L assumptions are solved to MWG's official guidance. The monthly phasing still differs, and Bull/Bear scenarios create full-year variance. | L33: Base-case annual revenue and PAT equal Budget by construction: H2 growth and P&L assumptions are solved to MWG's official guidance. The monthly phasing still differs, and Bull/Bear scenarios create full-year variance. | M33: Base-case annual revenue and PAT equal Budget by construction: H2 growth and P&L assumptions are solved to MWG's official guidance. The monthly phasing still differs, and Bull/Bear scenarios create full-year variance. | N33: Base-case annual revenue and PAT equal Budget by construction: H2 growth and P&L assumptions are solved to MWG's official guidance. The monthly phasing still differs, and Bull/Bear scenarios create full-year variance. | O33: Base-case annual revenue and PAT equal Budget by construction: H2 growth and P&L assumptions are solved to MWG's official guidance. The monthly phasing still differs, and Bull/Bear scenarios create full-year variance.
I34: Base-case annual revenue and PAT equal Budget by construction: H2 growth and P&L assumptions are solved to MWG's official guidance. The monthly phasing still differs, and Bull/Bear scenarios create full-year variance. | J34: Base-case annual revenue and PAT equal Budget by construction: H2 growth and P&L assumptions are solved to MWG's official guidance. The monthly phasing still differs, and Bull/Bear scenarios create full-year variance. | K34: Base-case annual revenue and PAT equal Budget by construction: H2 growth and P&L assumptions are solved to MWG's official guidance. The monthly phasing still differs, and Bull/Bear scenarios create full-year variance. | L34: Base-case annual revenue and PAT equal Budget by construction: H2 growth and P&L assumptions are solved to MWG's official guidance. The monthly phasing still differs, and Bull/Bear scenarios create full-year variance. | M34: Base-case annual revenue and PAT equal Budget by construction: H2 growth and P&L assumptions are solved to MWG's official guidance. The monthly phasing still differs, and Bull/Bear scenarios create full-year variance. | N34: Base-case annual revenue and PAT equal Budget by construction: H2 growth and P&L assumptions are solved to MWG's official guidance. The monthly phasing still differs, and Bull/Bear scenarios create full-year variance. | O34: Base-case annual revenue and PAT equal Budget by construction: H2 growth and P&L assumptions are solved to MWG's official guidance. The monthly phasing still differs, and Bull/Bear scenarios create full-year variance.

Sheet 08_Working_Capital
A1: Working Capital & Cash Conversion Cycle | B1: Working Capital & Cash Conversion Cycle | C1: Working Capital & Cash Conversion Cycle | D1: Working Capital & Cash Conversion Cycle | E1: Working Capital & Cash Conversion Cycle
A2: 2024A/2025A balances are reported. 2026F uses revenue, COGS and explicit DSO/DIO/DPO assumptions. | B2: 2024A/2025A balances are reported. 2026F uses revenue, COGS and explicit DSO/DIO/DPO assumptions. | C2: 2024A/2025A balances are reported. 2026F uses revenue, COGS and explicit DSO/DIO/DPO assumptions. | D2: 2024A/2025A balances are reported. 2026F uses revenue, COGS and explicit DSO/DIO/DPO assumptions. | E2: 2024A/2025A balances are reported. 2026F uses revenue, COGS and explicit DSO/DIO/DPO assumptions.
A4: Metric | B4: FY2024A | C4: FY2025A | D4: FY2026F | F4: FY2026F assumption | G4: Value
A6: Revenue | B6: 134341.15 | C6: 155928.15 | D6: ='07_Rolling_Forecast'!O16 -> 185000 | F6: DSO | G6: 0.6
A7: COGS | B7: 106841.94 | C7: 124926.27 | D7: =-'07_Rolling_Forecast'!O17 -> 147452 | F7: DIO | G7: 80
A8: Trade receivables | B8: 241.4054 | C8: 253.35884 | D8: =D6/365*$G$6 -> 304.10959 | F8: DPO | G8: 40
A9: Inventory (net) | B9: 22244.676 | C9: 27266.858 | D9: =D7/365*$G$7 -> 32318.247
A10: Trade payables | B10: 9179.6361 | C10: 13113.9 | D10: =D7/365*$G$8 -> 16159.123
A11: Net working capital | B11: =B8+B9-B10 -> 13306.446 | C11: =C8+C9-C10 -> 14406.317 | D11: =D8+D9-D10 -> 16463.233
A12: DSO | B12: =IFERROR(B8/B6*365,0) -> 0.65588964 | C12: =IFERROR(C8/C6*365,0) -> 0.59306789 | D12: =$G$6 -> 0.6
A13: DIO | B13: =IFERROR(B9/B7*365,0) -> 75.993628 | C13: =IFERROR(C9/C7*365,0) -> 79.666217 | D13: =$G$7 -> 80
A14: DPO | B14: =IFERROR(B10/B7*365,0) -> 31.360036 | C14: =IFERROR(C10/C7*365,0) -> 38.315187 | D14: =$G$8 -> 40
A15: Cash conversion cycle | B15: =B12+B13-B14 -> 45.289482 | C15: =C12+C13-C14 -> 41.944097 | D15: =D12+D13-D14 -> 40.6
A16: NWC / Revenue | B16: =IFERROR(B11/B6,0) -> 0.099049661 | C16: =IFERROR(C11/C6,0) -> 0.092390742 | D16: =IFERROR(D11/D6,0) -> 0.088990448
A17: Change in NWC | B17: =0 -> 0 | C17: =C11-B11 -> 1099.8715 | D17: =D11-C11 -> 2056.9157
A20: Definition: NWC = trade receivables + net inventory − trade payables. Retail receivables are structurally low; inventory and supplier terms dominate the cash conversion cycle. Forecast days are analyst assumptions. | B20: Definition: NWC = trade receivables + net inventory − trade payables. Retail receivables are structurally low; inventory and supplier terms dominate the cash conversion cycle. Forecast days are analyst assumptions. | C20: Definition: NWC = trade receivables + net inventory − trade payables. Retail receivables are structurally low; inventory and supplier terms dominate the cash conversion cycle. Forecast days are analyst assumptions. | D20: Definition: NWC = trade receivables + net inventory − trade payables. Retail receivables are structurally low; inventory and supplier terms dominate the cash conversion cycle. Forecast days are analyst assumptions. | E20: Definition: NWC = trade receivables + net inventory − trade payables. Retail receivables are structurally low; inventory and supplier terms dominate the cash conversion cycle. Forecast days are analyst assumptions.
A21: Definition: NWC = trade receivables + net inventory − trade payables. Retail receivables are structurally low; inventory and supplier terms dominate the cash conversion cycle. Forecast days are analyst assumptions. | B21: Definition: NWC = trade receivables + net inventory − trade payables. Retail receivables are structurally low; inventory and supplier terms dominate the cash conversion cycle. Forecast days are analyst assumptions. | C21: Definition: NWC = trade receivables + net inventory − trade payables. Retail receivables are structurally low; inventory and supplier terms dominate the cash conversion cycle. Forecast days are analyst assumptions. | D21: Definition: NWC = trade receivables + net inventory − trade payables. Retail receivables are structurally low; inventory and supplier terms dominate the cash conversion cycle. Forecast days are analyst assumptions. | E21: Definition: NWC = trade receivables + net inventory − trade payables. Retail receivables are structurally low; inventory and supplier terms dominate the cash conversion cycle. Forecast days are analyst assumptions.
A22: Definition: NWC = trade receivables + net inventory − trade payables. Retail receivables are structurally low; inventory and supplier terms dominate the cash conversion cycle. Forecast days are analyst assumptions. | B22: Definition: NWC = trade receivables + net inventory − trade payables. Retail receivables are structurally low; inventory and supplier terms dominate the cash conversion cycle. Forecast days are analyst assumptions. | C22: Definition: NWC = trade receivables + net inventory − trade payables. Retail receivables are structurally low; inventory and supplier terms dominate the cash conversion cycle. Forecast days are analyst assumptions. | D22: Definition: NWC = trade receivables + net inventory − trade payables. Retail receivables are structurally low; inventory and supplier terms dominate the cash conversion cycle. Forecast days are analyst assumptions. | E22: Definition: NWC = trade receivables + net inventory − trade payables. Retail receivables are structurally low; inventory and supplier terms dominate the cash conversion cycle. Forecast days are analyst assumptions.
A23: Definition: NWC = trade receivables + net inventory − trade payables. Retail receivables are structurally low; inventory and supplier terms dominate the cash conversion cycle. Forecast days are analyst assumptions. | B23: Definition: NWC = trade receivables + net inventory − trade payables. Retail receivables are structurally low; inventory and supplier terms dominate the cash conversion cycle. Forecast days are analyst assumptions. | C23: Definition: NWC = trade receivables + net inventory − trade payables. Retail receivables are structurally low; inventory and supplier terms dominate the cash conversion cycle. Forecast days are analyst assumptions. | D23: Definition: NWC = trade receivables + net inventory − trade payables. Retail receivables are structurally low; inventory and supplier terms dominate the cash conversion cycle. Forecast days are analyst assumptions. | E23: Definition: NWC = trade receivables + net inventory − trade payables. Retail receivables are structurally low; inventory and supplier terms dominate the cash conversion cycle. Forecast days are analyst assumptions.

Sheet 09_Management_Dashboard
A1: MWG Management Dashboard — FY2025 Review & FY2026 Outlook | B1: MWG Management Dashboard — FY2025 Review & FY2026 Outlook | C1: MWG Management Dashboard — FY2025 Review & FY2026 Outlook | D1: MWG Management Dashboard — FY2025 Review & FY2026 Outlook | E1: MWG Management Dashboard — FY2025 Review & FY2026 Outlook | F1: MWG Management Dashboard — FY2025 Review & FY2026 Outlook | G1: MWG Management Dashboard — FY2025 Review & FY2026 Outlook | H1: MWG Management Dashboard — FY2025 Review & FY2026 Outlook | I1: MWG Management Dashboard — FY2025 Review & FY2026 Outlook | J1: MWG Management Dashboard — FY2025 Review & FY2026 Outlook | K1: MWG Management Dashboard — FY2025 Review & FY2026 Outlook | L1: MWG Management Dashboard — FY2025 Review & FY2026 Outlook
A2: Executive summary. All outputs are formula-linked; change the scenario on 07_Rolling_Forecast to update FY2026. | B2: Executive summary. All outputs are formula-linked; change the scenario on 07_Rolling_Forecast to update FY2026. | C2: Executive summary. All outputs are formula-linked; change the scenario on 07_Rolling_Forecast to update FY2026. | D2: Executive summary. All outputs are formula-linked; change the scenario on 07_Rolling_Forecast to update FY2026. | E2: Executive summary. All outputs are formula-linked; change the scenario on 07_Rolling_Forecast to update FY2026. | F2: Executive summary. All outputs are formula-linked; change the scenario on 07_Rolling_Forecast to update FY2026. | G2: Executive summary. All outputs are formula-linked; change the scenario on 07_Rolling_Forecast to update FY2026. | H2: Executive summary. All outputs are formula-linked; change the scenario on 07_Rolling_Forecast to update FY2026. | I2: Executive summary. All outputs are formula-linked; change the scenario on 07_Rolling_Forecast to update FY2026. | J2: Executive summary. All outputs are formula-linked; change the scenario on 07_Rolling_Forecast to update FY2026. | K2: Executive summary. All outputs are formula-linked; change the scenario on 07_Rolling_Forecast to update FY2026. | L2: Executive summary. All outputs are formula-linked; change the scenario on 07_Rolling_Forecast to update FY2026. | N2: Month | O2: Actual 2025 | P2: Budget 2025
N3: 45658 | O3: ='05_Monthly_P&L'!C7 -> 12276.935 | P3: ='05_Monthly_P&L'!C24 -> 12066.123
A4: FY2025 Revenue | D4: Revenue vs Budget | G4: FY2025 PAT | J4: PAT vs Budget | N4: 45689 | O4: ='05_Monthly_P&L'!D7 -> 12276.935 | P4: ='05_Monthly_P&L'!D24 -> 12066.123
A5: ='05_Monthly_P&L'!O7 -> 155928.15 | D5: ='06_Variance_Analysis'!E7 -> 0.039520971 | G5: ='05_Monthly_P&L'!O20 -> 7072.6229 | J5: ='06_Variance_Analysis'!E14 -> 0.45827276 | N5: 45717 | O5: ='05_Monthly_P&L'!E7 -> 11581.088 | P5: ='05_Monthly_P&L'!E24 -> 10973.567
N6: 45748 | O6: ='05_Monthly_P&L'!F7 -> 12562.69 | P6: ='05_Monthly_P&L'!F24 -> 12949.881
N7: 45778 | O7: ='05_Monthly_P&L'!G7 -> 12612.764 | P7: ='05_Monthly_P&L'!G24 -> 12506.606
N8: 45809 | O8: ='05_Monthly_P&L'!H7 -> 12444.514 | P8: ='05_Monthly_P&L'!H24 -> 12707.587
A9: FY2026 Scenario | B9: FY2026F Revenue | C9: Plan Achievement | D9: 6M2026 Revenue | E9: % of Plan | F9: Required H2 Growth | N9: 45839 | O9: ='05_Monthly_P&L'!I7 -> 12875.102 | P9: ='05_Monthly_P&L'!I24 -> 12192.853
A10: ='07_Rolling_Forecast'!B3 -> Base | B10: ='07_Rolling_Forecast'!B35 -> 185000 | C10: ='07_Rolling_Forecast'!B37 -> 1 | D10: 95305 | E10: =D10/'03_Master_Data'!F15 -> 0.51516216 | F10: ='07_Rolling_Forecast'!B11 -> 0.087067179 | N10: 45870 | O10: ='05_Monthly_P&L'!J7 -> 13317.896 | P10: ='05_Monthly_P&L'!J24 -> 12757.833
N11: 45901 | O11: ='05_Monthly_P&L'!K7 -> 13659.509 | P11: ='05_Monthly_P&L'!K24 -> 13175.427
N12: 45931 | O12: ='05_Monthly_P&L'!L7 -> 14710.731 | P12: ='05_Monthly_P&L'!L24 -> 12936.483
N13: 45962 | O13: ='05_Monthly_P&L'!M7 -> 13878.777 | P13: ='05_Monthly_P&L'!M24 -> 12220.767
N14: 45992 | O14: ='05_Monthly_P&L'!N7 -> 13731.204 | P14: ='05_Monthly_P&L'!N24 -> 13446.751
N17: Business Unit | O17: Actual | P17: Budget
N18: TGDĐ | O18: ='06_Variance_Analysis'!B20 -> 37255.618 | P18: ='06_Variance_Analysis'!C20 -> 33000
N19: ĐMX | O19: ='06_Variance_Analysis'!B21 -> 68304.05 | P19: ='06_Variance_Analysis'!C21 -> 63000
N20: BHX | O20: ='06_Variance_Analysis'!B22 -> 46782.107 | P20: ='06_Variance_Analysis'!C22 -> 46500
N21: Other | O21: ='06_Variance_Analysis'!B23 -> 3586.37 | P21: ='06_Variance_Analysis'!C23 -> 7500
N24: Month | O24: FY2026 Cum. | P24: Plan run-rate
N25: 46023 | O25: ='07_Rolling_Forecast'!C30 -> 16102 | P25: ='03_Master_Data'!$F$15*1/12 -> 15416.667
N26: 46054 | O26: ='07_Rolling_Forecast'!D30 -> 32204 | P26: ='03_Master_Data'!$F$15*2/12 -> 30833.333
N27: 46082 | O27: ='07_Rolling_Forecast'!E30 -> 46508 | P27: ='03_Master_Data'!$F$15*3/12 -> 46250
N28: 46113 | O28: ='07_Rolling_Forecast'!F30 -> 62496 | P28: ='03_Master_Data'!$F$15*4/12 -> 61666.667
N29: 46143 | O29: ='07_Rolling_Forecast'!G30 -> 79159 | P29: ='03_Master_Data'!$F$15*5/12 -> 77083.333
N30: 46174 | O30: ='07_Rolling_Forecast'!H30 -> 95305 | P30: ='03_Master_Data'!$F$15*6/12 -> 92500
N31: 46204 | O31: ='07_Rolling_Forecast'!I30 -> 109275.99 | P31: ='03_Master_Data'!$F$15*7/12 -> 107916.67
N32: 46235 | O32: ='07_Rolling_Forecast'!J30 -> 123727.46 | P32: ='03_Master_Data'!$F$15*8/12 -> 123333.33
N33: 46266 | O33: ='07_Rolling_Forecast'!K30 -> 138549.62 | P33: ='03_Master_Data'!$F$15*9/12 -> 138750
N34: 46296 | O34: ='07_Rolling_Forecast'!L30 -> 154695.83 | P34: ='03_Master_Data'!$F$15*10/12 -> 154166.67
N35: 46327 | O35: ='07_Rolling_Forecast'!M30 -> 169928.9 | P35: ='03_Master_Data'!$F$15*11/12 -> 169583.33
N36: 46357 | O36: ='07_Rolling_Forecast'!N30 -> 185000 | P36: ='03_Master_Data'!$F$15*12/12 -> 185000
N39: Metric | O39: Achievement
N40: FY2025 Revenue vs Plan | O40: ='05_Monthly_P&L'!O7/'05_Monthly_P&L'!O24 -> 1.039521
N41: FY2025 PAT vs Plan | O41: ='05_Monthly_P&L'!O20/'05_Monthly_P&L'!O37 -> 1.4582728
N42: 6M2026 Revenue vs FY Plan | O42: =D10/'03_Master_Data'!F15 -> 0.51516216
N43: FY2026F Revenue vs Plan | O43: ='07_Rolling_Forecast'!B37 -> 1

Sheet 10_Checks
A1: Checks & Controls | B1: Checks & Controls | C1: Checks & Controls | D1: Checks & Controls | E1: Checks & Controls | F1: Checks & Controls | G1: Checks & Controls | H1: Checks & Controls
A2: MODEL STATUS | B2: =IF(COUNTIF(F6:F21,"FAIL")=0,"PASS","FAIL") -> PASS
A5: Check | B5: Actual | C5: Expected | D5: Difference | E5: Tolerance | F5: Status | G5: Where to fix | H5: Notes
A6: FY2025 revenue ties audited BCTC | B6: ='05_Monthly_P&L'!O7 -> 155928.15 | C6: =155928.145619367 -> 155928.15 | D6: =B6-C6 -> 0 | E6: 0.1 | F6: =IF(ABS(D6)<=E6,"PASS","FAIL") -> PASS | G6: 01_Raw_Actual | H6: Audited FY2025 BCTC
A7: FY2025 PAT ties audited BCTC | B7: ='05_Monthly_P&L'!O20 -> 7072.6229 | C7: =7072.622885875 -> 7072.6229 | D7: =B7-C7 -> 0 | E7: 0.1 | F7: =IF(ABS(D7)<=E7,"PASS","FAIL") -> PASS | G7: 01_Raw_Actual | H7: Audited FY2025 BCTC
A8: FY2025 budget revenue ties guidance | B8: ='05_Monthly_P&L'!O24 -> 150000 | C8: =150000 -> 150000 | D8: =B8-C8 -> 0 | E8: 0.1 | F8: =IF(ABS(D8)<=E8,"PASS","FAIL") -> PASS | G8: 02_Raw_Budget | H8: Official target
A9: FY2025 budget PAT ties guidance | B9: ='05_Monthly_P&L'!O37 -> 4850 | C9: =4850 -> 4850 | D9: =B9-C9 -> 0 | E9: 0.1 | F9: =IF(ABS(D9)<=E9,"PASS","FAIL") -> PASS | G9: 02_Raw_Budget | H9: Official target
A10: Actual mapping completeness | B10: =COUNTIF('01_Raw_Actual'!$J$6:$J$569,"Unmapped") -> 0 | C10: =0 -> 0 | D10: =B10-C10 -> 0 | E10: 0 | F10: =IF(ABS(D10)<=E10,"PASS","FAIL") -> PASS | G10: 04_Account_Mapping | H10: No unmapped account
A11: Budget mapping completeness | B11: =COUNTIF('02_Raw_Budget'!$J$6:$J$869,"Unmapped") -> 0 | C11: =0 -> 0 | D11: =B11-C11 -> 0 | E11: 0 | F11: =IF(ABS(D11)<=E11,"PASS","FAIL") -> PASS | G11: 04_Account_Mapping | H11: No unmapped account
A12: FY2026 Base revenue reaches plan | B12: ='07_Rolling_Forecast'!B35 -> 185000 | C12: =185000 -> 185000 | D12: =B12-C12 -> 0 | E12: 0.1 | F12: =IF(ABS(D12)<=E12,"PASS","FAIL") -> PASS | G12: 07_Rolling_Forecast | H12: Passes in Base scenario
A13: FY2026 guidance PAT assumption | B13: ='03_Master_Data'!F16 -> 9200 | C13: =9200 -> 9200 | D13: =B13-C13 -> 0 | E13: 0.1 | F13: =IF(ABS(D13)<=E13,"PASS","FAIL") -> PASS | G13: 03_Master_Data | H13: Official target
A14: 2025 NWC identity | B14: ='08_Working_Capital'!C11 -> 14406.317 | C14: ='08_Working_Capital'!C8+'08_Working_Capital'!C9-'08_Working_Capital'!C10 -> 14406.317 | D14: =B14-C14 -> 0 | E14: 0.1 | F14: =IF(ABS(D14)<=E14,"PASS","FAIL") -> PASS | G14: 08_Working_Capital | H14: AR + Inventory - AP
A15: Power Query objects | B15: 5 | C15: 5 | D15: =B15-C15 -> 0 | E15: 0 | F15: =IF(ABS(D15)<=E15,"PASS","FAIL") -> PASS | G15: 03_Master_Data | H15: Updated after query creation
A16: PivotTable object | B16: 1 | C16: 1 | D16: =B16-C16 -> 0 | E16: 0 | F16: =IF(ABS(D16)<=E16,"PASS","FAIL") -> PASS | G16: 06_Variance_Analysis | H16: Updated after PivotTable creation
A17: Source register populated | B17: =COUNTA('11_Sources'!A6:A15) -> 10 | C17: =10 -> 10 | D17: =B17-C17 -> 0 | E17: 0 | F17: =IF(ABS(D17)<=E17,"PASS","FAIL") -> PASS | G17: 11_Sources | H17: Minimum ten source rows
A18: FY2024 revenue ties audited BCTC | B18: ='05A_YoY_Analysis'!B7 -> 134341.15 | C18: =134341.152848802 -> 134341.15 | D18: =B18-C18 -> 0 | E18: 0.1 | F18: =IF(ABS(D18)<=E18,"PASS","FAIL") -> PASS | G18: 01_Raw_Actual | H18: Audited FY2024 BCTC
A19: FY2024 PAT ties audited BCTC | B19: ='05A_YoY_Analysis'!B14 -> 3733.2882 | C19: =3733.28822872 -> 3733.2882 | D19: =B19-C19 -> 0 | E19: 0.1 | F19: =IF(ABS(D19)<=E19,"PASS","FAIL") -> PASS | G19: 01_Raw_Actual | H19: Audited FY2024 BCTC
A20: FY2026 budget revenue ties guidance | B20: ='07A_Forecast_Variance'!C16 -> 185000 | C20: =185000 -> 185000 | D20: =B20-C20 -> 0 | E20: 0.1 | F20: =IF(ABS(D20)<=E20,"PASS","FAIL") -> PASS | G20: 02_Raw_Budget | H20: Official FY2026 target
A21: FY2026 budget PAT ties guidance | B21: ='07A_Forecast_Variance'!C23 -> 9200 | C21: =9200 -> 9200 | D21: =B21-C21 -> 0 | E21: 0.1 | F21: =IF(ABS(D21)<=E21,"PASS","FAIL") -> PASS | G21: 02_Raw_Budget | H21: Official FY2026 target

Sheet 11_Sources
A1: Sources & Audit Trail | B1: Sources & Audit Trail | C1: Sources & Audit Trail | D1: Sources & Audit Trail | E1: Sources & Audit Trail | F1: Sources & Audit Trail | G1: Sources & Audit Trail | H1: Sources & Audit Trail | I1: Sources & Audit Trail | J1: Sources & Audit Trail
A2: Full local paths and URLs are stored once here. Source dates and allocation limitations are explicit. | B2: Full local paths and URLs are stored once here. Source dates and allocation limitations are explicit. | C2: Full local paths and URLs are stored once here. Source dates and allocation limitations are explicit. | D2: Full local paths and URLs are stored once here. Source dates and allocation limitations are explicit. | E2: Full local paths and URLs are stored once here. Source dates and allocation limitations are explicit. | F2: Full local paths and URLs are stored once here. Source dates and allocation limitations are explicit. | G2: Full local paths and URLs are stored once here. Source dates and allocation limitations are explicit. | H2: Full local paths and URLs are stored once here. Source dates and allocation limitations are explicit. | I2: Full local paths and URLs are stored once here. Source dates and allocation limitations are explicit. | J2: Full local paths and URLs are stored once here. Source dates and allocation limitations are explicit.
A5: SourceID | B5: Item | C5: Units | D5: Period | E5: Source Type | F5: Source Name | G5: Ref | H5: Local Path | I5: URL | J5: Notes
A6: SRC-001 | B6: Q1 2025 consolidated P&L | C6: VND bn | D6: 3M2025 | E6: Company filing | F6: MWG BCTC Hợp nhất Q1/2025 | G6: P&L page 5 | H6: C:\topdown\FP&A\Thêm\bs 2025 q1.pdf | I6: https://mwg.vn/bao-cao | J6: Actual Q1 totals
A7: SRC-002 | B7: H1 2025 consolidated P&L | C7: VND bn | D7: 6M2025 | E7: Company filing | F7: MWG BCTC Hợp nhất Bán niên 2025 | G7: P&L page 7 | H7: C:\topdown\FP&A\2025\MWG_BCTC_Hop_Nhat_Ban_Nien_2025.pdf | I7: https://mwg.vn/bao-cao | J7: Reviewed by EY
A8: SRC-003 | B8: 9M 2025 consolidated P&L | C8: VND bn | D8: 9M2025 | E8: Company filing | F8: MWG BCTC Hợp nhất Q3/2025 | G8: P&L pages 5-6 | H8: C:\topdown\FP&A\2025\MWG_BCTC_Hop_Nhat_Q3_2025.pdf | I8: https://mwg.vn/bao-cao | J8: Actual 9M totals
A9: SRC-004 | B9: FY2025 consolidated P&L and balance sheet | C9: VND bn | D9: FY2025 | E9: Company filing | F9: MWG audited consolidated FS 2025 | G9: BS/P&L pages 5-7 | H9: C:\topdown\FP&A\2025\bs 2025.pdf | I9: https://mwg.vn/bao-cao | J9: Audited year-end actual
A10: SRC-005 | B10: FY2024 consolidated P&L and balance sheet | C10: VND bn | D10: FY2024 | E10: Company filing | F10: MWG audited consolidated FS 2024 | G10: BS/P&L pages 5-7 | H10: C:\topdown\FP&A\2024\bs_2024 hopnhat.pdf | I10: https://mwg.vn/bao-cao | J10: Audited prior-year actual
A11: SRC-006 | B11: Monthly cumulative revenue and mix | C11: VND bn / % | D11: 2M-12M2025 | E11: Company update | F11: MWG monthly business updates 2025 | G11: Cover revenue chart | H11: C:\topdown\FP&A\KQKD 2025 | I11: https://mwg.vn/bao-cao | J11: Monthly deltas derived from cumulative values
A12: SRC-007 | B12: 6M2026 reported revenue and mix | C12: VND bn / % | D12: 2M-6M2026 | E12: Company update | F12: MWG monthly business updates 2026 | G12: Cover revenue chart | H12: C:\topdown\FP&A\KQKD 2026 | I12: https://mwg.vn/bao-cao | J12: Jan/Feb split 50/50 because only 2M cumulative is published
A13: SRC-008 | B13: FY2025 revenue and PAT targets | C13: VND bn | D13: FY2025 | E13: Company guidance | F13: MWG Định hướng kinh doanh 2025 | G13: Target table | H13: C:\topdown\FP&A\KQKD 2025\1afd6ca76c5da1a22766cb5c53a76e97.pdf | I13: https://mwg.vn/bao-cao | J13: Revenue 150,000; PAT 4,850
A14: SRC-009 | B14: FY2026 revenue, PAT and segment direction | C14: VND bn / % | D14: FY2026 | E14: Company guidance | F14: MWG Định hướng kinh doanh 2026 | G14: Target and segment pages | H14: C:\topdown\FP&A\KQKD 2026\3329b29508569abd63f80d72a4c26368.pdf | I14: https://mwg.vn/bao-cao | J14: Revenue 185,000; PAT 9,200
A15: SRC-010 | B15: Analyst allocation method | C15: Method | D15: Model-wide | E15: Analyst assumption | F15: FP&A modelling convention | G15: Read_Me limitation | H15: Workbook logic | J15: Quarterly costs allocated by revenue; budget calibrated to guidance

Sheet 12_Pivot_Source
A1: Version | B1: Year | C1: Period | D1: BusinessUnit | E1: AccountCategory | F1: Amount_VNDm
A2: Actual | B2: 2025 | C2: 45658 | D2: TGDĐ | E2: Revenue | F2: 2823.695
A3: Actual | B3: 2025 | C3: 45658 | D3: TGDĐ | E3: COGS | F3: -2261.0332
A4: Actual | B4: 2025 | C4: 45658 | D4: TGDĐ | E4: Selling Expense | F4: -344.06425
A5: Actual | B5: 2025 | C5: 45658 | D5: TGDĐ | E5: G&A | F5: -94.912504
A6: Actual | B6: 2025 | C6: 45658 | D6: TGDĐ | E6: Finance Income | F6: 54.176066
A7: Actual | B7: 2025 | C7: 45658 | D7: TGDĐ | E7: Finance Expense | F7: -26.492296
A8: Actual | B8: 2025 | C8: 45658 | D8: TGDĐ | E8: JV Profit/(Loss) | F8: 0.24457004
A9: Actual | B9: 2025 | C9: 45658 | D9: TGDĐ | E9: Other Net | F9: -0.43317627
A10: Actual | B10: 2025 | C10: 45658 | D10: TGDĐ | E10: Tax Expense | F10: -30.227881
A11: Actual | B11: 2025 | C11: 45658 | D11: ĐMX | E11: Revenue | F11: 5635.1132
A12: Actual | B12: 2025 | C12: 45658 | D12: ĐMX | E12: COGS | F12: -4512.2357
A13: Actual | B13: 2025 | C13: 45658 | D13: ĐMX | E13: Selling Expense | F13: -686.63256
... A865: Budget | B865: 2025 | C865: 45992 | D865: Other | E865: Tax Expense | F865: -5.4347286

Sheet 13_Query_M_Code
A1: Power Query M Code — Audit Copy | B1: Power Query M Code — Audit Copy | C1: Power Query M Code — Audit Copy
A2: The live query objects are created in the workbook. This sheet keeps a readable audit copy of their logic. | B2: The live query objects are created in the workbook. This sheet keeps a readable audit copy of their logic. | C2: The live query objects are created in the workbook. This sheet keeps a readable audit copy of their logic.
A5: Query | B5: Purpose | C5: M Code
A6: qActual_Clean | B6: Clean/type Actual table | C6: let Source = Excel.CurrentWorkbook(){[Name="tbl_Actual_Input"]}[Content], Typed = Table.TransformColumnTypes(Source,{{"Period", type date},{"Year", Int64.Type},{"Month", Int64.Type},{"Amount_VNDm", type number}}), Filtered = Table.SelectRows(Typed, each [AccountCode] <> null) in Filtered
A7: qBudget_Clean | B7: Clean/type Budget table | C7: let Source = Excel.CurrentWorkbook(){[Name="tbl_Budget_Input"]}[Content], Typed = Table.TransformColumnTypes(Source,{{"Period", type date},{"Year", Int64.Type},{"Month", Int64.Type},{"Amount_VNDm", type number}}), Filtered = Table.SelectRows(Typed, each [AccountCode] <> null) in Filtered
A8: qAccount_Map | B8: Type account map | C8: let Source = Excel.CurrentWorkbook(){[Name="tbl_Account_Map"]}[Content], Typed = Table.TransformColumnTypes(Source,{{"AccountCode", type text},{"P&L Category", type text},{"CostNature", type text}}) in Typed
A9: qActual_Mapped | B9: Merge Actual with mapping | C9: let A = qActual_Clean, M = qAccount_Map, Joined = Table.NestedJoin(A,{"AccountCode"},M,{"AccountCode"},"Map",JoinKind.LeftOuter), Expanded = Table.ExpandTableColumn(Joined,"Map",{"P&L Category","CostNature"},{"PQ_Category","PQ_CostNature"}) in Expanded
A10: qCombined_Actual_Budget | B10: Append Actual and Budget | C10: let A = Table.AddColumn(qActual_Clean,"Version",each "Actual"), B = Table.AddColumn(qBudget_Clean,"Version",each "Budget"), Combined = Table.Combine({A,B}) in Combined

Sheet 14_Formula_Guide
A1: Hướng dẫn công thức và logic FP&A | B1: Hướng dẫn công thức và logic FP&A | C1: Hướng dẫn công thức và logic FP&A | D1: Hướng dẫn công thức và logic FP&A | E1: Hướng dẫn công thức và logic FP&A | F1: Hướng dẫn công thức và logic FP&A | G1: Hướng dẫn công thức và logic FP&A
A2: Học theo mẫu công thức lặp lại trong workbook; không cần ghi nhớ từng ô riêng lẻ. | B2: Học theo mẫu công thức lặp lại trong workbook; không cần ghi nhớ từng ô riêng lẻ. | C2: Học theo mẫu công thức lặp lại trong workbook; không cần ghi nhớ từng ô riêng lẻ. | D2: Học theo mẫu công thức lặp lại trong workbook; không cần ghi nhớ từng ô riêng lẻ. | E2: Học theo mẫu công thức lặp lại trong workbook; không cần ghi nhớ từng ô riêng lẻ. | F2: Học theo mẫu công thức lặp lại trong workbook; không cần ghi nhớ từng ô riêng lẻ. | G2: Học theo mẫu công thức lặp lại trong workbook; không cần ghi nhớ từng ô riêng lẻ.
A4: Luồng tư duy của workbook | B4: Luồng tư duy của workbook | C4: Luồng tư duy của workbook | D4: Luồng tư duy của workbook | E4: Luồng tư duy của workbook | F4: Luồng tư duy của workbook | G4: Luồng tư duy của workbook
A5: 1. Raw data | B5: 2. Mapping | C5: 3. Monthly P&L | D5: 4. Variance | E5: 5. Forecast | F5: 6. Working capital | G5: 7. Dashboard & Checks
A6: Actual/Budget theo tháng | B6: AccountCode → P&L line | C6: SUMIFS tổng hợp | D6: Actual − Budget | E6: Actual YTD + phần còn lại | F6: AR + Inventory − AP | G6: KPI, chart và kiểm soát
A7: 01/02 | B7: 04 | C7: 05 | D7: 06 | E7: 07 | F7: 08 | G7: 09/10
A9: Cách học hiệu quả | B9: Cách học hiệu quả | C9: Cách học hiệu quả | D9: Cách học hiệu quả | E9: Cách học hiệu quả | F9: Cách học hiệu quả | G9: Cách học hiệu quả
A10: Đọc cột “Ý nghĩa” trước, sau đó trace ví dụ tại sheet được ghi trong cột “Dùng ở đâu”. Tiếp theo sang 15_Practice_Lab, tự nhập công thức vào ô màu vàng/chữ xanh và chỉ mở 16_Answer_Key sau khi đã thử. Hãy luyện theo logic: xác định đầu vào → chọn hàm → khóa tham chiếu đúng → kiểm tra kết quả.
A13: Danh mục công thức và kỹ năng dùng trong bài | B13: Danh mục công thức và kỹ năng dùng trong bài | C13: Danh mục công thức và kỹ năng dùng trong bài | D13: Danh mục công thức và kỹ năng dùng trong bài | E13: Danh mục công thức và kỹ năng dùng trong bài | F13: Danh mục công thức và kỹ năng dùng trong bài | G13: Danh mục công thức và kỹ năng dùng trong bài
A14: Công thức / kỹ năng | B14: Ý nghĩa | C14: Mẫu cú pháp | D14: Ví dụ trong model | E14: Dùng ở đâu | F14: Lỗi hay gặp | G14: Bài tập
A15: Relative reference | B15: Tham chiếu thay đổi khi copy công thức. | C15: =B7-C7 | D15: Variance = Actual − Budget | E15: 06_Variance_Analysis | F15: Khóa nhầm hàng/cột nên copy sai. | G15: 9
A16: Absolute reference ($) | B16: Giữ cố định assumption khi copy. | C16: =C16*(1+$B$11) | D16: Forecast dùng cùng một growth assumption | E16: 07_Rolling_Forecast | F16: Quên dấu $ làm assumption trôi. | G16: 14
A17: Cross-sheet link | B17: Lấy dữ liệu từ một sheet khác. | C17: ='05_Monthly_P&L'!O7 | D17: Dashboard lấy KPI từ model | E17: 09_Management_Dashboard | F17: Gõ lại số thay vì tạo link. | G17: 6
A18: SUM | B18: Cộng một dải liên tục. | C18: =SUM(C7:N7) | D18: Cộng 12 tháng thành FY | E18: 05_Monthly_P&L | F18: Cộng thiếu tháng hoặc chèn hardcode. | G18: 1
A19: SUMIF | B19: Tổng theo một điều kiện. | C19: =SUMIF(B6:B13,"TGDĐ",D6:D13) | D19: Tổng theo một BU | E19: Bài tập minh họa | F19: Criteria range và sum range lệch kích thước. | G19: 2
A20: SUMIFS | B20: Tổng theo nhiều điều kiện. | C20: =SUMIFS(Amount,Year,2025,Code,"REV") | D20: Revenue theo năm/tháng/BU/account | E20: 05/05A/06/07A | F20: Sai dấu của chi phí hoặc dùng nhầm cột. | G20: 2-3
A21: XLOOKUP | B21: Map mã tài khoản sang category/nature. | C21: =XLOOKUP(Code,MapCode,Category,"Unmapped",0) | D21: AccountCode → P&L Category | E21: 01/02_Raw, 04_Mapping | F21: Không dùng exact match hoặc thiếu fallback. | G21: 4
A22: IF | B22: Rẽ nhánh theo điều kiện. | C22: =IF(Variance>=0,"F","U") | D22: Đánh dấu favorable/unfavorable | E22: 06_Variance_Analysis | F22: Không xét bản chất income/expense. | G22: 11-12
A23: IFERROR | B23: Thay lỗi bằng kết quả an toàn. | C23: =IFERROR(Numerator/Denominator,0) | D23: Margin và variance % | E23: 05/06/07/08 | F23: Dùng để che lỗi logic thay vì xử lý nguyên nhân. | G23: 5, 8, 10
A24: ABS | B24: Lấy trị tuyệt đối để so sánh/tính %. | C24: =Variance/ABS(Budget) | D24: Variance % và tolerance check | E24: 06/07A/10 | F24: Mất ý nghĩa dấu nếu dùng ABS sai chỗ. | G24: 10, 18
... A37: Chart linked to cells | B37: Biểu đồ tự đổi khi nguồn công thức đổi. | C37: Chart source = helper range | D37: 4 dashboard charts | E37: 09_Management_Dashboard | F37: Hardcode series hoặc phủ chart lên dữ liệu. | G37: Manual 4

Sheet 15_Practice_Lab
A1: Practice Lab — Tự nhập công thức và chấm tự động | B1: Practice Lab — Tự nhập công thức và chấm tự động | C1: Practice Lab — Tự nhập công thức và chấm tự động | D1: Practice Lab — Tự nhập công thức và chấm tự động | E1: Practice Lab — Tự nhập công thức và chấm tự động | F1: Practice Lab — Tự nhập công thức và chấm tự động | G1: Practice Lab — Tự nhập công thức và chấm tự động | H1: Practice Lab — Tự nhập công thức và chấm tự động | I1: Practice Lab — Tự nhập công thức và chấm tự động | J1: Practice Lab — Tự nhập công thức và chấm tự động | K1: Practice Lab — Tự nhập công thức và chấm tự động | L1: Practice Lab — Tự nhập công thức và chấm tự động | M1: Practice Lab — Tự nhập công thức và chấm tự động | N1: Practice Lab — Tự nhập công thức và chấm tự động
A2: Chỉ nhập công thức vào cột E của bảng bài tập. Vùng luyện tập độc lập với model core nên không thể làm hỏng báo cáo. | B2: Chỉ nhập công thức vào cột E của bảng bài tập. Vùng luyện tập độc lập với model core nên không thể làm hỏng báo cáo. | C2: Chỉ nhập công thức vào cột E của bảng bài tập. Vùng luyện tập độc lập với model core nên không thể làm hỏng báo cáo. | D2: Chỉ nhập công thức vào cột E của bảng bài tập. Vùng luyện tập độc lập với model core nên không thể làm hỏng báo cáo. | E2: Chỉ nhập công thức vào cột E của bảng bài tập. Vùng luyện tập độc lập với model core nên không thể làm hỏng báo cáo. | F2: Chỉ nhập công thức vào cột E của bảng bài tập. Vùng luyện tập độc lập với model core nên không thể làm hỏng báo cáo. | G2: Chỉ nhập công thức vào cột E của bảng bài tập. Vùng luyện tập độc lập với model core nên không thể làm hỏng báo cáo. | H2: Chỉ nhập công thức vào cột E của bảng bài tập. Vùng luyện tập độc lập với model core nên không thể làm hỏng báo cáo. | I2: Chỉ nhập công thức vào cột E của bảng bài tập. Vùng luyện tập độc lập với model core nên không thể làm hỏng báo cáo. | J2: Chỉ nhập công thức vào cột E của bảng bài tập. Vùng luyện tập độc lập với model core nên không thể làm hỏng báo cáo. | K2: Chỉ nhập công thức vào cột E của bảng bài tập. Vùng luyện tập độc lập với model core nên không thể làm hỏng báo cáo. | L2: Chỉ nhập công thức vào cột E của bảng bài tập. Vùng luyện tập độc lập với model core nên không thể làm hỏng báo cáo. | M2: Chỉ nhập công thức vào cột E của bảng bài tập. Vùng luyện tập độc lập với model core nên không thể làm hỏng báo cáo. | N2: Chỉ nhập công thức vào cột E của bảng bài tập. Vùng luyện tập độc lập với model core nên không thể làm hỏng báo cáo.
A3: Scenario | B3: Base | D3: Tiến độ | E3: =COUNTIF(G25:G43,"ĐÚNG")&"/19 đúng" -> 0/19 đúng
A5: Mini transaction dataset | B5: Mini transaction dataset | C5: Mini transaction dataset | D5: Mini transaction dataset | H5: Account mapping | I5: Account mapping | J5: Account mapping | L5: Scenario table | M5: Scenario table | N5: Scenario table
A6: Period | B6: Business Unit | C6: AccountCode | D6: Amount (VND bn) | H6: AccountCode | I6: Category | J6: Nature | L6: Scenario | M6: Growth | N6: Gross Margin
A7: 46023 | B7: TGDĐ | C7: REV | D7: 1200 | H7: REV | I7: Revenue | J7: Income | L7: Bear | M7: -0.05 | N7: 0.18
A8: 46023 | B8: TGDĐ | C8: COGS | D8: -900 | H8: COGS | I8: COGS | J8: Expense | L8: Base | M8: 0 | N8: 0.2
A9: 46023 | B9: TGDĐ | C9: SELL | D9: -120 | H9: SELL | I9: Selling Expense | J9: Expense | L9: Bull | M9: 0.05 | N9: 0.22
A10: 46023 | B10: ĐMX | C10: REV | D10: 1800 | H10: GA | I10: G&A | J10: Expense
A11: 46023 | B11: ĐMX | C11: COGS | D11: -1350
A12: 46023 | B12: BHX | C12: REV | D12: 1500 | H12: Inputs for finance exercises | I12: Inputs for finance exercises | J12: Inputs for finance exercises
A13: 46023 | B13: BHX | C13: COGS | D13: -1100 | H13: Budget Revenue | I13: 4300
A14: 46023 | B14: BHX | C14: SELL | D14: -180 | H14: Actual Revenue | I14: 4500
H15: Revenue | I15: 4500
H16: Actual COGS | I16: -3350
H17: Budget COGS | I17: -3200
H18: Accounts Receivable | I18: 400
H19: Inventory | I19: 900
H20: YTD Actual | I20: 2500
H21: H2 Forecast | I21: 2200
H22: Accounts Payable | I22: 350
A23: Bài tập công thức | B23: Bài tập công thức | C23: Bài tập công thức | D23: Bài tập công thức | E23: Bài tập công thức | F23: Bài tập công thức | G23: Bài tập công thức | H23: Tolerance | I23: 0.1
A24: # | B24: Level | C24: Skill | D24: Yêu cầu | E24: Nhập công thức tại đây | F24: Đơn vị | G24: Chấm tự động | H24: Gợi ý
A25: 1 | B25: Basic | C25: SUM | D25: Tính tổng toàn bộ Amount trong mini dataset. | F25: VND bn | G25: =IFERROR(IF(E25="","CHƯA LÀM",IF(ABS(E25-'16_Answer_Key'!C6)<=0.0001,"ĐÚNG","THỬ LẠI")),"THỬ LẠI") -> CHƯA LÀM | H25: SUM một dải liên tục.
A26: 2 | B26: Basic | C26: SUMIFS | D26: Tính Revenue của TGDĐ. | F26: VND bn | G26: =IFERROR(IF(E26="","CHƯA LÀM",IF(ABS(E26-'16_Answer_Key'!C7)<=0.0001,"ĐÚNG","THỬ LẠI")),"THỬ LẠI") -> CHƯA LÀM | H26: Dùng 2 điều kiện: BU và AccountCode.
A27: 3 | B27: Basic | C27: SUMIFS | D27: Tính tổng Revenue của tất cả BU. | F27: VND bn | G27: =IFERROR(IF(E27="","CHƯA LÀM",IF(ABS(E27-'16_Answer_Key'!C8)<=0.0001,"ĐÚNG","THỬ LẠI")),"THỬ LẠI") -> CHƯA LÀM | H27: Điều kiện AccountCode = REV.
A28: 4 | B28: Basic | C28: XLOOKUP | D28: Map mã REV sang Category từ bảng mapping. | F28: Text | G28: =IFERROR(IF(E28="","CHƯA LÀM",IF(E28='16_Answer_Key'!C9,"ĐÚNG","THỬ LẠI")),"THỬ LẠI") -> CHƯA LÀM | H28: Exact match; fallback = Unmapped.
A29: 5 | B29: Basic | C29: IFERROR + XLOOKUP | D29: Map mã TAX; nếu không tìm thấy trả về Unmapped. | F29: Text | G29: =IFERROR(IF(E29="","CHƯA LÀM",IF(E29='16_Answer_Key'!C10,"ĐÚNG","THỬ LẠI")),"THỬ LẠI") -> CHƯA LÀM | H29: Bọc XLOOKUP bằng IFERROR.
A30: 6 | B30: Basic | C30: Cross-sheet link | D30: Link FY2025 Revenue từ 05_Monthly_P&L ô O7. | F30: VND bn | G30: =IFERROR(IF(E30="","CHƯA LÀM",IF(ABS(E30-'16_Answer_Key'!C11)<=0.0001,"ĐÚNG","THỬ LẠI")),"THỬ LẠI") -> CHƯA LÀM | H30: Tên sheet luôn đặt trong dấu nháy đơn.
A31: 7 | B31: FP&A | C31: Gross Profit | D31: Tính Gross Profit từ Revenue và Actual COGS. | F31: VND bn | G31: =IFERROR(IF(E31="","CHƯA LÀM",IF(ABS(E31-'16_Answer_Key'!C12)<=0.0001,"ĐÚNG","THỬ LẠI")),"THỬ LẠI") -> CHƯA LÀM | H31: COGS đã mang dấu âm.
A32: 8 | B32: FP&A | C32: Gross Margin | D32: Tính Gross Margin từ kết quả Gross Profit. | F32: % | G32: =IFERROR(IF(E32="","CHƯA LÀM",IF(ABS(E32-'16_Answer_Key'!C13)<=0.0001,"ĐÚNG","THỬ LẠI")),"THỬ LẠI") -> CHƯA LÀM | H32: Dùng IFERROR để tránh chia cho 0.
A33: 9 | B33: FP&A | C33: Variance amount | D33: Tính Actual Revenue − Budget Revenue. | F33: VND bn | G33: =IFERROR(IF(E33="","CHƯA LÀM",IF(ABS(E33-'16_Answer_Key'!C14)<=0.0001,"ĐÚNG","THỬ LẠI")),"THỬ LẠI") -> CHƯA LÀM | H33: Actual trừ Budget.
A34: 10 | B34: FP&A | C34: Variance % | D34: Tính Revenue variance % trên Budget. | F34: % | G34: =IFERROR(IF(E34="","CHƯA LÀM",IF(ABS(E34-'16_Answer_Key'!C15)<=0.0001,"ĐÚNG","THỬ LẠI")),"THỬ LẠI") -> CHƯA LÀM | H34: Chia variance cho ABS(Budget).
A35: 11 | B35: FP&A | C35: F/U — Income | D35: Đánh dấu F/U cho Revenue variance. | F35: Text | G35: =IFERROR(IF(E35="","CHƯA LÀM",IF(E35='16_Answer_Key'!C16,"ĐÚNG","THỬ LẠI")),"THỬ LẠI") -> CHƯA LÀM | H35: Revenue cao hơn Budget là favorable.
A36: 12 | B36: FP&A | C36: F/U — Expense | D36: Đánh dấu F/U cho COGS variance bằng favorable sign −1. | F36: Text | G36: =IFERROR(IF(E36="","CHƯA LÀM",IF(E36='16_Answer_Key'!C17,"ĐÚNG","THỬ LẠI")),"THỬ LẠI") -> CHƯA LÀM | H36: Expense thấp hơn Budget mới favorable.
A37: 13 | B37: Forecast | C37: Scenario lookup | D37: Lấy Growth theo Scenario đang chọn tại B3. | F37: % | G37: =IFERROR(IF(E37="","CHƯA LÀM",IF(ABS(E37-'16_Answer_Key'!C18)<=0.0001,"ĐÚNG","THỬ LẠI")),"THỬ LẠI") -> CHƯA LÀM | H37: XLOOKUP B3 trong bảng scenario.
A38: 14 | B38: Forecast | C38: Scenario forecast | D38: Forecast Revenue = Revenue × (1 + scenario growth). | F38: VND bn | G38: =IFERROR(IF(E38="","CHƯA LÀM",IF(ABS(E38-'16_Answer_Key'!C19)<=0.0001,"ĐÚNG","THỬ LẠI")),"THỬ LẠI") -> CHƯA LÀM | H38: Khóa vùng scenario bằng dấu $.
A39: 15 | B39: Forecast | C39: Rolling forecast | D39: Tính FY Forecast = YTD Actual + H2 Forecast. | F39: VND bn | G39: =IFERROR(IF(E39="","CHƯA LÀM",IF(ABS(E39-'16_Answer_Key'!C20)<=0.0001,"ĐÚNG","THỬ LẠI")),"THỬ LẠI") -> CHƯA LÀM | H39: Không forecast lại phần YTD actual.
A40: 16 | B40: Working capital | C40: AR days | D40: Tính AR days = AR / Revenue × 365. | F40: Ngày | G40: =IFERROR(IF(E40="","CHƯA LÀM",IF(ABS(E40-'16_Answer_Key'!C21)<=0.0001,"ĐÚNG","THỬ LẠI")),"THỬ LẠI") -> CHƯA LÀM | H40: Dùng IFERROR.
A41: 17 | B41: Working capital | C41: Net Working Capital | D41: Tính NWC = AR + Inventory − AP. | F41: VND bn | G41: =IFERROR(IF(E41="","CHƯA LÀM",IF(ABS(E41-'16_Answer_Key'!C22)<=0.0001,"ĐÚNG","THỬ LẠI")),"THỬ LẠI") -> CHƯA LÀM | H41: Giữ đúng dấu AP.
A42: 18 | B42: Controls | C42: Tolerance check | D42: So sánh tổng Revenue mini dataset với input Revenue; trả PASS/FAIL. | F42: Text | G42: =IFERROR(IF(E42="","CHƯA LÀM",IF(E42='16_Answer_Key'!C23,"ĐÚNG","THỬ LẠI")),"THỬ LẠI") -> CHƯA LÀM | H42: ABS(delta) <= Tolerance.
A43: 19 | B43: Controls | C43: COUNTIF | D43: Đếm số check PASS tại 10_Checks!F6:F21. | F43: Checks | G43: =IFERROR(IF(E43="","CHƯA LÀM",IF(ABS(E43-'16_Answer_Key'!C24)<=0.0001,"ĐÚNG","THỬ LẠI")),"THỬ LẠI") -> CHƯA LÀM | H43: COUNTIF theo text PASS.
A46: Bài tập thao tác Excel — tự đánh dấu sau khi hoàn thành | B46: Bài tập thao tác Excel — tự đánh dấu sau khi hoàn thành | C46: Bài tập thao tác Excel — tự đánh dấu sau khi hoàn thành | D46: Bài tập thao tác Excel — tự đánh dấu sau khi hoàn thành | E46: Bài tập thao tác Excel — tự đánh dấu sau khi hoàn thành | F46: Bài tập thao tác Excel — tự đánh dấu sau khi hoàn thành | G46: Bài tập thao tác Excel — tự đánh dấu sau khi hoàn thành | H46: Bài tập thao tác Excel — tự đánh dấu sau khi hoàn thành
A47: # | B47: Skill | C47: Bài tập thao tác | D47: Bằng chứng cần thấy | E47: Trạng thái
A48: 1 | B48: Data Validation | C48: Đổi Scenario tại B3 qua Bear/Base/Bull. | D48: Dropdown chỉ cho phép 3 lựa chọn. | E48: Chưa làm
A49: 2 | B49: Power Query | C49: Mở Queries & Connections và Refresh All. | D49: Thấy 5 query/connection và không báo lỗi. | E49: Chưa làm
A50: 3 | B50: PivotTable | C50: Tại 06_Variance_Analysis, đổi filter AccountCategory. | D50: Pivot cập nhật theo category đã chọn. | E50: Chưa làm
A51: 4 | B51: Formula Auditing | C51: Sau khi làm bài 14, dùng Trace Precedents tại E38. | D51: Mũi tên đi tới Revenue và bảng scenario. | E51: Chưa làm
A52: 5 | B52: Chart | C52: Đổi Scenario ở 07_Rolling_Forecast và xem dashboard. | D52: KPI/chart forecast thay đổi theo input. | E52: Chưa làm

Sheet 16_Answer_Key
A1: Đáp án và giải thích — mở sau khi đã tự làm | B1: Đáp án và giải thích — mở sau khi đã tự làm | C1: Đáp án và giải thích — mở sau khi đã tự làm | D1: Đáp án và giải thích — mở sau khi đã tự làm | E1: Đáp án và giải thích — mở sau khi đã tự làm | F1: Đáp án và giải thích — mở sau khi đã tự làm
A2: Cột B là công thức gợi ý; cột C tính kết quả động từ dữ liệu trong Practice Lab. | B2: Cột B là công thức gợi ý; cột C tính kết quả động từ dữ liệu trong Practice Lab. | C2: Cột B là công thức gợi ý; cột C tính kết quả động từ dữ liệu trong Practice Lab. | D2: Cột B là công thức gợi ý; cột C tính kết quả động từ dữ liệu trong Practice Lab. | E2: Cột B là công thức gợi ý; cột C tính kết quả động từ dữ liệu trong Practice Lab. | F2: Cột B là công thức gợi ý; cột C tính kết quả động từ dữ liệu trong Practice Lab.
A3: Đừng học thuộc công thức. Hãy tự trả lời bốn câu: đầu vào ở đâu, điều kiện nào cần lọc, tham chiếu nào phải khóa, và kết quả cần kiểm tra bằng cách nào. | B3: Đừng học thuộc công thức. Hãy tự trả lời bốn câu: đầu vào ở đâu, điều kiện nào cần lọc, tham chiếu nào phải khóa, và kết quả cần kiểm tra bằng cách nào. | C3: Đừng học thuộc công thức. Hãy tự trả lời bốn câu: đầu vào ở đâu, điều kiện nào cần lọc, tham chiếu nào phải khóa, và kết quả cần kiểm tra bằng cách nào. | D3: Đừng học thuộc công thức. Hãy tự trả lời bốn câu: đầu vào ở đâu, điều kiện nào cần lọc, tham chiếu nào phải khóa, và kết quả cần kiểm tra bằng cách nào. | E3: Đừng học thuộc công thức. Hãy tự trả lời bốn câu: đầu vào ở đâu, điều kiện nào cần lọc, tham chiếu nào phải khóa, và kết quả cần kiểm tra bằng cách nào. | F3: Đừng học thuộc công thức. Hãy tự trả lời bốn câu: đầu vào ở đâu, điều kiện nào cần lọc, tham chiếu nào phải khóa, và kết quả cần kiểm tra bằng cách nào.
A5: # | B5: Công thức gợi ý | C5: Kết quả đúng | D5: Vì sao dùng công thức này | E5: Lỗi thường gặp | F5: Áp dụng trong model
A6: 1 | B6: =SUM(D7:D14) | C6: =SUM('15_Practice_Lab'!$D$7:$D$14) -> 850 | D6: Cộng toàn bộ Amount trong một dải liên tục. | E6: Bỏ sót hàng cuối. | F6: FY total trong 05_Monthly_P&L
A7: 2 | B7: =SUMIFS(D7:D14,B7:B14,"TGDĐ",C7:C14,"REV") | C7: =SUMIFS('15_Practice_Lab'!$D$7:$D$14,'15_Practice_Lab'!$B$7:$B$14,"TGDĐ",'15_Practice_Lab'!$C$7:$C$14,"REV") -> 1200 | D7: SUMIFS lọc đồng thời BU và account. | E7: Criteria range không cùng kích thước. | F7: Variance by BU
A8: 3 | B8: =SUMIFS(D7:D14,C7:C14,"REV") | C8: =SUMIFS('15_Practice_Lab'!$D$7:$D$14,'15_Practice_Lab'!$C$7:$C$14,"REV") -> 4500 | D8: Chỉ cộng các dòng Revenue. | E8: Cộng cả expense làm revenue bị thấp. | F8: Monthly revenue roll-up
A9: 4 | B9: =XLOOKUP("REV",H7:H10,I7:I10,"Unmapped",0) | C9: =_xlfn.XLOOKUP("REV",'15_Practice_Lab'!$H$7:$H$10,'15_Practice_Lab'!$I$7:$I$10,"Unmapped",0) -> Revenue | D9: Exact-match mapping từ code sang category. | E9: Thiếu fallback Unmapped. | F9: 01/02 Raw Mapping
A10: 5 | B10: =IFERROR(XLOOKUP("TAX",H7:H10,I7:I10),"Unmapped") | C10: =IFERROR(_xlfn.XLOOKUP("TAX",'15_Practice_Lab'!$H$7:$H$10,'15_Practice_Lab'!$I$7:$I$10),"Unmapped") -> Unmapped | D10: IFERROR xử lý code chưa tồn tại trong mapping. | E10: Dùng IFERROR để che lỗi range sai. | F10: Mapping completeness
A11: 6 | B11: ='05_Monthly_P&L'!O7 | C11: ='05_Monthly_P&L'!O7 -> 155928.15 | D11: Link trực tiếp, không gõ lại output. | E11: Hardcode số 155,928.1. | F11: Dashboard links
A12: 7 | B12: =I15+I16 | C12: ='15_Practice_Lab'!$I$15+'15_Practice_Lab'!$I$16 -> 1150 | D12: COGS đang âm nên Gross Profit = Revenue + COGS. | E12: Revenue − COGS làm lợi nhuận tăng sai. | F12: P&L subtotal
A13: 8 | B13: =IFERROR((I15+I16)/I15,0) | C13: =IFERROR(C12/'15_Practice_Lab'!$I$15,0) -> 0.25555556 | D13: Margin là profit chia revenue. | E13: Chia cho COGS. | F13: Gross Margin
A14: 9 | B14: =I14-I13 | C14: ='15_Practice_Lab'!$I$14-'15_Practice_Lab'!$I$13 -> 200 | D14: Quy ước variance = Actual − Budget. | E14: Đảo Budget − Actual. | F14: Variance amount
A15: 10 | B15: =(I14-I13)/ABS(I13) | C15: =IFERROR(C14/ABS('15_Practice_Lab'!$I$13),0) -> 0.046511628 | D15: ABS giữ mẫu số dương để dấu đến từ variance. | E15: Chia cho Actual thay vì Budget. | F15: Variance %
A16: 11 | B16: =IF(I14-I13>=0,"F","U") | C16: =IF(C14>=0,"F","U") -> F | D16: Revenue cao hơn budget là favorable. | E16: Cho rằng logic này áp dụng cho expense. | F16: Revenue F/U
A17: 12 | B17: =IF((I16-I17)*-1>=0,"F","U") | C17: =IF(('15_Practice_Lab'!$I$16-'15_Practice_Lab'!$I$17)*-1>=0,"F","U") -> F | D17: Expense dùng favorable sign −1. | E17: Nhìn variance dương là tốt cho mọi account. | F17: Cost-nature logic
A18: 13 | B18: =XLOOKUP($B$3,$L$7:$L$9,$M$7:$M$9) | C18: =_xlfn.XLOOKUP('15_Practice_Lab'!$B$3,'15_Practice_Lab'!$L$7:$L$9,'15_Practice_Lab'!$M$7:$M$9) -> 0 | D18: Một selector điều khiển assumption scenario. | E18: Không khóa vùng lookup. | F18: Rolling Forecast
A19: 14 | B19: =$I$15*(1+XLOOKUP($B$3,$L$7:$L$9,$M$7:$M$9)) | C19: ='15_Practice_Lab'!$I$15*(1+C18) -> 4500 | D19: Forecast nối base revenue với growth của scenario. | E19: Hardcode 5% trong công thức. | F19: Scenario forecast
A20: 15 | B20: =$I$20+$I$21 | C20: ='15_Practice_Lab'!$I$20+'15_Practice_Lab'!$I$21 -> 4700 | D20: Rolling forecast giữ actual YTD và chỉ forecast phần còn lại. | E20: Forecast lại cả năm. | F20: FY2026F
A21: 16 | B21: =IFERROR($I$18/$I$15*365,0) | C21: =IFERROR('15_Practice_Lab'!$I$18/'15_Practice_Lab'!$I$15*365,0) -> 32.444444 | D21: Quy đổi AR thành số ngày doanh thu. | E21: Dùng doanh thu không cùng kỳ. | F21: Working Capital
A22: 17 | B22: =$I$18+$I$19-$I$22 | C22: ='15_Practice_Lab'!$I$18+'15_Practice_Lab'!$I$19-'15_Practice_Lab'!$I$22 -> 950 | D22: NWC = AR + Inventory − AP. | E22: Cộng AP thay vì trừ. | F22: NWC schedule
A23: 18 | B23: =IF(ABS(SUMIFS(D7:D14,C7:C14,"REV")-$I$15)<=$I$23,"PASS","FAIL") | C23: =IF(ABS(C8-'15_Practice_Lab'!$I$15)<='15_Practice_Lab'!$I$23,"PASS","FAIL") -> PASS | D23: Tolerance tránh fail vì sai số làm tròn nhỏ. | E23: Tolerance quá rộng. | F23: Checks
A24: 19 | B24: =COUNTIF('10_Checks'!F6:F21,"PASS") | C24: =COUNTIF('10_Checks'!$F$6:$F$21,"PASS") -> 16 | D24: Đếm số kiểm soát đang PASS. | E24: Range thiếu dòng check. | F24: Read_Me model status
